Workbook
Name NativeTimeline_Order_Date: #N/A
Name Slicer_Category: #N/A
Name Slicer_Region: #N/A

Sheet Sales_Data
A1: Order_ID | B1: Customer_ID | C1: Product_ID | D1: Order_Date | E1: Delivery_Date | F1: Customer_Name | G1: Gender | H1: DOB | I1: City | J1: Region | K1: Category | L1: Product_Name | M1: Quantity | N1: Unit_Price | O1: Discount_% | P1: Sales | Q1: Rating | R1: Payment_Mode | S1: Salesperson | T1: Email | U1: Phone | V1: Order_Status
A2: ORD10001 | B2: C008 | C2: P202 | D2: 18/09/2025 | E2: 22/09/2025 | F2: Kavya Nair | G2: Female | H2: 01/08/1976 | I2: Hyderabad | J2: South | K2: Home Appliances | L2: Iron | M2: 4 | N2: 2200 | O2: 10 | P2: 7920 | Q2: 4 | R2: Cash | S2: Ritika | T2: KAvya.nair@company.com | U2: 9431429797 | V2: Completed
A3: ORD10002 | B3: C008 | C3: P104 | D3: 27/04/2025 | E3: 04/05/2025 | F3: Kavya Nair | G3: Female | H3: 16/10/2000 | I3: Delhi | J3: North | K3: Electronics | L3: Monitor | M3: 17 | N3: 12000 | O3: 10 | P3: 183600 | Q3: 1 | R3: NetBanking | S3: Rahul | T3: kavya.nair@company.com | U3: 9129865339 | V3: Completed
A4: ORD10003 | B4: C010 | C4: P101 | D4: 03/09/2025 | E4: 14/09/2025 | F4: pooja shah | G4: Female | H4: 16/09/1994 | I4: Bengaluru | J4: South | K4: Electronics | L4: Laptop | M4: 5 | N4: 55000 | O4: 5 | P4: 261250 | Q4: 3 | R4: NetBanking | S4: Aisha | T4: pooja.shah@company.com | U4: 9380975626 | V4: Pending
A5: ORD10002 | B5: C008 | C5: P202 | D5: 21/03/2026 | E5: 02/04/2026 | F5: Kavya Nair | G5: Female | H5: 07/03/2004 | I5: Bengaluru | J5: South | K5: Home Appliances | L5: Iron | M5: 5 | N5: 2200 | O5: 5 | P5: 10450 | Q5: 5 | R5: NetBanking | S5: Aisha | T5: kavya.nair@company.com | U5: 9600261125 | V5: Cancelled
A6: ORD10005 | B6: C009 | C6: P103 | D6: 27/09/2025 | E6: 07/10/2025 | F6: Mohit Verma | G6: Male | H6: 13/04/1976 | I6: Delhi | J6: North | K6: Electronics | L6: Keyboard | M6: 8 | N6: 1200 | O6: 5 | P6: 9120 | Q6: 2 | R6: Card | S6: Aisha | T6: mohit.verma@company.com | U6: 9724635978 | V6: Pending
A7: ORD10006 | B7: C007 | C7: P202 | D7: 04/01/2026 | E7: 12/01/2026 | F7: arjun Rao | G7: Male | H7: 07/02/1988 | I7: Hyderabad | J7: South | K7: Home Appliances | L7: Iron | M7: 4 | N7: 2200 | O7: 0 | P7: 8800 | Q7: 1 | R7: UPI | S7: Ritika | T7: arjun.rao@company.com | U7: 9780584905 | V7: Completed
A8: ORD10007 | B8: C008 | C8: P201 | D8: 31/02/2025 | E8: 25/02/2026 | F8: Kavya Nair | G8: Female | H8: 20/03/2003 | I8: Hyderabad | J8: South | K8: Home Appliances | L8: Mixer | M8: 2 | N8: 3500 | O8: 5 | P8: 6650 | Q8: 1 | R8: UPI | S8: Ritika | T8: kavya.nair@company.com | U8: 9958252176 | V8: Completed
A9: ORD10008 | B9: C002 | C9: P104 | D9: 13/04/2025 | E9: 19/04/2025 | F9: Priya Patel | G9: Female | H9: 07/03/1995 | I9: Mumbai | J9: West | K9: Electronics | L9: Monitor | M9: 14 | N9: 12000 | O9: 15 | P9: 142800 | Q9: 4 | R9: NetBanking | S9: Ritika | T9: priYa.patel@company.com | U9: 9705521654 | V9: Completed
A10: ORD10009 | B10: C008 | C10: P104 | D10: 31/01/2026 | E10: 02/02/2026 | F10: kavya Nair | G10: Female | H10: 06/04/1997 | I10: Pune | J10: West | K10: Electronics | L10: Monitor | M10: 4 | N10: 12000 | O10: 15 | P10: 40800 | Q10: 4 | R10: UPI | S10: Neha | T10: kavya.nair@company.com | U10: 9588041011 | V10: Completed
A11: ORD10010 | B11: C002 | C11: P301 | D11: 25/03/2025 | E11: 27/03/2025 | F11: Priya Patel | G11: Female | H11: 07/01/1990 | I11: Mumbai | J11: West | K11: Stationery | L11: Notebook | M11: 6 | N11: 60 | O11: 0 | P11: 360 | Q11: 4 | R11: Card | S11: Neha | T11: PRiya.patel@company.com | U11: 9340540608 | V11: Completed
A12: ORD10011 | B12: C003 | C12: P202 | D12: 19/09/2025 | E12: 23/09/2025 | F12: Rohit Singh | G12: Male | H12: 10/05/1982 | I12: Delhi | J12: North | K12: Home Appliances | L12: Iron | M12: -3 | N12: 2200 | O12: 0 | P12: 35200 | Q12: 2 | R12: Card | S12: Rahul | T12: rohit.singh@company.com | U12: 9521710321 | V12: Pending
A13: ORD10012 | B13: C008 | C13: P201 | D13: 08/03/2025 | E13: 15/03/2025 | F13: Kavya Nair | G13: Female | H13: 23/01/1982 | I13: Ahmedabad | J13: West | K13: Home Appliances | L13: Mixer | M13: 10 | N13: 3500 | O13: 5 | P13: 33250 | Q13: 5 | R13: Card | S13: Aisha | T13: kavya.nair@company.com | U13: 9123535241 | V13: Cancelled
... A39: ORD10038 | B39: C006 | C39: P201 | D39: 08/03/2026 | E39: 20/03/2026 | F39: Sneha Joshi | G39: Female | H39: 21/06/1980 | I39: Delhi | J39: North | K39: Home Appliances | L39: Mixer | M39: 20 | N39: 3500 | O39: 10 | P39: 63000 | Q39: 3 | R39: Card | S39: Rahul | T39: sneha.joshi@company.com | U39: 9283578533 | V39: Cancelled
A40: ORD10039 | B40: C008 | C40: P302 | D40: 13/02/2025 | E40: 19/02/2025 | F40: Kavya Nair | G40: Female | H40: 17/06/1979 | I40: Pune | J40: West | K40: Stationery | L40: Pen | M40: 5 | N40: 1200 | O40: 0 | P40: 100 | Q40: 1 | R40: Cash | S40: Rahul | T40: kavya.nair@company.com | U40: 9963005771 | V40: Cancelled
A41: ORD10040 | B41: C010 | C41: P203 | D41: 05/10/2025 | E41: 15/10/2025 | F41: Pooja Shah | G41: Female | H41: 18/06/1992 | I41: Mumbai | J41: West | K41: Home Appliances | L41: Microwave | M41: 20 | N41: 8500 | O41: 0 | P41: 170000 | Q41: 1 | R41: UPI | S41: Neha | T41: pooja.shah@company.com | U41: 9484632635 | V41: Cancelled
A42: ORD10041 | B42: C007 | C42: P301 | D42: 10/02/2026 | E42: 12/02/2026 | F42: Arjun Rao | G42: Male | H42: 06/06/1994 | I42: Bengaluru | J42: South | K42: Stationery | L42: Notebook | M42: 8 | N42: 60 | O42: 15 | P42: 408 | Q42: 5 | R42: UPI | S42: Rahul | T42: arjun.rao@company.com | U42: 9276319484 | V42: Pending
A43: ORD10042 | B43: C010 | C43: P201 | D43: 04/06/2025 | E43: 16/06/2025 | F43: Pooja Shah | G43: Female | H43: 22/09/1988 | I43: Pune | J43: West | K43: Home Appliances | L43: Mixer | M43: 8 | N43: 3500 | O43: 5 | P43: 26600 | Q43: 1 | R43: Card | S43: Neha | T43: pooja.shah@company.com | U43: 9619034852 | V43: Pending
A44: ORD10043 | B44: C009 | C44: P203 | D44: 08/02/2026 | E44: 14/02/2026 | F44: Mohit Verma | G44: Male | H44: 14/07/2001 | I44: Jaipur | J44: North | K44: Home Appliances | L44: Microwave | M44: 1 | N44: 8500 | O44: 0 | P44: 8500 | Q44: 2 | R44: Card | S44: Neha | T44: mohit.verma@company.com | U44: 9636416962 | V44: Pending
A45: ORD10044 | B45: C001 | C45: P303 | D45: 30/03/2025 | E45: 31/03/2025 | F45: amit Sharma | G45: Male | H45: 09/08/1991 | I45: Pune | J45: West | K45: Stationery | L45: Marker | M45: 8 | N45: 45 | O45: 15 | P45: 306 | Q45: 2 | R45: Card | S45: Aisha | T45: amit.sharma@company.com | U45: 9357133880 | V45: Completed
A46: ORD10045 | B46: C006 | C46: P202 | D46: 25/04/2025 | E46: 28/04/2025 | F46: Sneha Joshi | G46: Female | H46: 21/10/1988 | I46: Pune | J46: West | K46: Home Appliances | L46: Iron | M46: 16 | N46: 2200 | O46: 5 | P46: 33440 | Q46: 5 | R46: Card | S46: Aisha | T46: sneha.joshi@company.com | U46: 9575210324 | V46: Cancelled
A47: ORD10046 | B47: C009 | C47: P201 | D47: 13/10/2025 | E47: 23/10/2025 | F47: Mohit Verma | G47: Male | H47: 19/11/2002 | I47: Bengaluru | J47: South | K47: Home Appliances | L47: Mixer | M47: 19 | N47: 3500 | O47: 20 | P47: 53200 | Q47: 3 | R47: Cash | S47: Karan | T47: mohit.verma@company.com | U47: 9276080204 | V47: Cancelled
A48: ORD10047 | B48: C006 | C48: P102 | D48: 11/10/2025 | E48: 14/10/2025 | F48: Sneha Joshi | G48: Female | H48: 06/07/2000 | I48: Pune | J48: West | K48: Electronics | L48: Mouse | M48: 15 | N48: 700 | O48: 15 | P48: 8925 | Q48: 4 | R48: UPI | S48: Neha | T48: sneha.joshicompany.com | U48: 9856624471 | V48: Completed
A49: ORD10048 | B49: C006 | C49: P102 | D49: 27/11/2025 | E49: 03/12/2025 | F49: Sneha Joshi | G49: Female | H49: 26/11/1998 | I49: Jaipur | J49: North | K49: Electronics | L49: Mouse | M49: 19 | N49: 700 | O49: 20 | P49: 10640 | Q49: 1 | R49: Cash | S49: Neha | T49: sneha.joshi@company.com | U49: 9238141322 | V49: Completed
A50: ORD10049 | B50: C009 | C50: P104 | D50: 19/04/2026 | F50: Mohit Verma | G50: Male | H50: 03/06/1996 | I50: Delhi | J50: North | K50: Electronics | L50: Monitor | M50: 19 | N50: 12000 | O50: 0 | P50: 228000 | Q50: 1 | R50: NetBanking | S50: Aisha | T50: mohit.verma@company.com | U50: 9890380030 | V50: Completed
A51: ORD10050 | B51: C004 | C51: P103 | D51: 19/04/2026 | E51: 21/04/2026 | F51: Anita Gupta | G51: Female | H51: 15/03/1987 | I51: Pune | J51: West | K51: Electronics | L51: Keyboard | M51: 6 | N51: 1200 | O51: 5 | P51: 6840 | Q51: 2 | R51: Cash | S51: Ritika | T51: anita.gupta@company.com | U51: 9495893170 | V51: Pending
A52: ORD10051 | B52: C010 | C52: P202 | D52: 28/03/2025 | E52: 07/04/2025 | F52: POoja Shah | G52: Female | H52: 20/02/1979 | I52: Bengaluru | J52: South | K52: Home Appliances | L52: Iron | M52: 7 | N52: 2200 | O52: 15 | P52: 13090 | Q52: 1 | R52: UPI | S52: Aisha | T52: pooja.shah@company.com | U52: 9485166307 | V52: Completed
A53: ORD10052 | B53: C002 | C53: P301 | D53: 25/08/2025 | E53: 28/08/2025 | F53: Priya Patel | G53: Female | H53: 09/08/2000 | I53: Jaipur | J53: North | K53: Stationery | L53: Notebook | M53: 8 | N53: 60 | O53: 10 | P53: 432 | Q53: 5 | R53: Card | S53: Aisha | T53: priya.patel@company.com | U53: 9924709648 | V53: Cancelled
A54: ORD10053 | B54: C005 | C54: P101 | D54: 19/08/2025 | E54: 23/08/2025 | F54: Vikas Mehta | G54: Male | H54: 17/01/1976 | I54: Kolkata | J54: East | K54: Electronics | L54: Laptop | M54: 12 | N54: 55000 | O54: 5 | P54: 627000 | Q54: 2 | R54: UPI | S54: Rahul | T54: vikas.mehta@company.com | U54: 9350554626 | V54: Pending
A55: ORD10054 | B55: C008 | C55: P102 | D55: 27/07/2025 | E55: 05/08/2025 | F55: Kavya Nair | G55: Female | H55: 04/04/1975 | I55: Jaipur | J55: North | K55: Electronics | L55: Mouse | M55: 3 | N55: 700 | O55: 0 | P55: 2100 | Q55: 3 | R55: Card | S55: Karan | T55: kavya.nair@company.com | U55: 9743295580 | V55: Cancelled
A56: ORD10055 | B56: C003 | C56: P301 | D56: 21/02/2025 | E56: 26/02/2025 | F56: RoHit Singh | G56: Male | H56: 11/12/1976 | I56: Ahmedabad | J56: West | K56: Stationery | L56: Notebook | M56: 19 | N56: 60 | O56: 15 | P56: 969 | Q56: 4 | R56: Card | S56: Rahul | T56: rohit.singh@company.com | U56: 9822926495 | V56: Cancelled
A57: ORD10056 | B57: C001 | C57: P301 | D57: 10/08/2025 | E57: 11/08/2025 | F57: Amit Sharma | G57: Male | H57: 03/12/1979 | I57: Jaipur | J57: North | K57: Stationery | L57: Notebook | M57: 9 | N57: 60 | O57: 20 | P57: 432 | Q57: 1 | R57: NetBanking | S57: Neha | T57: amit.sharma@company.com | U57: 9518298190 | V57: Pending
A58: ORD10057 | B58: C001 | C58: P102 | D58: 24/03/2026 | E58: 30/03/2026 | F58: Amit Sharma | G58: Male | H58: 27/12/1978 | I58: Bengaluru | J58: South | K58: Electronics | L58: Mouse | M58: 6 | N58: 700 | O58: 0 | P58: 4200 | Q58: 4 | R58: UPI | S58: Rahul | T58: amit.sharmcompany.com | U58: 9366223547 | V58: Cancelled
A59: ORD10058 | B59: C003 | C59: P303 | D59: 13/03/2026 | E59: 19/03/2026 | F59: Rohit Singh | G59: Male | H59: 15/04/1975 | I59: Delhi | J59: North | K59: Stationery | L59: Marker | M59: 18 | N59: 45 | O59: 5 | P59: 769.5 | Q59: 1 | R59: Card | S59: Aisha | T59: rohit.singh@company.com | U59: 9701988524 | V59: Pending
A60: ORD10059 | B60: C007 | C60: P302 | D60: 15/06/2025 | E60: 26/06/2025 | F60: Arjun Rao | G60: Male | H60: 19/12/1988 | I60: Jaipur | J60: North | K60: Stationery | L60: Pen | M60: 8 | N60: 20 | O60: 5 | P60: 152 | Q60: 1 | R60: Card | S60: Ritika | T60: arjun.rao@company.com | U60: 9836327649 | V60: completed
A61: ORD10060 | B61: C005 | C61: P102 | D61: 05/03/2025 | E61: 06/03/2025 | F61: Vikas Mehta | G61: Male | H61: 07/03/1979 | I61: Jaipur | J61: North | K61: Electronics | L61: Mouse | M61: 8 | N61: 700 | O61: 10 | P61: 5040 | Q61: 1 | R61: NetBanking | S61: Aisha | T61: Vikas.mehta@company.com | U61: 9261800516 | V61: Cancelled
A62: ORD10061 | B62: C008 | C62: P302 | D62: 09/04/2026 | E62: 19/04/2026 | F62: Kavya Nair | G62: Female | H62: 17/12/2003 | I62: Delhi | J62: North | K62: Stationery | L62: Pen | M62: 7 | N62: 20 | O62: 15 | P62: 119 | Q62: 5 | R62: Card | S62: Rahul | T62: kavya.nair@company.com | U62: 9950802015 | V62: Completed
... A74: ORD10073 | B74: C008 | C74: P103 | D74: 13/12/2025 | E74: 23/12/2025 | F74: Kavya Nair | G74: Female | H74: 22/09/1981 | I74: Jaipur | J74: North | K74: Electronics | L74: Keyboard | M74: 1 | N74: 1200 | O74: 5 | P74: 1140 | Q74: 3 | R74: UPI | S74: Aisha | T74: kavya.nair@company.com | U74: 9808988530 | V74: Cancelled
A75: ORD10074 | B75: C010 | C75: P202 | D75: 04/02/2026 | E75: 16/02/2026 | F75: Pooja Shah | G75: Female | H75: 20/06/1980 | J75: South | K75: Home Appliances | L75: Iron | M75: 1 | N75: 2200 | O75: 15 | P75: 1870 | Q75: 4 | R75: Card | S75: Aisha | T75: pooja.shah@company.com | U75: 9286410494 | V75: Completed
A76: ORD10075 | B76: C003 | C76: P103 | D76: 26/01/2026 | E76: 28/01/2026 | F76: Rohit Singh | G76: Male | H76: 02/11/1982 | I76: Pune | J76: West | K76: Electronics | L76: Keyboard | M76: 3 | N76: 1200 | O76: 10 | P76: 3240 | Q76: 5 | R76: Cash | S76: Rahul | T76: rohit.singh@company.com | U76: 9311555196 | V76: Completed
A77: ORD10076 | B77: C008 | C77: P201 | D77: 27/06/2025 | E77: 07/07/2025 | F77: Kavya Nair | G77: Female | H77: 10/01/1980 | I77: Bengaluru | J77: South | K77: Home Appliances | L77: Mixer | M77: 10 | N77: 3500 | O77: 20 | P77: 28000 | Q77: 5 | R77: Card | S77: Ritika | T77: kavya.nair@company.com | U77: 9101810266 | V77: Completed
A78: ORD10077 | B78: C007 | C78: P102 | D78: 17/03/2026 | E78: 19/03/2026 | F78: Arjun Rao | G78: Male | H78: 27/04/1981 | I78: Delhi | J78: North | K78: Electronics | L78: Mouse | M78: 18 | N78: 700 | O78: 5 | P78: 11970 | Q78: 3 | R78: Card | S78: Neha | T78: arjun.rao@company.com | U78: 9464556593 | V78: Cancelled
A79: ORD10078 | B79: C005 | C79: P102 | D79: 09/06/2025 | E79: 18/06/2025 | F79: Vikas Mehta | G79: Male | H79: 12/03/1985 | I79: Bengaluru | J79: South | K79: Electronics | L79: Mouse | M79: 12 | N79: 700 | O79: 15 | P79: 7140 | Q79: 2 | R79: UPI | S79: Rahul | T79: vikas.mehta@company.com | U79: 9338278358 | V79: Completed
A80: ORD10079 | B80: C009 | C80: P103 | D80: 15/11/2025 | E80: 16/11/2025 | F80: Mohit Verma | G80: Male | H80: 15/03/1999 | I80: Mumbai | J80: West | K80: Electronics | L80: Keyboard | M80: 8 | N80: 1200 | O80: 0 | P80: 9600 | Q80: 4 | R80: Card | S80: Rahul | T80: mohit.verma@company.com | U80: 9621410770 | V80: Pending
A81: ORD10080 | B81: C003 | C81: P301 | D81: 06/11/2025 | E81: 10/11/2025 | F81: Rohit Singh | G81: Male | H81: 07/07/1983 | I81: Pune | J81: West | K81: Stationery | L81: Notebook | M81: 2 | N81: 60 | O81: 0 | P81: 120 | Q81: 2 | R81: UPI | S81: Rahul | T81: rohit.singh@company.com | U81: 9981333189 | V81: Completed
A82: ORD10081 | B82: C001 | C82: P303 | D82: 01/01/2025 | E82: 07/01/2025 | F82: Amit Sharma | G82: Male | H82: 06/03/1989 | I82: Pune | J82: West | K82: Stationery | L82: Marker | M82: 10 | N82: 45 | O82: 15 | P82: 382.5 | Q82: 3 | R82: NetBanking | S82: Ritika | T82: amit.sharma@company.com | U82: 9723450355 | V82: Cancelled
A83: ORD10082 | B83: C005 | C83: P201 | D83: 25/04/2026 | E83: 03/05/2026 | F83: Vikas Mehta | G83: Male | H83: 20/06/1982 | I83: Kolkata | J83: East | K83: Home Appliances | L83: Mixer | M83: 12 | N83: 3500 | O83: 5 | P83: 39900 | Q83: 3 | R83: NetBanking | S83: Aisha | T83: vikas.mehta@company.com | U83: 9886243907 | V83: Pending
A84: ORD10083 | B84: C003 | C84: P301 | D84: 19/09/2025 | E84: 27/09/2025 | F84: Rohit Singh | G84: Male | H84: 23/06/2001 | I84: Mumbai | J84: West | K84: Stationery | L84: Notebook | M84: 2 | N84: 60 | O84: 15 | P84: 102 | Q84: 1 | R84: UPI | S84: Neha | T84: rohit.singh@company.com | U84: 9473931904 | V84: Completed
A85: ORD10084 | B85: C003 | C85: P103 | D85: 18/03/2025 | E85: 21/03/2025 | F85: Rohit Singh | G85: Male | H85: 19/07/1983 | I85: Hyderabad | J85: South | K85: Electronics | L85: Keyboard | M85: 18 | N85: 1200 | O85: 15 | P85: 18360 | Q85: 3 | R85: Card | S85: Neha | T85: rohit.singh@company.com | U85: 9287159610 | V85: Pending
A86: ORD10085 | B86: C008 | C86: P104 | D86: 30/10/2025 | E86: 31/10/2025 | F86: Kavya Nair | G86: Female | H86: 24/03/1993 | I86: Mumbai | J86: West | K86: Electronics | L86: Monitor | M86: 18 | N86: 12000 | O86: 15 | P86: 183600 | Q86: 2 | R86: Cash | S86: Rahul | T86: kavya.nair@company.com | U86: 9876513858 | V86: Completed
A87: ORD10086 | B87: C007 | C87: P302 | D87: 31/10/2025 | E87: 11/11/2025 | F87: Arjun Rao | G87: Male | H87: 10/05/1995 | I87: Ahmedabad | J87: West | K87: Stationery | L87: Pen | M87: 7 | N87: 20 | O87: 0 | P87: 140 | Q87: 2 | R87: Card | S87: Ritika | T87: arjun.rao@company.com | U87: 9237400853 | V87: Cancelled
... A119: ORD10118 | B119: C001 | C119: P303 | D119: 31/05/2025 | E119: 11/06/2025 | F119: Amit Sharma | G119: Male | H119: 07/09/1995 | I119: Pune | J119: West | K119: Stationery | L119: Marker | M119: 16 | N119: 45 | O119: 0 | P119: 720 | Q119: 1 | R119: NetBanking | S119: Aisha | T119: amit.sharma@company.com | U119: 9807154421 | V119: Completed
A120: ORD10119 | B120: C009 | C120: P103 | D120: 30/05/2025 | E120: 02/06/2025 | F120: Mohit Verma | G120: Male | H120: 08/03/1988 | I120: Ahmedabad | J120: West | K120: Electronics | L120: Keyboard | M120: Ten | N120: 1200 | O120: 15 | P120: 7140 | Q120: 4 | R120: UPI | S120: Karan | T120: mohit.verma@company.com | U120: 9919834000 | V120: Pending
A121: ORD10120 | B121: C002 | C121: P104 | D121: 19/08/2025 | E121: 30/08/2025 | F121: Priya Patel | G121: Female | H121: 07/07/1989 | I121: Jaipur | J121: North | K121: Electronics | L121: Monitor | M121: 14 | N121: 12000 | O121: 15 | P121: 142800 | Q121: 2 | R121: NetBanking | S121: Aisha | T121: priya.patel@company.com | U121: 9739798818 | V121: Pending
A122: ORD10121 | B122: C003 | C122: P203 | D122: 14/12/2025 | E122: 16/12/2025 | F122: Rohit Singh | G122: Male | H122: 11/11/1993 | I122: Pune | J122: West | K122: Home Appliances | L122: Microwave | M122: 8 | N122: 8500 | O122: 20 | P122: 54400 | Q122: 3 | R122: Card | S122: Rahul | T122: rohit.singh@company.com | U122: 9208625306 | V122: Completed
A123: ORD10122 | B123: C007 | C123: P303 | D123: 31/01/2026 | E123: 10/02/2026 | F123: Arjun Rao | G123: Male | H123: 01/02/2000 | I123: Bengaluru | J123: South | K123: Stationery | L123: Marker | M123: 3 | N123: 45 | O123: 0 | P123: 135 | Q123: 4 | R123: UPI | S123: Aisha | T123: arjun.rao@company.com | U123: 9970178536 | V123: Cancelled
A124: ORD10123 | B124: C001 | C124: P102 | D124: 03/01/2026 | E124: 04/01/2026 | F124: Amit Sharma | G124: Male | H124: 22/06/1986 | I124: Jaipur | J124: North | K124: Electronics | L124: Mouse | M124: 13 | N124: 700 | O124: 5 | P124: 8645 | Q124: 3 | R124: Card | S124: Neha | T124: amit.sharma@company.com | U124: 9633745195 | V124: Pending
A125: ORD10124 | B125: C004 | C125: P103 | D125: 20/10/2025 | E125: 26/10/2025 | F125: Anita Gupta | G125: Female | H125: 16/02/1986 | I125: Mumbai | J125: West | K125: Electronics | L125: Keyboard | M125: 14 | N125: 1200 | O125: 20 | P125: 13440 | Q125: 5 | R125: NetBanking | S125: Aisha | T125: anita.gupta@company.com | U125: 9922102053 | V125: Completed
A126: ORD10125 | B126: C002 | C126: P303 | D126: 11/05/2025 | E126: 21/05/2025 | F126: Priya Patel | G126: Female | H126: 18/09/1991 | I126: Delhi | J126: North | K126: Stationery | L126: Marker | M126: 2 | N126: 45 | O126: 5 | P126: 85.5 | Q126: 3 | R126: UPI | S126: Ritika | T126: priya.patel@company.com | U126: 9135963930 | V126: Cancelled
A127: ORD10126 | B127: C004 | C127: P103 | D127: 02/01/2026 | E127: 06/01/2026 | F127: Anita Gupta | G127: Female | H127: 04/01/1981 | I127: Bengaluru | J127: South | K127: Electronics | L127: Keyboard | M127: 2 | N127: 1200 | O127: 20 | P127: 1920 | Q127: 3 | R127: Card | S127: Neha | T127: anita.gupta@company.com | U127: 9429405275 | V127: Completed
A128: ORD10127 | B128: C003 | C128: P101 | D128: 20/04/2026 | E128: 26/04/2026 | F128: Rohit Singh | G128: Male | H128: 12/10/2004 | I128: Bengaluru | J128: South | K128: Electronics | L128: Laptop | M128: 10 | N128: 55000 | O128: 5 | P128: 522500 | Q128: 5 | R128: UPI | S128: Aisha | T128: rohit.singh@company.com | U128: 9521757571 | V128: Pending
A129: ORD10128 | B129: C006 | C129: P201 | D129: 04/08/2025 | E129: 05/08/2025 | F129: Sneha Joshi | G129: Female | H129: 25/03/1984 | I129: Jaipur | J129: North | K129: Home Appliances | L129: Mixer | M129: 15 | N129: 3500 | O129: 10 | P129: 47250 | Q129: 3 | R129: NetBanking | S129: Neha | T129: sneha.joshi@company.com | U129: 9467375455 | V129: Completed
A130: ORD10129 | B130: C002 | C130: P202 | D130: 13/08/2025 | E130: 18/08/2025 | F130: Priya Patel | G130: Female | H130: 09/09/1982 | I130: Bengaluru | J130: South | K130: Home Appliances | L130: Iron | M130: 10 | N130: 2200 | O130: 15 | P130: 18700 | Q130: 4 | R130: Card | S130: Rahul | T130: priya.patel@company.com | U130: 9838809695 | V130: Pending
A131: ORD10130 | B131: C006 | C131: P201 | D131: 16/06/2025 | E131: 24/06/2025 | F131: Sneha Joshi | G131: Female | H131: 15/02/1993 | I131: Pune | J131: West | K131: Home Appliances | L131: Mixer | M131: 11 | N131: 3500 | O131: 5 | P131: 36575 | Q131: 5 | R131: Cash | S131: Ritika | T131: sneha.joshi@company.com | U131: 9296609782 | V131: Cancelled
A132: ORD10131 | B132: C004 | C132: P103 | D132: 27/04/2026 | E132: 30/04/2026 | F132: Anita Gupta | G132: Female | H132: 08/04/2003 | I132: Bengaluru | J132: South | K132: Electronics | L132: Keyboard | M132: 14 | N132: 1200 | O132: 0 | P132: 16800 | Q132: 5 | R132: Cash | S132: Rahul | T132: anita.gupta@company.com | U132: 9848259992 | V132: Cancelled
... A299: ORD10298 | B299: C003 | C299: P101 | D299: 13/01/2025 | E299: 16/01/2025 | F299: Rohit Singh | G299: Male | H299: 03/01/2004 | I299: Hyderabad | J299: South | K299: Electronics | L299: Laptop | M299: 11 | N299: 55000 | O299: 5 | P299: 574750 | Q299: 1 | R299: UPI | S299: Ritika | T299: rohit.singh@company.com | U299: 9482699727 | V299: Cancelled
A300: ORD10299 | B300: C007 | C300: P201 | D300: 05/10/2025 | E300: 17/10/2025 | F300: Arjun Rao | G300: Male | H300: 02/05/1992 | I300: Jaipur | J300: North | K300: Home Appliances | L300: Mixer | M300: 12 | N300: 3500 | O300: 0 | P300: 42000 | Q300: 2 | R300: NetBanking | T300: arjun.rao@company.com | U300: 9332473934 | V300: Pending
A301: ORD10300 | B301: C009 | C301: P303 | D301: 25/02/2026 | E301: 08/03/2026 | F301: Mohit Verma | G301: Male | H301: 26/01/2003 | I301: Hyderabad | J301: South | K301: Stationery | L301: Marker | M301: 15 | N301: 45 | O301: 10 | P301: 607.5 | Q301: 2 | R301: Cash | S301: Karan | T301: mohit.verma@company.com | U301: 9647657382 | V301: Pending
A302: ORD10301 | B302: C001 | C302: P303 | D302: 16/05/2025 | E302: 26/05/2025 | F302: Amit Sharma | G302: Male | H302: 20/05/1987 | I302: Bengaluru | J302: South | K302: Stationery | L302: Marker | M302: 13 | N302: 45 | O302: 0 | P302: 585 | Q302: 5 | R302: NetBanking | S302: Rahul | T302: amit.sharma@company.com | U302: 9736797776 | V302: Pending
A303: ORD10302 | B303: C003 | C303: P101 | D303: 02/01/2026 | E303: 05/01/2026 | F303: Rohit Singh | G303: Male | H303: 07/09/1975 | I303: Bengaluru | J303: South | K303: Electronics | L303: Laptop | M303: 8 | N303: 55000 | O303: 0 | P303: 440000 | Q303: 2 | R303: UPI | S303: Karan | T303: rohit.singh@company.com | U303: 9745773533 | V303: Cancelled
A304: ORD10303 | B304: C006 | C304: P101 | D304: 23/07/2025 | E304: 27/07/2025 | F304: Sneha Joshi | G304: Female | H304: 10/08/1980 | I304: Delhi | J304: North | K304: Electronics | L304: Laptop | M304: 4 | N304: 55000 | O304: 20 | P304: 176000 | Q304: 5 | R304: Cash | S304: Rahul | T304: sneha.joshi@company.com | U304: 9246715757 | V304: Pending
A305: ORD10304 | B305: C008 | C305: P201 | D305: 23/04/2026 | E305: 26/04/2026 | F305: Kavya Nair | G305: Female | H305: 07/04/1989 | I305: Ahmedabad | J305: West | K305: Home Appliances | L305: Mixer | M305: 19 | N305: 3500 | O305: 5 | P305: 63175 | Q305: 1 | R305: Card | S305: Neha | T305: kavya.nair@company.com | U305: 9904065774 | V305: Completed
A306: ORD10305 | B306: C005 | C306: P103 | D306: 02/03/2025 | E306: 06/03/2025 | F306: Vikas Mehta | G306: Male | H306: 20/08/1998 | I306: Jaipur | J306: North | K306: Electronics | L306: Keyboard | M306: 17 | N306: 1200 | O306: 15 | P306: 17340 | Q306: 2 | R306: NetBanking | S306: Rahul | T306: vikas.mehta@company.com | U306: 9652985385 | V306: Completed
A307: ORD10306 | B307: C008 | C307: P202 | D307: 09/02/2026 | E307: 17/02/2026 | F307: Kavya Nair | G307: Female | H307: 03/04/2001 | I307: Hyderabad | J307: South | K307: Home Appliances | L307: Iron | M307: 8 | N307: 2200 | O307: 5 | P307: 16720 | Q307: 3 | R307: Card | S307: Neha | T307: kavya.nair@company.com | U307: 9427001508 | V307: Pending
A308: ORD10307 | B308: C006 | C308: P102 | D308: 16/02/2025 | E308: 26/02/2025 | F308: Sneha Joshi | G308: Female | H308: 05/03/1992 | I308: Mumbai | J308: West | K308: Electronics | L308: Mouse | M308: 17 | N308: 700 | O308: 20 | P308: 9520 | Q308: 4 | R308: NetBanking | S308: Neha | T308: sneha.joshi@company.com | U308: 9666803655 | V308: Completed
A309: ORD10308 | B309: C006 | C309: P203 | D309: 28/08/2025 | E309: 08/09/2025 | F309: Sneha Joshi | G309: Female | H309: 28/12/1976 | I309: Pune | J309: West | K309: Home Appliances | L309: Microwave | M309: 6 | N309: 8500 | O309: 15 | P309: 43350 | Q309: 1 | R309: Cash | S309: Aisha | T309: sneha.joshi@company.com | U309: 9134878547 | V309: Completed
A310: ORD10309 | B310: C010 | C310: P201 | D310: 06/10/2025 | E310: 11/10/2025 | F310: Pooja Shah | G310: Female | H310: 04/09/1986 | I310: Hyderabad | J310: South | K310: Home Appliances | L310: Mixer | M310: 3 | N310: 3500 | O310: 10 | P310: 9450 | Q310: 1 | R310: NetBanking | S310: Rahul | T310: pooja.shah@company.com | U310: 9253593557 | V310: Completed
A311: ORD10310 | B311: C009 | C311: P104 | D311: 17/01/2025 | E311: 29/01/2025 | F311: Mohit Verma | G311: Male | H311: 14/08/1989 | I311: Ahmedabad | J311: West | K311: Electronics | L311: Monitor | M311: 2 | N311: 12000 | O311: 20 | P311: 19200 | Q311: 1 | R311: Card | S311: Aisha | T311: mohit.verma@company.com | U311: 9183094051 | V311: Completed
A312: ORD10311 | B312: C005 | C312: P302 | D312: 13/10/2025 | E312: 16/10/2025 | F312: Vikas Mehta | G312: Male | H312: 02/03/1991 | I312: Delhi | J312: North | K312: Stationery | L312: Pen | M312: 12 | N312: 20 | O312: 20 | P312: 192 | Q312: 2 | R312: Card | S312: Rahul | T312: vikas.mehta@company.com | U312: 9293147620 | V312: Completed
... A370: ORD10369 | B370: C010 | C370: P301 | D370: 01/04/2026 | E370: 05/04/2026 | F370: Pooja Shah | G370: Female | H370: 04/01/1987 | I370: Hyderabad | J370: South | K370: Stationery | L370: Notebook | M370: 19 | N370: 60 | O370: 15 | P370: 969 | Q370: 4 | R370: NetBanking | S370: Neha | T370: pooja.shah@company.com | U370: 9435947486 | V370: Cancelled
A371: ORD10370 | B371: C001 | C371: P101 | E371: 02/02/2025 | F371: Amit Sharma | G371: Male | H371: 14/05/1992 | I371: Delhi | J371: North | K371: Electronics | L371: Laptop | M371: 15 | N371: 55000 | O371: 0 | P371: 825000 | Q371: 5 | R371: Card | S371: Neha | T371: amit.sharma@company.com | U371: 9411668831 | V371: Cancelled
A372: ORD10371 | B372: C009 | C372: P303 | D372: 06/10/2025 | E372: 08/10/2025 | F372: Mohit Verma | G372: Male | H372: 03/05/1989 | I372: Bengaluru | J372: South | K372: Stationery | L372: Marker | M372: 11 | N372: 45 | O372: 5 | P372: 470.25 | Q372: 5 | R372: NetBanking | S372: Karan | T372: mohit.verma@company.com | U372: 9523682403 | V372: Completed
A373: ORD10372 | B373: C006 | C373: P302 | D373: 12/06/2025 | E373: 17/06/2025 | F373: Sneha Joshi | G373: Female | H373: 19/12/1990 | I373: Jaipur | J373: North | K373: Stationery | L373: Pen | M373: 9 | N373: 20 | O373: 10 | P373: 162 | Q373: 1 | R373: Card | S373: Rahul | T373: sneha.joshi@company.com | U373: 9652936744 | V373: Cancelled
A374: ORD10373 | B374: C004 | C374: P303 | D374: 18/11/2025 | E374: 20/11/2025 | F374: Anita Gupta | G374: Female | H374: 09/07/1995 | I374: Bengaluru | J374: South | K374: Stationery | L374: Marker | M374: 5 | N374: 45 | O374: 5 | P374: 213.75 | Q374: 3 | R374: Card | S374: Neha | T374: anita.gupta@company.com | U374: 9726464733 | V374: Pending
A375: ORD10374 | B375: C007 | C375: P102 | D375: 01/11/2025 | E375: 02/11/2025 | F375: Arjun Rao | G375: Male | H375: 23/12/1998 | I375: Hyderabad | J375: South | K375: Electronics | L375: Mouse | M375: 5 | N375: 700 | O375: 10 | P375: 3150 | Q375: 2 | R375: UPI | S375: Rahul | T375: arjun.rao@company.com | U375: 9273520544 | V375: Completed
A376: ORD10375 | B376: C005 | C376: P102 | D376: 24/01/2025 | E376: 31/01/2025 | F376: Vikas Mehta | G376: Male | H376: 23/12/1979 | I376: Kolkata | J376: East | K376: Electronics | L376: Mouse | M376: 1 | N376: 700 | O376: 0 | P376: 700 | Q376: 1 | R376: UPI | S376: Karan | T376: vikas.mehta@company.com | U376: 9374259988 | V376: Completed
A377: ORD10376 | B377: C008 | C377: P102 | D377: 13/02/2026 | E377: 21/02/2026 | F377: Kavya Nair | G377: Female | H377: 15/12/1975 | I377: Mumbai | J377: West | K377: Electronics | L377: Mouse | M377: 13 | N377: 700 | O377: 20 | P377: 7280 | Q377: 2 | R377: Card | S377: Ritika | T377: kavya.nair@company.com | U377: 9538129419 | V377: Completed
A378: ORD10377 | B378: C009 | C378: P104 | D378: 08/02/2025 | E378: 19/02/2025 | F378: Mohit Verma | G378: Male | H378: 17/05/1993 | I378: Pune | J378: West | K378: Electronics | L378: Monitor | M378: 20 | N378: 12000 | O378: 0 | P378: 240000 | Q378: 2 | R378: Card | S378: Neha | T378: mohit.verma@company.com | U378: 9382815686 | V378: Completed
A379: ORD10378 | B379: C007 | C379: P103 | D379: 28/12/2025 | E379: 06/01/2026 | F379: Arjun Rao | G379: Male | H379: 17/09/1976 | I379: Kolkata | J379: East | K379: Electronics | L379: Keyboard | M379: 9 | N379: 1200 | O379: 15 | P379: 9180 | Q379: 1 | R379: UPI | S379: Ritika | T379: arjun.rao@company.com | U379: 9450746157 | V379: Pending
A380: ORD10379 | B380: C007 | C380: P302 | D380: 01/10/2025 | E380: 03/10/2025 | F380: Arjun Rao | G380: Male | H380: 22/12/1996 | I380: Jaipur | J380: North | K380: Stationery | L380: Pen | M380: 3 | N380: 20 | O380: 15 | P380: 51 | Q380: 3 | R380: Cash | S380: Neha | T380: arjun.rao@company.com | U380: 9349012570 | V380: Pending
A381: ORD10380 | B381: C006 | C381: P101 | D381: 18/12/2025 | E381: 19/12/2025 | F381: Sneha Joshi | G381: Female | H381: 25/12/1995 | I381: Delhi | J381: North | K381: Electronics | L381: Laptop | M381: 8 | N381: 55000 | O381: 20 | P381: 352000 | Q381: 5 | R381: Card | S381: Karan | T381: sneha.joshi@company.com | U381: 9442163790 | V381: Pending
A382: ORD10381 | B382: C006 | C382: P301 | D382: 29/09/2025 | E382: 07/10/2025 | F382: Sneha Joshi | G382: Female | H382: 23/06/1985 | I382: Delhi | J382: North | K382: Stationery | L382: Notebook | M382: 17 | N382: 60 | O382: 20 | P382: 816 | Q382: 1 | R382: UPI | S382: Ritika | T382: sneha.joshi@company.com | U382: 9953329223 | V382: Pending
A383: ORD10382 | B383: C003 | C383: P302 | D383: 14/05/2025 | E383: 22/05/2025 | F383: Rohit Singh | G383: Male | H383: 10/02/1984 | I383: Bengaluru | J383: South | K383: Stationery | L383: Pen | M383: 4 | N383: 20 | O383: 15 | P383: 68 | Q383: 3 | R383: NetBanking | S383: Aisha | T383: rohit.singh@company.com | U383: 9202321359 | V383: Pending
... A399: ORD10398 | B399: C007 | C399: P104 | D399: 31/01/2025 | E399: 04/02/2025 | F399: Arjun Rao | G399: Male | H399: 10/12/1978 | I399: Kolkata | J399: East | K399: Electronics | L399: Monitor | M399: 19 | N399: 12000 | O399: 0 | P399: 228000 | Q399: 4 | R399: UPI | S399: Aisha | T399: arjun.rao@company.com | U399: 9136906750 | V399: Pending
A400: ORD10399 | B400: C001 | C400: P102 | E400: 03/11/2025 | F400: Amit Sharma | G400: Male | H400: 01/09/1979 | I400: Bengaluru | J400: South | K400: Electronics | L400: Mouse | M400: 12 | N400: 700 | O400: 15 | P400: 7140 | Q400: 3 | R400: Card | S400: Ritika | T400: amit.sharma@company.com | U400: 9485286324 | V400: Completed
A401: ORD10400 | B401: C008 | C401: P103 | D401: 13/05/2025 | E401: 21/05/2025 | F401: Kavya Nair | G401: Female | H401: 08/04/2001 | I401: Delhi | J401: North | K401: Electronics | L401: Keyboard | M401: 16 | N401: 1200 | O401: 20 | P401: 15360 | Q401: 1 | R401: Cash | S401: Rahul | T401: kavya.nair@company.com | U401: 9414633966 | V401: Pending
A402: ORD10401 | B402: C009 | C402: P203 | D402: 27/12/2025 | E402: 04/01/2026 | F402: Mohit Verma | G402: Male | H402: 01/01/1983 | I402: Hyderabad | J402: South | K402: Home Appliances | L402: Microwave | M402: 10 | N402: 8500 | O402: 5 | P402: 80750 | Q402: 5 | R402: NetBanking | S402: Ritika | T402: mohit.verma@company.com | U402: 9833735234 | V402: Completed
A403: ORD10402 | B403: C008 | C403: P302 | D403: 11/02/2025 | E403: 21/02/2025 | F403: Kavya Nair | G403: Female | H403: 09/08/1989 | I403: Ahmedabad | J403: West | K403: Stationery | L403: Pen | M403: 18 | N403: 20 | O403: 20 | P403: 288 | Q403: 1 | R403: UPI | S403: Ritika | T403: kavya.nair@company.com | U403: 9523689108 | V403: Pending
A404: ORD10403 | B404: C009 | C404: P203 | D404: 13/03/2026 | E404: 19/03/2026 | F404: Mohit Verma | G404: Male | H404: 22/10/1993 | I404: Mumbai | J404: West | K404: Home Appliances | L404: Microwave | M404: 9 | N404: 8500 | O404: 0 | P404: 76500 | Q404: 2 | R404: Card | S404: Ritika | T404: mohit.verma@company.com | U404: 9812909831 | V404: Pending
A405: ORD10404 | B405: C008 | C405: P203 | D405: 01/10/2025 | E405: 12/10/2025 | F405: Kavya Nair | G405: Female | H405: 05/05/2000 | I405: Mumbai | J405: West | K405: Home Appliances | L405: Microwave | M405: 8 | N405: 8500 | O405: 10 | P405: 61200 | Q405: 4 | R405: Cash | S405: Neha | T405: kavya.nair@company.com | U405: 9106290987 | V405: Cancelled
...

Sheet Product_master
A1: Product_ID | B1: Product_Name | C1: Category | D1: Supplier | E1: Cost_Price | F1: Warranty_Months
A2: P101 | B2: Laptop | C2: Electronics | D2: TechHub | E2: 41250 | F2: 12
A3: P102 | B3: Mouse | C3: Electronics | D3: TechHub | E3: 525 | F3: 24
A4: P103 | B4: Keyboard | C4: Electronics | D4: TechHub | E4: 900 | F4: 6
A5: P104 | B5: Monitor | C5: Electronics | D5: Global Trade | E5: 9000 | F5: 24
A6: P201 | B6: Mixer | C6: Home Appliances | D6: Global Trade | E6: 2625 | F6: 6
A7: P202 | B7: Iron | C7: Home Appliances | D7: Global Trade | E7: 1650 | F7: 24
A8: P203 | B8: Microwave | C8: Home Appliances | D8: TechHub | E8: 6375 | F8: 24
A9: P301 | B9: Notebook | C9: Stationery | D9: ABC Corp | E9: 45 | F9: 12
A10: P302 | B10: Pen | C10: Stationery | D10: Prime Supplies | E10: 15 | F10: 12
A11: P303 | B11: Marker | C11: Stationery | D11: TechHub | E11: 33.75 | F11: 12

Sheet Customer_master
A1: Customer_ID | B1: Customer_Name | C1: Membership | D1: State
A2: C001 | B2: Amit Sharma | C2: Silver | D2: RJ
A3: C002 | B3: Priya Patel | C3: Platinum | D3: WB
A4: C003 | B4: Rohit Singh | C4: Gold | D4: DL
A5: C004 | B5: Anita Gupta | C5: Gold | D5: WB
A6: C005 | B6: Vikas Mehta | C6: Gold | D6: DL
A7: C006 | B7: Sneha Joshi | C7: Gold | D7: WB
A8: C007 | B8: Arjun Rao | C8: Silver | D8: RJ
A9: C008 | B9: Kavya Nair | C9: Silver | D9: WB
A10: C009 | B10: Mohit Verma | C10: Platinum | D10: KA
A11: C010 | B11: Pooja Shah | C11: Silver | D11: WB

Sheet Q1
A1: Order_ID | B1: Customer_ID | C1: Product_ID | D1: Order_Date | E1: Delivery_Date | F1: Customer_Name | G1: Gender | H1: DOB | I1: City | J1: Region | K1: Category | L1: Product_Name | M1: Quantity | N1: Unit_Price | O1: Discount_% | P1: Sales | Q1: Rating | R1: Payment_Mode | S1: Salesperson | T1: Email | U1: Phone | V1: Order_Status | W1: Customer Classification
A2: ORD10001 | B2: C008 | C2: P202 | D2: 18/09/2025 | E2: 22/09/2025 | F2: Kavya Nair | G2: Female | H2: 01/08/1976 | I2: Hyderabad | J2: South | K2: Home Appliances | L2: Iron | M2: 4 | N2: 2200 | O2: 10 | P2: 7920 | Q2: 4 | R2: Cash | S2: Ritika | T2: KAvya.nair@company.com | U2: 9431429797 | V2: Completed | W2: =IF(OR(Q2<=2, V2="Cancelled"), "Blacklisted", IF(AND(P2>=100000, Q2>=4, O2<=10, V2="Completed"), "Platinum", IF(AND(P2>=50000, P2<=99999, Q2>=3, V2="Completed"), "Gold", IF(AND(P2<50000, V2="Completed"), "Silver", "Pending")))) -> Silver
A3: ORD10002 | B3: C008 | C3: P104 | D3: 27/04/2025 | E3: 04/05/2025 | F3: Kavya Nair | G3: Female | H3: 16/10/2000 | I3: Delhi | J3: North | K3: Electronics | L3: Monitor | M3: 17 | N3: 12000 | O3: 10 | P3: 183600 | Q3: 1 | R3: NetBanking | S3: Rahul | T3: kavya.nair@company.com | U3: 9129865339 | V3: Completed | W3: =IF(OR(Q3<=2, V3="Cancelled"), "Blacklisted", IF(AND(P3>=100000, Q3>=4, O3<=10, V3="Completed"), "Platinum", IF(AND(P3>=50000, P3<=99999, Q3>=3, V3="Completed"), "Gold", IF(AND(P3<50000, V3="Completed"), "Silver", "Pending")))) -> Blacklisted
A4: ORD10003 | B4: C010 | C4: P101 | D4: 03/09/2025 | E4: 14/09/2025 | F4: pooja shah | G4: Female | H4: 16/09/1994 | I4: Bengaluru | J4: South | K4: Electronics | L4: Laptop | M4: 5 | N4: 55000 | O4: 5 | P4: 261250 | Q4: 3 | R4: NetBanking | S4: Aisha | T4: pooja.shah@company.com | U4: 9380975626 | V4: Pending | W4: =IF(OR(Q4<=2, V4="Cancelled"), "Blacklisted", IF(AND(P4>=100000, Q4>=4, O4<=10, V4="Completed"), "Platinum", IF(AND(P4>=50000, P4<=99999, Q4>=3, V4="Completed"), "Gold", IF(AND(P4<50000, V4="Completed"), "Silver", "Pending")))) -> Pending
A5: ORD10002 | B5: C008 | C5: P202 | D5: 21/03/2026 | E5: 02/04/2026 | F5: Kavya Nair | G5: Female | H5: 07/03/2004 | I5: Bengaluru | J5: South | K5: Home Appliances | L5: Iron | M5: 5 | N5: 2200 | O5: 5 | P5: 10450 | Q5: 5 | R5: NetBanking | S5: Aisha | T5: kavya.nair@company.com | U5: 9600261125 | V5: Cancelled | W5: =IF(OR(Q5<=2, V5="Cancelled"), "Blacklisted", IF(AND(P5>=100000, Q5>=4, O5<=10, V5="Completed"), "Platinum", IF(AND(P5>=50000, P5<=99999, Q5>=3, V5="Completed"), "Gold", IF(AND(P5<50000, V5="Completed"), "Silver", "Pending")))) -> Blacklisted
A6: ORD10005 | B6: C009 | C6: P103 | D6: 27/09/2025 | E6: 07/10/2025 | F6: Mohit Verma | G6: Male | H6: 13/04/1976 | I6: Delhi | J6: North | K6: Electronics | L6: Keyboard | M6: 8 | N6: 1200 | O6: 5 | P6: 9120 | Q6: 2 | R6: Card | S6: Aisha | T6: mohit.verma@company.com | U6: 9724635978 | V6: Pending | W6: =IF(OR(Q6<=2, V6="Cancelled"), "Blacklisted", IF(AND(P6>=100000, Q6>=4, O6<=10, V6="Completed"), "Platinum", IF(AND(P6>=50000, P6<=99999, Q6>=3, V6="Completed"), "Gold", IF(AND(P6<50000, V6="Completed"), "Silver", "Pending")))) -> Blacklisted
A7: ORD10006 | B7: C007 | C7: P202 | D7: 04/01/2026 | E7: 12/01/2026 | F7: arjun Rao | G7: Male | H7: 07/02/1988 | I7: Hyderabad | J7: South | K7: Home Appliances | L7: Iron | M7: 4 | N7: 2200 | O7: 0 | P7: 8800 | Q7: 1 | R7: UPI | S7: Ritika | T7: arjun.rao@company.com | U7: 9780584905 | V7: Completed | W7: =IF(OR(Q7<=2, V7="Cancelled"), "Blacklisted", IF(AND(P7>=100000, Q7>=4, O7<=10, V7="Completed"), "Platinum", IF(AND(P7>=50000, P7<=99999, Q7>=3, V7="Completed"), "Gold", IF(AND(P7<50000, V7="Completed"), "Silver", "Pending")))) -> Blacklisted
A8: ORD10007 | B8: C008 | C8: P201 | D8: 31/02/2025 | E8: 25/02/2026 | F8: Kavya Nair | G8: Female | H8: 20/03/2003 | I8: Hyderabad | J8: South | K8: Home Appliances | L8: Mixer | M8: 2 | N8: 3500 | O8: 5 | P8: 6650 | Q8: 1 | R8: UPI | S8: Ritika | T8: kavya.nair@company.com | U8: 9958252176 | V8: Completed | W8: =IF(OR(Q8<=2, V8="Cancelled"), "Blacklisted", IF(AND(P8>=100000, Q8>=4, O8<=10, V8="Completed"), "Platinum", IF(AND(P8>=50000, P8<=99999, Q8>=3, V8="Completed"), "Gold", IF(AND(P8<50000, V8="Completed"), "Silver", "Pending")))) -> Blacklisted
A9: ORD10008 | B9: C002 | C9: P104 | D9: 13/04/2025 | E9: 19/04/2025 | F9: Priya Patel | G9: Female | H9: 07/03/1995 | I9: Mumbai | J9: West | K9: Electronics | L9: Monitor | M9: 14 | N9: 12000 | O9: 15 | P9: 142800 | Q9: 4 | R9: NetBanking | S9: Ritika | T9: priYa.patel@company.com | U9: 9705521654 | V9: Completed | W9: =IF(OR(Q9<=2, V9="Cancelled"), "Blacklisted", IF(AND(P9>=100000, Q9>=4, O9<=10, V9="Completed"), "Platinum", IF(AND(P9>=50000, P9<=99999, Q9>=3, V9="Completed"), "Gold", IF(AND(P9<50000, V9="Completed"), "Silver", "Pending")))) -> Pending
A10: ORD10009 | B10: C008 | C10: P104 | D10: 31/01/2026 | E10: 02/02/2026 | F10: kavya Nair | G10: Female | H10: 06/04/1997 | I10: Pune | J10: West | K10: Electronics | L10: Monitor | M10: 4 | N10: 12000 | O10: 15 | P10: 40800 | Q10: 4 | R10: UPI | S10: Neha | T10: kavya.nair@company.com | U10: 9588041011 | V10: Completed | W10: =IF(OR(Q10<=2, V10="Cancelled"), "Blacklisted", IF(AND(P10>=100000, Q10>=4, O10<=10, V10="Completed"), "Platinum", IF(AND(P10>=50000, P10<=99999, Q10>=3, V10="Completed"), "Gold", IF(AND(P10<50000, V10="Completed"), "Silver", "Pending")))) -> Silver
A11: ORD10010 | B11: C002 | C11: P301 | D11: 25/03/2025 | E11: 27/03/2025 | F11: Priya Patel | G11: Female | H11: 07/01/1990 | I11: Mumbai | J11: West | K11: Stationery | L11: Notebook | M11: 6 | N11: 60 | O11: 0 | P11: 360 | Q11: 4 | R11: Card | S11: Neha | T11: PRiya.patel@company.com | U11: 9340540608 | V11: Completed | W11: =IF(OR(Q11<=2, V11="Cancelled"), "Blacklisted", IF(AND(P11>=100000, Q11>=4, O11<=10, V11="Completed"), "Platinum", IF(AND(P11>=50000, P11<=99999, Q11>=3, V11="Completed"), "Gold", IF(AND(P11<50000, V11="Completed"), "Silver", "Pending")))) -> Silver
A12: ORD10011 | B12: C003 | C12: P202 | D12: 19/09/2025 | E12: 23/09/2025 | F12: Rohit Singh | G12: Male | H12: 10/05/1982 | I12: Delhi | J12: North | K12: Home Appliances | L12: Iron | M12: -3 | N12: 2200 | O12: 0 | P12: 35200 | Q12: 2 | R12: Card | S12: Rahul | T12: rohit.singh@company.com | U12: 9521710321 | V12: Pending | W12: =IF(OR(Q12<=2, V12="Cancelled"), "Blacklisted", IF(AND(P12>=100000, Q12>=4, O12<=10, V12="Completed"), "Platinum", IF(AND(P12>=50000, P12<=99999, Q12>=3, V12="Completed"), "Gold", IF(AND(P12<50000, V12="Completed"), "Silver", "Pending")))) -> Blacklisted
A13: ORD10012 | B13: C008 | C13: P201 | D13: 08/03/2025 | E13: 15/03/2025 | F13: Kavya Nair | G13: Female | H13: 23/01/1982 | I13: Ahmedabad | J13: West | K13: Home Appliances | L13: Mixer | M13: 10 | N13: 3500 | O13: 5 | P13: 33250 | Q13: 5 | R13: Card | S13: Aisha | T13: kavya.nair@company.com | U13: 9123535241 | V13: Cancelled | W13: =IF(OR(Q13<=2, V13="Cancelled"), "Blacklisted", IF(AND(P13>=100000, Q13>=4, O13<=10, V13="Completed"), "Platinum", IF(AND(P13>=50000, P13<=99999, Q13>=3, V13="Completed"), "Gold", IF(AND(P13<50000, V13="Completed"), "Silver", "Pending")))) -> Blacklisted
... A39: ORD10038 | B39: C006 | C39: P201 | D39: 08/03/2026 | E39: 20/03/2026 | F39: Sneha Joshi | G39: Female | H39: 21/06/1980 | I39: Delhi | J39: North | K39: Home Appliances | L39: Mixer | M39: 20 | N39: 3500 | O39: 10 | P39: 63000 | Q39: 3 | R39: Card | S39: Rahul | T39: sneha.joshi@company.com | U39: 9283578533 | V39: Cancelled | W39: =IF(OR(Q39<=2, V39="Cancelled"), "Blacklisted", IF(AND(P39>=100000, Q39>=4, O39<=10, V39="Completed"), "Platinum", IF(AND(P39>=50000, P39<=99999, Q39>=3, V39="Completed"), "Gold", IF(AND(P39<50000, V39="Completed"), "Silver", "Pending")))) -> Blacklisted
A40: ORD10039 | B40: C008 | C40: P302 | D40: 13/02/2025 | E40: 19/02/2025 | F40: Kavya Nair | G40: Female | H40: 17/06/1979 | I40: Pune | J40: West | K40: Stationery | L40: Pen | M40: 5 | N40: 1200 | O40: 0 | P40: 100 | Q40: 1 | R40: Cash | S40: Rahul | T40: kavya.nair@company.com | U40: 9963005771 | V40: Cancelled | W40: =IF(OR(Q40<=2, V40="Cancelled"), "Blacklisted", IF(AND(P40>=100000, Q40>=4, O40<=10, V40="Completed"), "Platinum", IF(AND(P40>=50000, P40<=99999, Q40>=3, V40="Completed"), "Gold", IF(AND(P40<50000, V40="Completed"), "Silver", "Pending")))) -> Blacklisted
A41: ORD10040 | B41: C010 | C41: P203 | D41: 05/10/2025 | E41: 15/10/2025 | F41: Pooja Shah | G41: Female | H41: 18/06/1992 | I41: Mumbai | J41: West | K41: Home Appliances | L41: Microwave | M41: 20 | N41: 8500 | O41: 0 | P41: 170000 | Q41: 1 | R41: UPI | S41: Neha | T41: pooja.shah@company.com | U41: 9484632635 | V41: Cancelled | W41: =IF(OR(Q41<=2, V41="Cancelled"), "Blacklisted", IF(AND(P41>=100000, Q41>=4, O41<=10, V41="Completed"), "Platinum", IF(AND(P41>=50000, P41<=99999, Q41>=3, V41="Completed"), "Gold", IF(AND(P41<50000, V41="Completed"), "Silver", "Pending")))) -> Blacklisted
A42: ORD10041 | B42: C007 | C42: P301 | D42: 10/02/2026 | E42: 12/02/2026 | F42: Arjun Rao | G42: Male | H42: 06/06/1994 | I42: Bengaluru | J42: South | K42: Stationery | L42: Notebook | M42: 8 | N42: 60 | O42: 15 | P42: 408 | Q42: 5 | R42: UPI | S42: Rahul | T42: arjun.rao@company.com | U42: 9276319484 | V42: Pending | W42: =IF(OR(Q42<=2, V42="Cancelled"), "Blacklisted", IF(AND(P42>=100000, Q42>=4, O42<=10, V42="Completed"), "Platinum", IF(AND(P42>=50000, P42<=99999, Q42>=3, V42="Completed"), "Gold", IF(AND(P42<50000, V42="Completed"), "Silver", "Pending")))) -> Pending
A43: ORD10042 | B43: C010 | C43: P201 | D43: 04/06/2025 | E43: 16/06/2025 | F43: Pooja Shah | G43: Female | H43: 22/09/1988 | I43: Pune | J43: West | K43: Home Appliances | L43: Mixer | M43: 8 | N43: 3500 | O43: 5 | P43: 26600 | Q43: 1 | R43: Card | S43: Neha | T43: pooja.shah@company.com | U43: 9619034852 | V43: Pending | W43: =IF(OR(Q43<=2, V43="Cancelled"), "Blacklisted", IF(AND(P43>=100000, Q43>=4, O43<=10, V43="Completed"), "Platinum", IF(AND(P43>=50000, P43<=99999, Q43>=3, V43="Completed"), "Gold", IF(AND(P43<50000, V43="Completed"), "Silver", "Pending")))) -> Blacklisted
A44: ORD10043 | B44: C009 | C44: P203 | D44: 08/02/2026 | E44: 14/02/2026 | F44: Mohit Verma | G44: Male | H44: 14/07/2001 | I44: Jaipur | J44: North | K44: Home Appliances | L44: Microwave | M44: 1 | N44: 8500 | O44: 0 | P44: 8500 | Q44: 2 | R44: Card | S44: Neha | T44: mohit.verma@company.com | U44: 9636416962 | V44: Pending | W44: =IF(OR(Q44<=2, V44="Cancelled"), "Blacklisted", IF(AND(P44>=100000, Q44>=4, O44<=10, V44="Completed"), "Platinum", IF(AND(P44>=50000, P44<=99999, Q44>=3, V44="Completed"), "Gold", IF(AND(P44<50000, V44="Completed"), "Silver", "Pending")))) -> Blacklisted
A45: ORD10044 | B45: C001 | C45: P303 | D45: 30/03/2025 | E45: 31/03/2025 | F45: amit Sharma | G45: Male | H45: 09/08/1991 | I45: Pune | J45: West | K45: Stationery | L45: Marker | M45: 8 | N45: 45 | O45: 15 | P45: 306 | Q45: 2 | R45: Card | S45: Aisha | T45: amit.sharma@company.com | U45: 9357133880 | V45: Completed | W45: =IF(OR(Q45<=2, V45="Cancelled"), "Blacklisted", IF(AND(P45>=100000, Q45>=4, O45<=10, V45="Completed"), "Platinum", IF(AND(P45>=50000, P45<=99999, Q45>=3, V45="Completed"), "Gold", IF(AND(P45<50000, V45="Completed"), "Silver", "Pending")))) -> Blacklisted
A46: ORD10045 | B46: C006 | C46: P202 | D46: 25/04/2025 | E46: 28/04/2025 | F46: Sneha Joshi | G46: Female | H46: 21/10/1988 | I46: Pune | J46: West | K46: Home Appliances | L46: Iron | M46: 16 | N46: 2200 | O46: 5 | P46: 33440 | Q46: 5 | R46: Card | S46: Aisha | T46: sneha.joshi@company.com | U46: 9575210324 | V46: Cancelled | W46: =IF(OR(Q46<=2, V46="Cancelled"), "Blacklisted", IF(AND(P46>=100000, Q46>=4, O46<=10, V46="Completed"), "Platinum", IF(AND(P46>=50000, P46<=99999, Q46>=3, V46="Completed"), "Gold", IF(AND(P46<50000, V46="Completed"), "Silver", "Pending")))) -> Blacklisted
A47: ORD10046 | B47: C009 | C47: P201 | D47: 13/10/2025 | E47: 23/10/2025 | F47: Mohit Verma | G47: Male | H47: 19/11/2002 | I47: Bengaluru | J47: South | K47: Home Appliances | L47: Mixer | M47: 19 | N47: 3500 | O47: 20 | P47: 53200 | Q47: 3 | R47: Cash | S47: Karan | T47: mohit.verma@company.com | U47: 9276080204 | V47: Cancelled | W47: =IF(OR(Q47<=2, V47="Cancelled"), "Blacklisted", IF(AND(P47>=100000, Q47>=4, O47<=10, V47="Completed"), "Platinum", IF(AND(P47>=50000, P47<=99999, Q47>=3, V47="Completed"), "Gold", IF(AND(P47<50000, V47="Completed"), "Silver", "Pending")))) -> Blacklisted
A48: ORD10047 | B48: C006 | C48: P102 | D48: 11/10/2025 | E48: 14/10/2025 | F48: Sneha Joshi | G48: Female | H48: 06/07/2000 | I48: Pune | J48: West | K48: Electronics | L48: Mouse | M48: 15 | N48: 700 | O48: 15 | P48: 8925 | Q48: 4 | R48: UPI | S48: Neha | T48: sneha.joshicompany.com | U48: 9856624471 | V48: Completed | W48: =IF(OR(Q48<=2, V48="Cancelled"), "Blacklisted", IF(AND(P48>=100000, Q48>=4, O48<=10, V48="Completed"), "Platinum", IF(AND(P48>=50000, P48<=99999, Q48>=3, V48="Completed"), "Gold", IF(AND(P48<50000, V48="Completed"), "Silver", "Pending")))) -> Silver
A49: ORD10048 | B49: C006 | C49: P102 | D49: 27/11/2025 | E49: 03/12/2025 | F49: Sneha Joshi | G49: Female | H49: 26/11/1998 | I49: Jaipur | J49: North | K49: Electronics | L49: Mouse | M49: 19 | N49: 700 | O49: 20 | P49: 10640 | Q49: 1 | R49: Cash | S49: Neha | T49: sneha.joshi@company.com | U49: 9238141322 | V49: Completed | W49: =IF(OR(Q49<=2, V49="Cancelled"), "Blacklisted", IF(AND(P49>=100000, Q49>=4, O49<=10, V49="Completed"), "Platinum", IF(AND(P49>=50000, P49<=99999, Q49>=3, V49="Completed"), "Gold", IF(AND(P49<50000, V49="Completed"), "Silver", "Pending")))) -> Blacklisted
A50: ORD10049 | B50: C009 | C50: P104 | D50: 19/04/2026 | F50: Mohit Verma | G50: Male | H50: 03/06/1996 | I50: Delhi | J50: North | K50: Electronics | L50: Monitor | M50: 19 | N50: 12000 | O50: 0 | P50: 228000 | Q50: 1 | R50: NetBanking | S50: Aisha | T50: mohit.verma@company.com | U50: 9890380030 | V50: Completed | W50: =IF(OR(Q50<=2, V50="Cancelled"), "Blacklisted", IF(AND(P50>=100000, Q50>=4, O50<=10, V50="Completed"), "Platinum", IF(AND(P50>=50000, P50<=99999, Q50>=3, V50="Completed"), "Gold", IF(AND(P50<50000, V50="Completed"), "Silver", "Pending")))) -> Blacklisted
A51: ORD10050 | B51: C004 | C51: P103 | D51: 19/04/2026 | E51: 21/04/2026 | F51: Anita Gupta | G51: Female | H51: 15/03/1987 | I51: Pune | J51: West | K51: Electronics | L51: Keyboard | M51: 6 | N51: 1200 | O51: 5 | P51: 6840 | Q51: 2 | R51: Cash | S51: Ritika | T51: anita.gupta@company.com | U51: 9495893170 | V51: Pending | W51: =IF(OR(Q51<=2, V51="Cancelled"), "Blacklisted", IF(AND(P51>=100000, Q51>=4, O51<=10, V51="Completed"), "Platinum", IF(AND(P51>=50000, P51<=99999, Q51>=3, V51="Completed"), "Gold", IF(AND(P51<50000, V51="Completed"), "Silver", "Pending")))) -> Blacklisted
A52: ORD10051 | B52: C010 | C52: P202 | D52: 28/03/2025 | E52: 07/04/2025 | F52: POoja Shah | G52: Female | H52: 20/02/1979 | I52: Bengaluru | J52: South | K52: Home Appliances | L52: Iron | M52: 7 | N52: 2200 | O52: 15 | P52: 13090 | Q52: 1 | R52: UPI | S52: Aisha | T52: pooja.shah@company.com | U52: 9485166307 | V52: Completed | W52: =IF(OR(Q52<=2, V52="Cancelled"), "Blacklisted", IF(AND(P52>=100000, Q52>=4, O52<=10, V52="Completed"), "Platinum", IF(AND(P52>=50000, P52<=99999, Q52>=3, V52="Completed"), "Gold", IF(AND(P52<50000, V52="Completed"), "Silver", "Pending")))) -> Blacklisted
A53: ORD10052 | B53: C002 | C53: P301 | D53: 25/08/2025 | E53: 28/08/2025 | F53: Priya Patel | G53: Female | H53: 09/08/2000 | I53: Jaipur | J53: North | K53: Stationery | L53: Notebook | M53: 8 | N53: 60 | O53: 10 | P53: 432 | Q53: 5 | R53: Card | S53: Aisha | T53: priya.patel@company.com | U53: 9924709648 | V53: Cancelled | W53: =IF(OR(Q53<=2, V53="Cancelled"), "Blacklisted", IF(AND(P53>=100000, Q53>=4, O53<=10, V53="Completed"), "Platinum", IF(AND(P53>=50000, P53<=99999, Q53>=3, V53="Completed"), "Gold", IF(AND(P53<50000, V53="Completed"), "Silver", "Pending")))) -> Blacklisted
A54: ORD10053 | B54: C005 | C54: P101 | D54: 19/08/2025 | E54: 23/08/2025 | F54: Vikas Mehta | G54: Male | H54: 17/01/1976 | I54: Kolkata | J54: East | K54: Electronics | L54: Laptop | M54: 12 | N54: 55000 | O54: 5 | P54: 627000 | Q54: 2 | R54: UPI | S54: Rahul | T54: vikas.mehta@company.com | U54: 9350554626 | V54: Pending | W54: =IF(OR(Q54<=2, V54="Cancelled"), "Blacklisted", IF(AND(P54>=100000, Q54>=4, O54<=10, V54="Completed"), "Platinum", IF(AND(P54>=50000, P54<=99999, Q54>=3, V54="Completed"), "Gold", IF(AND(P54<50000, V54="Completed"), "Silver", "Pending")))) -> Blacklisted
A55: ORD10054 | B55: C008 | C55: P102 | D55: 27/07/2025 | E55: 05/08/2025 | F55: Kavya Nair | G55: Female | H55: 04/04/1975 | I55: Jaipur | J55: North | K55: Electronics | L55: Mouse | M55: 3 | N55: 700 | O55: 0 | P55: 2100 | Q55: 3 | R55: Card | S55: Karan | T55: kavya.nair@company.com | U55: 9743295580 | V55: Cancelled | W55: =IF(OR(Q55<=2, V55="Cancelled"), "Blacklisted", IF(AND(P55>=100000, Q55>=4, O55<=10, V55="Completed"), "Platinum", IF(AND(P55>=50000, P55<=99999, Q55>=3, V55="Completed"), "Gold", IF(AND(P55<50000, V55="Completed"), "Silver", "Pending")))) -> Blacklisted
A56: ORD10055 | B56: C003 | C56: P301 | D56: 21/02/2025 | E56: 26/02/2025 | F56: RoHit Singh | G56: Male | H56: 11/12/1976 | I56: Ahmedabad | J56: West | K56: Stationery | L56: Notebook | M56: 19 | N56: 60 | O56: 15 | P56: 969 | Q56: 4 | R56: Card | S56: Rahul | T56: rohit.singh@company.com | U56: 9822926495 | V56: Cancelled | W56: =IF(OR(Q56<=2, V56="Cancelled"), "Blacklisted", IF(AND(P56>=100000, Q56>=4, O56<=10, V56="Completed"), "Platinum", IF(AND(P56>=50000, P56<=99999, Q56>=3, V56="Completed"), "Gold", IF(AND(P56<50000, V56="Completed"), "Silver", "Pending")))) -> Blacklisted
A57: ORD10056 | B57: C001 | C57: P301 | D57: 10/08/2025 | E57: 11/08/2025 | F57: Amit Sharma | G57: Male | H57: 03/12/1979 | I57: Jaipur | J57: North | K57: Stationery | L57: Notebook | M57: 9 | N57: 60 | O57: 20 | P57: 432 | Q57: 1 | R57: NetBanking | S57: Neha | T57: amit.sharma@company.com | U57: 9518298190 | V57: Pending | W57: =IF(OR(Q57<=2, V57="Cancelled"), "Blacklisted", IF(AND(P57>=100000, Q57>=4, O57<=10, V57="Completed"), "Platinum", IF(AND(P57>=50000, P57<=99999, Q57>=3, V57="Completed"), "Gold", IF(AND(P57<50000, V57="Completed"), "Silver", "Pending")))) -> Blacklisted
A58: ORD10057 | B58: C001 | C58: P102 | D58: 24/03/2026 | E58: 30/03/2026 | F58: Amit Sharma | G58: Male | H58: 27/12/1978 | I58: Bengaluru | J58: South | K58: Electronics | L58: Mouse | M58: 6 | N58: 700 | O58: 0 | P58: 4200 | Q58: 4 | R58: UPI | S58: Rahul | T58: amit.sharmcompany.com | U58: 9366223547 | V58: Cancelled | W58: =IF(OR(Q58<=2, V58="Cancelled"), "Blacklisted", IF(AND(P58>=100000, Q58>=4, O58<=10, V58="Completed"), "Platinum", IF(AND(P58>=50000, P58<=99999, Q58>=3, V58="Completed"), "Gold", IF(AND(P58<50000, V58="Completed"), "Silver", "Pending")))) -> Blacklisted
A59: ORD10058 | B59: C003 | C59: P303 | D59: 13/03/2026 | E59: 19/03/2026 | F59: Rohit Singh | G59: Male | H59: 15/04/1975 | I59: Delhi | J59: North | K59: Stationery | L59: Marker | M59: 18 | N59: 45 | O59: 5 | P59: 769.5 | Q59: 1 | R59: Card | S59: Aisha | T59: rohit.singh@company.com | U59: 9701988524 | V59: Pending | W59: =IF(OR(Q59<=2, V59="Cancelled"), "Blacklisted", IF(AND(P59>=100000, Q59>=4, O59<=10, V59="Completed"), "Platinum", IF(AND(P59>=50000, P59<=99999, Q59>=3, V59="Completed"), "Gold", IF(AND(P59<50000, V59="Completed"), "Silver", "Pending")))) -> Blacklisted
A60: ORD10059 | B60: C007 | C60: P302 | D60: 15/06/2025 | E60: 26/06/2025 | F60: Arjun Rao | G60: Male | H60: 19/12/1988 | I60: Jaipur | J60: North | K60: Stationery | L60: Pen | M60: 8 | N60: 20 | O60: 5 | P60: 152 | Q60: 1 | R60: Card | S60: Ritika | T60: arjun.rao@company.com | U60: 9836327649 | V60: completed | W60: =IF(OR(Q60<=2, V60="Cancelled"), "Blacklisted", IF(AND(P60>=100000, Q60>=4, O60<=10, V60="Completed"), "Platinum", IF(AND(P60>=50000, P60<=99999, Q60>=3, V60="Completed"), "Gold", IF(AND(P60<50000, V60="Completed"), "Silver", "Pending")))) -> Blacklisted
A61: ORD10060 | B61: C005 | C61: P102 | D61: 05/03/2025 | E61: 06/03/2025 | F61: Vikas Mehta | G61: Male | H61: 07/03/1979 | I61: Jaipur | J61: North | K61: Electronics | L61: Mouse | M61: 8 | N61: 700 | O61: 10 | P61: 5040 | Q61: 1 | R61: NetBanking | S61: Aisha | T61: Vikas.mehta@company.com | U61: 9261800516 | V61: Cancelled | W61: =IF(OR(Q61<=2, V61="Cancelled"), "Blacklisted", IF(AND(P61>=100000, Q61>=4, O61<=10, V61="Completed"), "Platinum", IF(AND(P61>=50000, P61<=99999, Q61>=3, V61="Completed"), "Gold", IF(AND(P61<50000, V61="Completed"), "Silver", "Pending")))) -> Blacklisted
A62: ORD10061 | B62: C008 | C62: P302 | D62: 09/04/2026 | E62: 19/04/2026 | F62: Kavya Nair | G62: Female | H62: 17/12/2003 | I62: Delhi | J62: North | K62: Stationery | L62: Pen | M62: 7 | N62: 20 | O62: 15 | P62: 119 | Q62: 5 | R62: Card | S62: Rahul | T62: kavya.nair@company.com | U62: 9950802015 | V62: Completed | W62: =IF(OR(Q62<=2, V62="Cancelled"), "Blacklisted", IF(AND(P62>=100000, Q62>=4, O62<=10, V62="Completed"), "Platinum", IF(AND(P62>=50000, P62<=99999, Q62>=3, V62="Completed"), "Gold", IF(AND(P62<50000, V62="Completed"), "Silver", "Pending")))) -> Silver
... A74: ORD10073 | B74: C008 | C74: P103 | D74: 13/12/2025 | E74: 23/12/2025 | F74: Kavya Nair | G74: Female | H74: 22/09/1981 | I74: Jaipur | J74: North | K74: Electronics | L74: Keyboard | M74: 1 | N74: 1200 | O74: 5 | P74: 1140 | Q74: 3 | R74: UPI | S74: Aisha | T74: kavya.nair@company.com | U74: 9808988530 | V74: Cancelled | W74: =IF(OR(Q74<=2, V74="Cancelled"), "Blacklisted", IF(AND(P74>=100000, Q74>=4, O74<=10, V74="Completed"), "Platinum", IF(AND(P74>=50000, P74<=99999, Q74>=3, V74="Completed"), "Gold", IF(AND(P74<50000, V74="Completed"), "Silver", "Pending")))) -> Blacklisted
A75: ORD10074 | B75: C010 | C75: P202 | D75: 04/02/2026 | E75: 16/02/2026 | F75: Pooja Shah | G75: Female | H75: 20/06/1980 | J75: South | K75: Home Appliances | L75: Iron | M75: 1 | N75: 2200 | O75: 15 | P75: 1870 | Q75: 4 | R75: Card | S75: Aisha | T75: pooja.shah@company.com | U75: 9286410494 | V75: Completed | W75: =IF(OR(Q75<=2, V75="Cancelled"), "Blacklisted", IF(AND(P75>=100000, Q75>=4, O75<=10, V75="Completed"), "Platinum", IF(AND(P75>=50000, P75<=99999, Q75>=3, V75="Completed"), "Gold", IF(AND(P75<50000, V75="Completed"), "Silver", "Pending")))) -> Silver
A76: ORD10075 | B76: C003 | C76: P103 | D76: 26/01/2026 | E76: 28/01/2026 | F76: Rohit Singh | G76: Male | H76: 02/11/1982 | I76: Pune | J76: West | K76: Electronics | L76: Keyboard | M76: 3 | N76: 1200 | O76: 10 | P76: 3240 | Q76: 5 | R76: Cash | S76: Rahul | T76: rohit.singh@company.com | U76: 9311555196 | V76: Completed | W76: =IF(OR(Q76<=2, V76="Cancelled"), "Blacklisted", IF(AND(P76>=100000, Q76>=4, O76<=10, V76="Completed"), "Platinum", IF(AND(P76>=50000, P76<=99999, Q76>=3, V76="Completed"), "Gold", IF(AND(P76<50000, V76="Completed"), "Silver", "Pending")))) -> Silver
A77: ORD10076 | B77: C008 | C77: P201 | D77: 27/06/2025 | E77: 07/07/2025 | F77: Kavya Nair | G77: Female | H77: 10/01/1980 | I77: Bengaluru | J77: South | K77: Home Appliances | L77: Mixer | M77: 10 | N77: 3500 | O77: 20 | P77: 28000 | Q77: 5 | R77: Card | S77: Ritika | T77: kavya.nair@company.com | U77: 9101810266 | V77: Completed | W77: =IF(OR(Q77<=2, V77="Cancelled"), "Blacklisted", IF(AND(P77>=100000, Q77>=4, O77<=10, V77="Completed"), "Platinum", IF(AND(P77>=50000, P77<=99999, Q77>=3, V77="Completed"), "Gold", IF(AND(P77<50000, V77="Completed"), "Silver", "Pending")))) -> Silver
A78: ORD10077 | B78: C007 | C78: P102 | D78: 17/03/2026 | E78: 19/03/2026 | F78: Arjun Rao | G78: Male | H78: 27/04/1981 | I78: Delhi | J78: North | K78: Electronics | L78: Mouse | M78: 18 | N78: 700 | O78: 5 | P78: 11970 | Q78: 3 | R78: Card | S78: Neha | T78: arjun.rao@company.com | U78: 9464556593 | V78: Cancelled | W78: =IF(OR(Q78<=2, V78="Cancelled"), "Blacklisted", IF(AND(P78>=100000, Q78>=4, O78<=10, V78="Completed"), "Platinum", IF(AND(P78>=50000, P78<=99999, Q78>=3, V78="Completed"), "Gold", IF(AND(P78<50000, V78="Completed"), "Silver", "Pending")))) -> Blacklisted
A79: ORD10078 | B79: C005 | C79: P102 | D79: 09/06/2025 | E79: 18/06/2025 | F79: Vikas Mehta | G79: Male | H79: 12/03/1985 | I79: Bengaluru | J79: South | K79: Electronics | L79: Mouse | M79: 12 | N79: 700 | O79: 15 | P79: 7140 | Q79: 2 | R79: UPI | S79: Rahul | T79: vikas.mehta@company.com | U79: 9338278358 | V79: Completed | W79: =IF(OR(Q79<=2, V79="Cancelled"), "Blacklisted", IF(AND(P79>=100000, Q79>=4, O79<=10, V79="Completed"), "Platinum", IF(AND(P79>=50000, P79<=99999, Q79>=3, V79="Completed"), "Gold", IF(AND(P79<50000, V79="Completed"), "Silver", "Pending")))) -> Blacklisted
A80: ORD10079 | B80: C009 | C80: P103 | D80: 15/11/2025 | E80: 16/11/2025 | F80: Mohit Verma | G80: Male | H80: 15/03/1999 | I80: Mumbai | J80: West | K80: Electronics | L80: Keyboard | M80: 8 | N80: 1200 | O80: 0 | P80: 9600 | Q80: 4 | R80: Card | S80: Rahul | T80: mohit.verma@company.com | U80: 9621410770 | V80: Pending | W80: =IF(OR(Q80<=2, V80="Cancelled"), "Blacklisted", IF(AND(P80>=100000, Q80>=4, O80<=10, V80="Completed"), "Platinum", IF(AND(P80>=50000, P80<=99999, Q80>=3, V80="Completed"), "Gold", IF(AND(P80<50000, V80="Completed"), "Silver", "Pending")))) -> Pending
A81: ORD10080 | B81: C003 | C81: P301 | D81: 06/11/2025 | E81: 10/11/2025 | F81: Rohit Singh | G81: Male | H81: 07/07/1983 | I81: Pune | J81: West | K81: Stationery | L81: Notebook | M81: 2 | N81: 60 | O81: 0 | P81: 120 | Q81: 2 | R81: UPI | S81: Rahul | T81: rohit.singh@company.com | U81: 9981333189 | V81: Completed | W81: =IF(OR(Q81<=2, V81="Cancelled"), "Blacklisted", IF(AND(P81>=100000, Q81>=4, O81<=10, V81="Completed"), "Platinum", IF(AND(P81>=50000, P81<=99999, Q81>=3, V81="Completed"), "Gold", IF(AND(P81<50000, V81="Completed"), "Silver", "Pending")))) -> Blacklisted
A82: ORD10081 | B82: C001 | C82: P303 | D82: 01/01/2025 | E82: 07/01/2025 | F82: Amit Sharma | G82: Male | H82: 06/03/1989 | I82: Pune | J82: West | K82: Stationery | L82: Marker | M82: 10 | N82: 45 | O82: 15 | P82: 382.5 | Q82: 3 | R82: NetBanking | S82: Ritika | T82: amit.sharma@company.com | U82: 9723450355 | V82: Cancelled | W82: =IF(OR(Q82<=2, V82="Cancelled"), "Blacklisted", IF(AND(P82>=100000, Q82>=4, O82<=10, V82="Completed"), "Platinum", IF(AND(P82>=50000, P82<=99999, Q82>=3, V82="Completed"), "Gold", IF(AND(P82<50000, V82="Completed"), "Silver", "Pending")))) -> Blacklisted
A83: ORD10082 | B83: C005 | C83: P201 | D83: 25/04/2026 | E83: 03/05/2026 | F83: Vikas Mehta | G83: Male | H83: 20/06/1982 | I83: Kolkata | J83: East | K83: Home Appliances | L83: Mixer | M83: 12 | N83: 3500 | O83: 5 | P83: 39900 | Q83: 3 | R83: NetBanking | S83: Aisha | T83: vikas.mehta@company.com | U83: 9886243907 | V83: Pending | W83: =IF(OR(Q83<=2, V83="Cancelled"), "Blacklisted", IF(AND(P83>=100000, Q83>=4, O83<=10, V83="Completed"), "Platinum", IF(AND(P83>=50000, P83<=99999, Q83>=3, V83="Completed"), "Gold", IF(AND(P83<50000, V83="Completed"), "Silver", "Pending")))) -> Pending
A84: ORD10083 | B84: C003 | C84: P301 | D84: 19/09/2025 | E84: 27/09/2025 | F84: Rohit Singh | G84: Male | H84: 23/06/2001 | I84: Mumbai | J84: West | K84: Stationery | L84: Notebook | M84: 2 | N84: 60 | O84: 15 | P84: 102 | Q84: 1 | R84: UPI | S84: Neha | T84: rohit.singh@company.com | U84: 9473931904 | V84: Completed | W84: =IF(OR(Q84<=2, V84="Cancelled"), "Blacklisted", IF(AND(P84>=100000, Q84>=4, O84<=10, V84="Completed"), "Platinum", IF(AND(P84>=50000, P84<=99999, Q84>=3, V84="Completed"), "Gold", IF(AND(P84<50000, V84="Completed"), "Silver", "Pending")))) -> Blacklisted
A85: ORD10084 | B85: C003 | C85: P103 | D85: 18/03/2025 | E85: 21/03/2025 | F85: Rohit Singh | G85: Male | H85: 19/07/1983 | I85: Hyderabad | J85: South | K85: Electronics | L85: Keyboard | M85: 18 | N85: 1200 | O85: 15 | P85: 18360 | Q85: 3 | R85: Card | S85: Neha | T85: rohit.singh@company.com | U85: 9287159610 | V85: Pending | W85: =IF(OR(Q85<=2, V85="Cancelled"), "Blacklisted", IF(AND(P85>=100000, Q85>=4, O85<=10, V85="Completed"), "Platinum", IF(AND(P85>=50000, P85<=99999, Q85>=3, V85="Completed"), "Gold", IF(AND(P85<50000, V85="Completed"), "Silver", "Pending")))) -> Pending
A86: ORD10085 | B86: C008 | C86: P104 | D86: 30/10/2025 | E86: 31/10/2025 | F86: Kavya Nair | G86: Female | H86: 24/03/1993 | I86: Mumbai | J86: West | K86: Electronics | L86: Monitor | M86: 18 | N86: 12000 | O86: 15 | P86: 183600 | Q86: 2 | R86: Cash | S86: Rahul | T86: kavya.nair@company.com | U86: 9876513858 | V86: Completed | W86: =IF(OR(Q86<=2, V86="Cancelled"), "Blacklisted", IF(AND(P86>=100000, Q86>=4, O86<=10, V86="Completed"), "Platinum", IF(AND(P86>=50000, P86<=99999, Q86>=3, V86="Completed"), "Gold", IF(AND(P86<50000, V86="Completed"), "Silver", "Pending")))) -> Blacklisted
A87: ORD10086 | B87: C007 | C87: P302 | D87: 31/10/2025 | E87: 11/11/2025 | F87: Arjun Rao | G87: Male | H87: 10/05/1995 | I87: Ahmedabad | J87: West | K87: Stationery | L87: Pen | M87: 7 | N87: 20 | O87: 0 | P87: 140 | Q87: 2 | R87: Card | S87: Ritika | T87: arjun.rao@company.com | U87: 9237400853 | V87: Cancelled | W87: =IF(OR(Q87<=2, V87="Cancelled"), "Blacklisted", IF(AND(P87>=100000, Q87>=4, O87<=10, V87="Completed"), "Platinum", IF(AND(P87>=50000, P87<=99999, Q87>=3, V87="Completed"), "Gold", IF(AND(P87<50000, V87="Completed"), "Silver", "Pending")))) -> Blacklisted
... A119: ORD10118 | B119: C001 | C119: P303 | D119: 31/05/2025 | E119: 11/06/2025 | F119: Amit Sharma | G119: Male | H119: 07/09/1995 | I119: Pune | J119: West | K119: Stationery | L119: Marker | M119: 16 | N119: 45 | O119: 0 | P119: 720 | Q119: 1 | R119: NetBanking | S119: Aisha | T119: amit.sharma@company.com | U119: 9807154421 | V119: Completed | W119: =IF(OR(Q119<=2, V119="Cancelled"), "Blacklisted", IF(AND(P119>=100000, Q119>=4, O119<=10, V119="Completed"), "Platinum", IF(AND(P119>=50000, P119<=99999, Q119>=3, V119="Completed"), "Gold", IF(AND(P119<50000, V119="Completed"), "Silver", "Pending")))) -> Blacklisted
A120: ORD10119 | B120: C009 | C120: P103 | D120: 30/05/2025 | E120: 02/06/2025 | F120: Mohit Verma | G120: Male | H120: 08/03/1988 | I120: Ahmedabad | J120: West | K120: Electronics | L120: Keyboard | M120: Ten | N120: 1200 | O120: 15 | P120: 7140 | Q120: 4 | R120: UPI | S120: Karan | T120: mohit.verma@company.com | U120: 9919834000 | V120: Pending | W120: =IF(OR(Q120<=2, V120="Cancelled"), "Blacklisted", IF(AND(P120>=100000, Q120>=4, O120<=10, V120="Completed"), "Platinum", IF(AND(P120>=50000, P120<=99999, Q120>=3, V120="Completed"), "Gold", IF(AND(P120<50000, V120="Completed"), "Silver", "Pending")))) -> Pending
A121: ORD10120 | B121: C002 | C121: P104 | D121: 19/08/2025 | E121: 30/08/2025 | F121: Priya Patel | G121: Female | H121: 07/07/1989 | I121: Jaipur | J121: North | K121: Electronics | L121: Monitor | M121: 14 | N121: 12000 | O121: 15 | P121: 142800 | Q121: 2 | R121: NetBanking | S121: Aisha | T121: priya.patel@company.com | U121: 9739798818 | V121: Pending | W121: =IF(OR(Q121<=2, V121="Cancelled"), "Blacklisted", IF(AND(P121>=100000, Q121>=4, O121<=10, V121="Completed"), "Platinum", IF(AND(P121>=50000, P121<=99999, Q121>=3, V121="Completed"), "Gold", IF(AND(P121<50000, V121="Completed"), "Silver", "Pending")))) -> Blacklisted
A122: ORD10121 | B122: C003 | C122: P203 | D122: 14/12/2025 | E122: 16/12/2025 | F122: Rohit Singh | G122: Male | H122: 11/11/1993 | I122: Pune | J122: West | K122: Home Appliances | L122: Microwave | M122: 8 | N122: 8500 | O122: 20 | P122: 54400 | Q122: 3 | R122: Card | S122: Rahul | T122: rohit.singh@company.com | U122: 9208625306 | V122: Completed | W122: =IF(OR(Q122<=2, V122="Cancelled"), "Blacklisted", IF(AND(P122>=100000, Q122>=4, O122<=10, V122="Completed"), "Platinum", IF(AND(P122>=50000, P122<=99999, Q122>=3, V122="Completed"), "Gold", IF(AND(P122<50000, V122="Completed"), "Silver", "Pending")))) -> Gold
A123: ORD10122 | B123: C007 | C123: P303 | D123: 31/01/2026 | E123: 10/02/2026 | F123: Arjun Rao | G123: Male | H123: 01/02/2000 | I123: Bengaluru | J123: South | K123: Stationery | L123: Marker | M123: 3 | N123: 45 | O123: 0 | P123: 135 | Q123: 4 | R123: UPI | S123: Aisha | T123: arjun.rao@company.com | U123: 9970178536 | V123: Cancelled | W123: =IF(OR(Q123<=2, V123="Cancelled"), "Blacklisted", IF(AND(P123>=100000, Q123>=4, O123<=10, V123="Completed"), "Platinum", IF(AND(P123>=50000, P123<=99999, Q123>=3, V123="Completed"), "Gold", IF(AND(P123<50000, V123="Completed"), "Silver", "Pending")))) -> Blacklisted
A124: ORD10123 | B124: C001 | C124: P102 | D124: 03/01/2026 | E124: 04/01/2026 | F124: Amit Sharma | G124: Male | H124: 22/06/1986 | I124: Jaipur | J124: North | K124: Electronics | L124: Mouse | M124: 13 | N124: 700 | O124: 5 | P124: 8645 | Q124: 3 | R124: Card | S124: Neha | T124: amit.sharma@company.com | U124: 9633745195 | V124: Pending | W124: =IF(OR(Q124<=2, V124="Cancelled"), "Blacklisted", IF(AND(P124>=100000, Q124>=4, O124<=10, V124="Completed"), "Platinum", IF(AND(P124>=50000, P124<=99999, Q124>=3, V124="Completed"), "Gold", IF(AND(P124<50000, V124="Completed"), "Silver", "Pending")))) -> Pending
A125: ORD10124 | B125: C004 | C125: P103 | D125: 20/10/2025 | E125: 26/10/2025 | F125: Anita Gupta | G125: Female | H125: 16/02/1986 | I125: Mumbai | J125: West | K125: Electronics | L125: Keyboard | M125: 14 | N125: 1200 | O125: 20 | P125: 13440 | Q125: 5 | R125: NetBanking | S125: Aisha | T125: anita.gupta@company.com | U125: 9922102053 | V125: Completed | W125: =IF(OR(Q125<=2, V125="Cancelled"), "Blacklisted", IF(AND(P125>=100000, Q125>=4, O125<=10, V125="Completed"), "Platinum", IF(AND(P125>=50000, P125<=99999, Q125>=3, V125="Completed"), "Gold", IF(AND(P125<50000, V125="Completed"), "Silver", "Pending")))) -> Silver
A126: ORD10125 | B126: C002 | C126: P303 | D126: 11/05/2025 | E126: 21/05/2025 | F126: Priya Patel | G126: Female | H126: 18/09/1991 | I126: Delhi | J126: North | K126: Stationery | L126: Marker | M126: 2 | N126: 45 | O126: 5 | P126: 85.5 | Q126: 3 | R126: UPI | S126: Ritika | T126: priya.patel@company.com | U126: 9135963930 | V126: Cancelled | W126: =IF(OR(Q126<=2, V126="Cancelled"), "Blacklisted", IF(AND(P126>=100000, Q126>=4, O126<=10, V126="Completed"), "Platinum", IF(AND(P126>=50000, P126<=99999, Q126>=3, V126="Completed"), "Gold", IF(AND(P126<50000, V126="Completed"), "Silver", "Pending")))) -> Blacklisted
A127: ORD10126 | B127: C004 | C127: P103 | D127: 02/01/2026 | E127: 06/01/2026 | F127: Anita Gupta | G127: Female | H127: 04/01/1981 | I127: Bengaluru | J127: South | K127: Electronics | L127: Keyboard | M127: 2 | N127: 1200 | O127: 20 | P127: 1920 | Q127: 3 | R127: Card | S127: Neha | T127: anita.gupta@company.com | U127: 9429405275 | V127: Completed | W127: =IF(OR(Q127<=2, V127="Cancelled"), "Blacklisted", IF(AND(P127>=100000, Q127>=4, O127<=10, V127="Completed"), "Platinum", IF(AND(P127>=50000, P127<=99999, Q127>=3, V127="Completed"), "Gold", IF(AND(P127<50000, V127="Completed"), "Silver", "Pending")))) -> Silver
A128: ORD10127 | B128: C003 | C128: P101 | D128: 20/04/2026 | E128: 26/04/2026 | F128: Rohit Singh | G128: Male | H128: 12/10/2004 | I128: Bengaluru | J128: South | K128: Electronics | L128: Laptop | M128: 10 | N128: 55000 | O128: 5 | P128: 522500 | Q128: 5 | R128: UPI | S128: Aisha | T128: rohit.singh@company.com | U128: 9521757571 | V128: Pending | W128: =IF(OR(Q128<=2, V128="Cancelled"), "Blacklisted", IF(AND(P128>=100000, Q128>=4, O128<=10, V128="Completed"), "Platinum", IF(AND(P128>=50000, P128<=99999, Q128>=3, V128="Completed"), "Gold", IF(AND(P128<50000, V128="Completed"), "Silver", "Pending")))) -> Pending
A129: ORD10128 | B129: C006 | C129: P201 | D129: 04/08/2025 | E129: 05/08/2025 | F129: Sneha Joshi | G129: Female | H129: 25/03/1984 | I129: Jaipur | J129: North | K129: Home Appliances | L129: Mixer | M129: 15 | N129: 3500 | O129: 10 | P129: 47250 | Q129: 3 | R129: NetBanking | S129: Neha | T129: sneha.joshi@company.com | U129: 9467375455 | V129: Completed | W129: =IF(OR(Q129<=2, V129="Cancelled"), "Blacklisted", IF(AND(P129>=100000, Q129>=4, O129<=10, V129="Completed"), "Platinum", IF(AND(P129>=50000, P129<=99999, Q129>=3, V129="Completed"), "Gold", IF(AND(P129<50000, V129="Completed"), "Silver", "Pending")))) -> Silver
A130: ORD10129 | B130: C002 | C130: P202 | D130: 13/08/2025 | E130: 18/08/2025 | F130: Priya Patel | G130: Female | H130: 09/09/1982 | I130: Bengaluru | J130: South | K130: Home Appliances | L130: Iron | M130: 10 | N130: 2200 | O130: 15 | P130: 18700 | Q130: 4 | R130: Card | S130: Rahul | T130: priya.patel@company.com | U130: 9838809695 | V130: Pending | W130: =IF(OR(Q130<=2, V130="Cancelled"), "Blacklisted", IF(AND(P130>=100000, Q130>=4, O130<=10, V130="Completed"), "Platinum", IF(AND(P130>=50000, P130<=99999, Q130>=3, V130="Completed"), "Gold", IF(AND(P130<50000, V130="Completed"), "Silver", "Pending")))) -> Pending
A131: ORD10130 | B131: C006 | C131: P201 | D131: 16/06/2025 | E131: 24/06/2025 | F131: Sneha Joshi | G131: Female | H131: 15/02/1993 | I131: Pune | J131: West | K131: Home Appliances | L131: Mixer | M131: 11 | N131: 3500 | O131: 5 | P131: 36575 | Q131: 5 | R131: Cash | S131: Ritika | T131: sneha.joshi@company.com | U131: 9296609782 | V131: Cancelled | W131: =IF(OR(Q131<=2, V131="Cancelled"), "Blacklisted", IF(AND(P131>=100000, Q131>=4, O131<=10, V131="Completed"), "Platinum", IF(AND(P131>=50000, P131<=99999, Q131>=3, V131="Completed"), "Gold", IF(AND(P131<50000, V131="Completed"), "Silver", "Pending")))) -> Blacklisted
A132: ORD10131 | B132: C004 | C132: P103 | D132: 27/04/2026 | E132: 30/04/2026 | F132: Anita Gupta | G132: Female | H132: 08/04/2003 | I132: Bengaluru | J132: South | K132: Electronics | L132: Keyboard | M132: 14 | N132: 1200 | O132: 0 | P132: 16800 | Q132: 5 | R132: Cash | S132: Rahul | T132: anita.gupta@company.com | U132: 9848259992 | V132: Cancelled | W132: =IF(OR(Q132<=2, V132="Cancelled"), "Blacklisted", IF(AND(P132>=100000, Q132>=4, O132<=10, V132="Completed"), "Platinum", IF(AND(P132>=50000, P132<=99999, Q132>=3, V132="Completed"), "Gold", IF(AND(P132<50000, V132="Completed"), "Silver", "Pending")))) -> Blacklisted
... A299: ORD10298 | B299: C003 | C299: P101 | D299: 13/01/2025 | E299: 16/01/2025 | F299: Rohit Singh | G299: Male | H299: 03/01/2004 | I299: Hyderabad | J299: South | K299: Electronics | L299: Laptop | M299: 11 | N299: 55000 | O299: 5 | P299: 574750 | Q299: 1 | R299: UPI | S299: Ritika | T299: rohit.singh@company.com | U299: 9482699727 | V299: Cancelled | W299: =IF(OR(Q299<=2, V299="Cancelled"), "Blacklisted", IF(AND(P299>=100000, Q299>=4, O299<=10, V299="Completed"), "Platinum", IF(AND(P299>=50000, P299<=99999, Q299>=3, V299="Completed"), "Gold", IF(AND(P299<50000, V299="Completed"), "Silver", "Pending")))) -> Blacklisted
A300: ORD10299 | B300: C007 | C300: P201 | D300: 05/10/2025 | E300: 17/10/2025 | F300: Arjun Rao | G300: Male | H300: 02/05/1992 | I300: Jaipur | J300: North | K300: Home Appliances | L300: Mixer | M300: 12 | N300: 3500 | O300: 0 | P300: 42000 | Q300: 2 | R300: NetBanking | T300: arjun.rao@company.com | U300: 9332473934 | V300: Pending | W300: =IF(OR(Q300<=2, V300="Cancelled"), "Blacklisted", IF(AND(P300>=100000, Q300>=4, O300<=10, V300="Completed"), "Platinum", IF(AND(P300>=50000, P300<=99999, Q300>=3, V300="Completed"), "Gold", IF(AND(P300<50000, V300="Completed"), "Silver", "Pending")))) -> Blacklisted
A301: ORD10300 | B301: C009 | C301: P303 | D301: 25/02/2026 | E301: 08/03/2026 | F301: Mohit Verma | G301: Male | H301: 26/01/2003 | I301: Hyderabad | J301: South | K301: Stationery | L301: Marker | M301: 15 | N301: 45 | O301: 10 | P301: 607.5 | Q301: 2 | R301: Cash | S301: Karan | T301: mohit.verma@company.com | U301: 9647657382 | V301: Pending | W301: =IF(OR(Q301<=2, V301="Cancelled"), "Blacklisted", IF(AND(P301>=100000, Q301>=4, O301<=10, V301="Completed"), "Platinum", IF(AND(P301>=50000, P301<=99999, Q301>=3, V301="Completed"), "Gold", IF(AND(P301<50000, V301="Completed"), "Silver", "Pending")))) -> Blacklisted
A302: ORD10301 | B302: C001 | C302: P303 | D302: 16/05/2025 | E302: 26/05/2025 | F302: Amit Sharma | G302: Male | H302: 20/05/1987 | I302: Bengaluru | J302: South | K302: Stationery | L302: Marker | M302: 13 | N302: 45 | O302: 0 | P302: 585 | Q302: 5 | R302: NetBanking | S302: Rahul | T302: amit.sharma@company.com | U302: 9736797776 | V302: Pending | W302: =IF(OR(Q302<=2, V302="Cancelled"), "Blacklisted", IF(AND(P302>=100000, Q302>=4, O302<=10, V302="Completed"), "Platinum", IF(AND(P302>=50000, P302<=99999, Q302>=3, V302="Completed"), "Gold", IF(AND(P302<50000, V302="Completed"), "Silver", "Pending")))) -> Pending
A303: ORD10302 | B303: C003 | C303: P101 | D303: 02/01/2026 | E303: 05/01/2026 | F303: Rohit Singh | G303: Male | H303: 07/09/1975 | I303: Bengaluru | J303: South | K303: Electronics | L303: Laptop | M303: 8 | N303: 55000 | O303: 0 | P303: 440000 | Q303: 2 | R303: UPI | S303: Karan | T303: rohit.singh@company.com | U303: 9745773533 | V303: Cancelled | W303: =IF(OR(Q303<=2, V303="Cancelled"), "Blacklisted", IF(AND(P303>=100000, Q303>=4, O303<=10, V303="Completed"), "Platinum", IF(AND(P303>=50000, P303<=99999, Q303>=3, V303="Completed"), "Gold", IF(AND(P303<50000, V303="Completed"), "Silver", "Pending")))) -> Blacklisted
A304: ORD10303 | B304: C006 | C304: P101 | D304: 23/07/2025 | E304: 27/07/2025 | F304: Sneha Joshi | G304: Female | H304: 10/08/1980 | I304: Delhi | J304: North | K304: Electronics | L304: Laptop | M304: 4 | N304: 55000 | O304: 20 | P304: 176000 | Q304: 5 | R304: Cash | S304: Rahul | T304: sneha.joshi@company.com | U304: 9246715757 | V304: Pending | W304: =IF(OR(Q304<=2, V304="Cancelled"), "Blacklisted", IF(AND(P304>=100000, Q304>=4, O304<=10, V304="Completed"), "Platinum", IF(AND(P304>=50000, P304<=99999, Q304>=3, V304="Completed"), "Gold", IF(AND(P304<50000, V304="Completed"), "Silver", "Pending")))) -> Pending
A305: ORD10304 | B305: C008 | C305: P201 | D305: 23/04/2026 | E305: 26/04/2026 | F305: Kavya Nair | G305: Female | H305: 07/04/1989 | I305: Ahmedabad | J305: West | K305: Home Appliances | L305: Mixer | M305: 19 | N305: 3500 | O305: 5 | P305: 63175 | Q305: 1 | R305: Card | S305: Neha | T305: kavya.nair@company.com | U305: 9904065774 | V305: Completed | W305: =IF(OR(Q305<=2, V305="Cancelled"), "Blacklisted", IF(AND(P305>=100000, Q305>=4, O305<=10, V305="Completed"), "Platinum", IF(AND(P305>=50000, P305<=99999, Q305>=3, V305="Completed"), "Gold", IF(AND(P305<50000, V305="Completed"), "Silver", "Pending")))) -> Blacklisted
A306: ORD10305 | B306: C005 | C306: P103 | D306: 02/03/2025 | E306: 06/03/2025 | F306: Vikas Mehta | G306: Male | H306: 20/08/1998 | I306: Jaipur | J306: North | K306: Electronics | L306: Keyboard | M306: 17 | N306: 1200 | O306: 15 | P306: 17340 | Q306: 2 | R306: NetBanking | S306: Rahul | T306: vikas.mehta@company.com | U306: 9652985385 | V306: Completed | W306: =IF(OR(Q306<=2, V306="Cancelled"), "Blacklisted", IF(AND(P306>=100000, Q306>=4, O306<=10, V306="Completed"), "Platinum", IF(AND(P306>=50000, P306<=99999, Q306>=3, V306="Completed"), "Gold", IF(AND(P306<50000, V306="Completed"), "Silver", "Pending")))) -> Blacklisted
A307: ORD10306 | B307: C008 | C307: P202 | D307: 09/02/2026 | E307: 17/02/2026 | F307: Kavya Nair | G307: Female | H307: 03/04/2001 | I307: Hyderabad | J307: South | K307: Home Appliances | L307: Iron | M307: 8 | N307: 2200 | O307: 5 | P307: 16720 | Q307: 3 | R307: Card | S307: Neha | T307: kavya.nair@company.com | U307: 9427001508 | V307: Pending | W307: =IF(OR(Q307<=2, V307="Cancelled"), "Blacklisted", IF(AND(P307>=100000, Q307>=4, O307<=10, V307="Completed"), "Platinum", IF(AND(P307>=50000, P307<=99999, Q307>=3, V307="Completed"), "Gold", IF(AND(P307<50000, V307="Completed"), "Silver", "Pending")))) -> Pending
A308: ORD10307 | B308: C006 | C308: P102 | D308: 16/02/2025 | E308: 26/02/2025 | F308: Sneha Joshi | G308: Female | H308: 05/03/1992 | I308: Mumbai | J308: West | K308: Electronics | L308: Mouse | M308: 17 | N308: 700 | O308: 20 | P308: 9520 | Q308: 4 | R308: NetBanking | S308: Neha | T308: sneha.joshi@company.com | U308: 9666803655 | V308: Completed | W308: =IF(OR(Q308<=2, V308="Cancelled"), "Blacklisted", IF(AND(P308>=100000, Q308>=4, O308<=10, V308="Completed"), "Platinum", IF(AND(P308>=50000, P308<=99999, Q308>=3, V308="Completed"), "Gold", IF(AND(P308<50000, V308="Completed"), "Silver", "Pending")))) -> Silver
A309: ORD10308 | B309: C006 | C309: P203 | D309: 28/08/2025 | E309: 08/09/2025 | F309: Sneha Joshi | G309: Female | H309: 28/12/1976 | I309: Pune | J309: West | K309: Home Appliances | L309: Microwave | M309: 6 | N309: 8500 | O309: 15 | P309: 43350 | Q309: 1 | R309: Cash | S309: Aisha | T309: sneha.joshi@company.com | U309: 9134878547 | V309: Completed | W309: =IF(OR(Q309<=2, V309="Cancelled"), "Blacklisted", IF(AND(P309>=100000, Q309>=4, O309<=10, V309="Completed"), "Platinum", IF(AND(P309>=50000, P309<=99999, Q309>=3, V309="Completed"), "Gold", IF(AND(P309<50000, V309="Completed"), "Silver", "Pending")))) -> Blacklisted
A310: ORD10309 | B310: C010 | C310: P201 | D310: 06/10/2025 | E310: 11/10/2025 | F310: Pooja Shah | G310: Female | H310: 04/09/1986 | I310: Hyderabad | J310: South | K310: Home Appliances | L310: Mixer | M310: 3 | N310: 3500 | O310: 10 | P310: 9450 | Q310: 1 | R310: NetBanking | S310: Rahul | T310: pooja.shah@company.com | U310: 9253593557 | V310: Completed | W310: =IF(OR(Q310<=2, V310="Cancelled"), "Blacklisted", IF(AND(P310>=100000, Q310>=4, O310<=10, V310="Completed"), "Platinum", IF(AND(P310>=50000, P310<=99999, Q310>=3, V310="Completed"), "Gold", IF(AND(P310<50000, V310="Completed"), "Silver", "Pending")))) -> Blacklisted
A311: ORD10310 | B311: C009 | C311: P104 | D311: 17/01/2025 | E311: 29/01/2025 | F311: Mohit Verma | G311: Male | H311: 14/08/1989 | I311: Ahmedabad | J311: West | K311: Electronics | L311: Monitor | M311: 2 | N311: 12000 | O311: 20 | P311: 19200 | Q311: 1 | R311: Card | S311: Aisha | T311: mohit.verma@company.com | U311: 9183094051 | V311: Completed | W311: =IF(OR(Q311<=2, V311="Cancelled"), "Blacklisted", IF(AND(P311>=100000, Q311>=4, O311<=10, V311="Completed"), "Platinum", IF(AND(P311>=50000, P311<=99999, Q311>=3, V311="Completed"), "Gold", IF(AND(P311<50000, V311="Completed"), "Silver", "Pending")))) -> Blacklisted
A312: ORD10311 | B312: C005 | C312: P302 | D312: 13/10/2025 | E312: 16/10/2025 | F312: Vikas Mehta | G312: Male | H312: 02/03/1991 | I312: Delhi | J312: North | K312: Stationery | L312: Pen | M312: 12 | N312: 20 | O312: 20 | P312: 192 | Q312: 2 | R312: Card | S312: Rahul | T312: vikas.mehta@company.com | U312: 9293147620 | V312: Completed | W312: =IF(OR(Q312<=2, V312="Cancelled"), "Blacklisted", IF(AND(P312>=100000, Q312>=4, O312<=10, V312="Completed"), "Platinum", IF(AND(P312>=50000, P312<=99999, Q312>=3, V312="Completed"), "Gold", IF(AND(P312<50000, V312="Completed"), "Silver", "Pending")))) -> Blacklisted
... A370: ORD10369 | B370: C010 | C370: P301 | D370: 01/04/2026 | E370: 05/04/2026 | F370: Pooja Shah | G370: Female | H370: 04/01/1987 | I370: Hyderabad | J370: South | K370: Stationery | L370: Notebook | M370: 19 | N370: 60 | O370: 15 | P370: 969 | Q370: 4 | R370: NetBanking | S370: Neha | T370: pooja.shah@company.com | U370: 9435947486 | V370: Cancelled | W370: =IF(OR(Q370<=2, V370="Cancelled"), "Blacklisted", IF(AND(P370>=100000, Q370>=4, O370<=10, V370="Completed"), "Platinum", IF(AND(P370>=50000, P370<=99999, Q370>=3, V370="Completed"), "Gold", IF(AND(P370<50000, V370="Completed"), "Silver", "Pending")))) -> Blacklisted
A371: ORD10370 | B371: C001 | C371: P101 | E371: 02/02/2025 | F371: Amit Sharma | G371: Male | H371: 14/05/1992 | I371: Delhi | J371: North | K371: Electronics | L371: Laptop | M371: 15 | N371: 55000 | O371: 0 | P371: 825000 | Q371: 5 | R371: Card | S371: Neha | T371: amit.sharma@company.com | U371: 9411668831 | V371: Cancelled | W371: =IF(OR(Q371<=2, V371="Cancelled"), "Blacklisted", IF(AND(P371>=100000, Q371>=4, O371<=10, V371="Completed"), "Platinum", IF(AND(P371>=50000, P371<=99999, Q371>=3, V371="Completed"), "Gold", IF(AND(P371<50000, V371="Completed"), "Silver", "Pending")))) -> Blacklisted
A372: ORD10371 | B372: C009 | C372: P303 | D372: 06/10/2025 | E372: 08/10/2025 | F372: Mohit Verma | G372: Male | H372: 03/05/1989 | I372: Bengaluru | J372: South | K372: Stationery | L372: Marker | M372: 11 | N372: 45 | O372: 5 | P372: 470.25 | Q372: 5 | R372: NetBanking | S372: Karan | T372: mohit.verma@company.com | U372: 9523682403 | V372: Completed | W372: =IF(OR(Q372<=2, V372="Cancelled"), "Blacklisted", IF(AND(P372>=100000, Q372>=4, O372<=10, V372="Completed"), "Platinum", IF(AND(P372>=50000, P372<=99999, Q372>=3, V372="Completed"), "Gold", IF(AND(P372<50000, V372="Completed"), "Silver", "Pending")))) -> Silver
A373: ORD10372 | B373: C006 | C373: P302 | D373: 12/06/2025 | E373: 17/06/2025 | F373: Sneha Joshi | G373: Female | H373: 19/12/1990 | I373: Jaipur | J373: North | K373: Stationery | L373: Pen | M373: 9 | N373: 20 | O373: 10 | P373: 162 | Q373: 1 | R373: Card | S373: Rahul | T373: sneha.joshi@company.com | U373: 9652936744 | V373: Cancelled | W373: =IF(OR(Q373<=2, V373="Cancelled"), "Blacklisted", IF(AND(P373>=100000, Q373>=4, O373<=10, V373="Completed"), "Platinum", IF(AND(P373>=50000, P373<=99999, Q373>=3, V373="Completed"), "Gold", IF(AND(P373<50000, V373="Completed"), "Silver", "Pending")))) -> Blacklisted
A374: ORD10373 | B374: C004 | C374: P303 | D374: 18/11/2025 | E374: 20/11/2025 | F374: Anita Gupta | G374: Female | H374: 09/07/1995 | I374: Bengaluru | J374: South | K374: Stationery | L374: Marker | M374: 5 | N374: 45 | O374: 5 | P374: 213.75 | Q374: 3 | R374: Card | S374: Neha | T374: anita.gupta@company.com | U374: 9726464733 | V374: Pending | W374: =IF(OR(Q374<=2, V374="Cancelled"), "Blacklisted", IF(AND(P374>=100000, Q374>=4, O374<=10, V374="Completed"), "Platinum", IF(AND(P374>=50000, P374<=99999, Q374>=3, V374="Completed"), "Gold", IF(AND(P374<50000, V374="Completed"), "Silver", "Pending")))) -> Pending
A375: ORD10374 | B375: C007 | C375: P102 | D375: 01/11/2025 | E375: 02/11/2025 | F375: Arjun Rao | G375: Male | H375: 23/12/1998 | I375: Hyderabad | J375: South | K375: Electronics | L375: Mouse | M375: 5 | N375: 700 | O375: 10 | P375: 3150 | Q375: 2 | R375: UPI | S375: Rahul | T375: arjun.rao@company.com | U375: 9273520544 | V375: Completed | W375: =IF(OR(Q375<=2, V375="Cancelled"), "Blacklisted", IF(AND(P375>=100000, Q375>=4, O375<=10, V375="Completed"), "Platinum", IF(AND(P375>=50000, P375<=99999, Q375>=3, V375="Completed"), "Gold", IF(AND(P375<50000, V375="Completed"), "Silver", "Pending")))) -> Blacklisted
A376: ORD10375 | B376: C005 | C376: P102 | D376: 24/01/2025 | E376: 31/01/2025 | F376: Vikas Mehta | G376: Male | H376: 23/12/1979 | I376: Kolkata | J376: East | K376: Electronics | L376: Mouse | M376: 1 | N376: 700 | O376: 0 | P376: 700 | Q376: 1 | R376: UPI | S376: Karan | T376: vikas.mehta@company.com | U376: 9374259988 | V376: Completed | W376: =IF(OR(Q376<=2, V376="Cancelled"), "Blacklisted", IF(AND(P376>=100000, Q376>=4, O376<=10, V376="Completed"), "Platinum", IF(AND(P376>=50000, P376<=99999, Q376>=3, V376="Completed"), "Gold", IF(AND(P376<50000, V376="Completed"), "Silver", "Pending")))) -> Blacklisted
A377: ORD10376 | B377: C008 | C377: P102 | D377: 13/02/2026 | E377: 21/02/2026 | F377: Kavya Nair | G377: Female | H377: 15/12/1975 | I377: Mumbai | J377: West | K377: Electronics | L377: Mouse | M377: 13 | N377: 700 | O377: 20 | P377: 7280 | Q377: 2 | R377: Card | S377: Ritika | T377: kavya.nair@company.com | U377: 9538129419 | V377: Completed | W377: =IF(OR(Q377<=2, V377="Cancelled"), "Blacklisted", IF(AND(P377>=100000, Q377>=4, O377<=10, V377="Completed"), "Platinum", IF(AND(P377>=50000, P377<=99999, Q377>=3, V377="Completed"), "Gold", IF(AND(P377<50000, V377="Completed"), "Silver", "Pending")))) -> Blacklisted
A378: ORD10377 | B378: C009 | C378: P104 | D378: 08/02/2025 | E378: 19/02/2025 | F378: Mohit Verma | G378: Male | H378: 17/05/1993 | I378: Pune | J378: West | K378: Electronics | L378: Monitor | M378: 20 | N378: 12000 | O378: 0 | P378: 240000 | Q378: 2 | R378: Card | S378: Neha | T378: mohit.verma@company.com | U378: 9382815686 | V378: Completed | W378: =IF(OR(Q378<=2, V378="Cancelled"), "Blacklisted", IF(AND(P378>=100000, Q378>=4, O378<=10, V378="Completed"), "Platinum", IF(AND(P378>=50000, P378<=99999, Q378>=3, V378="Completed"), "Gold", IF(AND(P378<50000, V378="Completed"), "Silver", "Pending")))) -> Blacklisted
A379: ORD10378 | B379: C007 | C379: P103 | D379: 28/12/2025 | E379: 06/01/2026 | F379: Arjun Rao | G379: Male | H379: 17/09/1976 | I379: Kolkata | J379: East | K379: Electronics | L379: Keyboard | M379: 9 | N379: 1200 | O379: 15 | P379: 9180 | Q379: 1 | R379: UPI | S379: Ritika | T379: arjun.rao@company.com | U379: 9450746157 | V379: Pending | W379: =IF(OR(Q379<=2, V379="Cancelled"), "Blacklisted", IF(AND(P379>=100000, Q379>=4, O379<=10, V379="Completed"), "Platinum", IF(AND(P379>=50000, P379<=99999, Q379>=3, V379="Completed"), "Gold", IF(AND(P379<50000, V379="Completed"), "Silver", "Pending")))) -> Blacklisted
A380: ORD10379 | B380: C007 | C380: P302 | D380: 01/10/2025 | E380: 03/10/2025 | F380: Arjun Rao | G380: Male | H380: 22/12/1996 | I380: Jaipur | J380: North | K380: Stationery | L380: Pen | M380: 3 | N380: 20 | O380: 15 | P380: 51 | Q380: 3 | R380: Cash | S380: Neha | T380: arjun.rao@company.com | U380: 9349012570 | V380: Pending | W380: =IF(OR(Q380<=2, V380="Cancelled"), "Blacklisted", IF(AND(P380>=100000, Q380>=4, O380<=10, V380="Completed"), "Platinum", IF(AND(P380>=50000, P380<=99999, Q380>=3, V380="Completed"), "Gold", IF(AND(P380<50000, V380="Completed"), "Silver", "Pending")))) -> Pending
A381: ORD10380 | B381: C006 | C381: P101 | D381: 18/12/2025 | E381: 19/12/2025 | F381: Sneha Joshi | G381: Female | H381: 25/12/1995 | I381: Delhi | J381: North | K381: Electronics | L381: Laptop | M381: 8 | N381: 55000 | O381: 20 | P381: 352000 | Q381: 5 | R381: Card | S381: Karan | T381: sneha.joshi@company.com | U381: 9442163790 | V381: Pending | W381: =IF(OR(Q381<=2, V381="Cancelled"), "Blacklisted", IF(AND(P381>=100000, Q381>=4, O381<=10, V381="Completed"), "Platinum", IF(AND(P381>=50000, P381<=99999, Q381>=3, V381="Completed"), "Gold", IF(AND(P381<50000, V381="Completed"), "Silver", "Pending")))) -> Pending
A382: ORD10381 | B382: C006 | C382: P301 | D382: 29/09/2025 | E382: 07/10/2025 | F382: Sneha Joshi | G382: Female | H382: 23/06/1985 | I382: Delhi | J382: North | K382: Stationery | L382: Notebook | M382: 17 | N382: 60 | O382: 20 | P382: 816 | Q382: 1 | R382: UPI | S382: Ritika | T382: sneha.joshi@company.com | U382: 9953329223 | V382: Pending | W382: =IF(OR(Q382<=2, V382="Cancelled"), "Blacklisted", IF(AND(P382>=100000, Q382>=4, O382<=10, V382="Completed"), "Platinum", IF(AND(P382>=50000, P382<=99999, Q382>=3, V382="Completed"), "Gold", IF(AND(P382<50000, V382="Completed"), "Silver", "Pending")))) -> Blacklisted
A383: ORD10382 | B383: C003 | C383: P302 | D383: 14/05/2025 | E383: 22/05/2025 | F383: Rohit Singh | G383: Male | H383: 10/02/1984 | I383: Bengaluru | J383: South | K383: Stationery | L383: Pen | M383: 4 | N383: 20 | O383: 15 | P383: 68 | Q383: 3 | R383: NetBanking | S383: Aisha | T383: rohit.singh@company.com | U383: 9202321359 | V383: Pending | W383: =IF(OR(Q383<=2, V383="Cancelled"), "Blacklisted", IF(AND(P383>=100000, Q383>=4, O383<=10, V383="Completed"), "Platinum", IF(AND(P383>=50000, P383<=99999, Q383>=3, V383="Completed"), "Gold", IF(AND(P383<50000, V383="Completed"), "Silver", "Pending")))) -> Pending
... A399: ORD10398 | B399: C007 | C399: P104 | D399: 31/01/2025 | E399: 04/02/2025 | F399: Arjun Rao | G399: Male | H399: 10/12/1978 | I399: Kolkata | J399: East | K399: Electronics | L399: Monitor | M399: 19 | N399: 12000 | O399: 0 | P399: 228000 | Q399: 4 | R399: UPI | S399: Aisha | T399: arjun.rao@company.com | U399: 9136906750 | V399: Pending | W399: =IF(OR(Q399<=2, V399="Cancelled"), "Blacklisted", IF(AND(P399>=100000, Q399>=4, O399<=10, V399="Completed"), "Platinum", IF(AND(P399>=50000, P399<=99999, Q399>=3, V399="Completed"), "Gold", IF(AND(P399<50000, V399="Completed"), "Silver", "Pending")))) -> Pending
A400: ORD10399 | B400: C001 | C400: P102 | E400: 03/11/2025 | F400: Amit Sharma | G400: Male | H400: 01/09/1979 | I400: Bengaluru | J400: South | K400: Electronics | L400: Mouse | M400: 12 | N400: 700 | O400: 15 | P400: 7140 | Q400: 3 | R400: Card | S400: Ritika | T400: amit.sharma@company.com | U400: 9485286324 | V400: Completed | W400: =IF(OR(Q400<=2, V400="Cancelled"), "Blacklisted", IF(AND(P400>=100000, Q400>=4, O400<=10, V400="Completed"), "Platinum", IF(AND(P400>=50000, P400<=99999, Q400>=3, V400="Completed"), "Gold", IF(AND(P400<50000, V400="Completed"), "Silver", "Pending")))) -> Silver
A401: ORD10400 | B401: C008 | C401: P103 | D401: 13/05/2025 | E401: 21/05/2025 | F401: Kavya Nair | G401: Female | H401: 08/04/2001 | I401: Delhi | J401: North | K401: Electronics | L401: Keyboard | M401: 16 | N401: 1200 | O401: 20 | P401: 15360 | Q401: 1 | R401: Cash | S401: Rahul | T401: kavya.nair@company.com | U401: 9414633966 | V401: Pending | W401: =IF(OR(Q401<=2, V401="Cancelled"), "Blacklisted", IF(AND(P401>=100000, Q401>=4, O401<=10, V401="Completed"), "Platinum", IF(AND(P401>=50000, P401<=99999, Q401>=3, V401="Completed"), "Gold", IF(AND(P401<50000, V401="Completed"), "Silver", "Pending")))) -> Blacklisted
A402: ORD10401 | B402: C009 | C402: P203 | D402: 27/12/2025 | E402: 04/01/2026 | F402: Mohit Verma | G402: Male | H402: 01/01/1983 | I402: Hyderabad | J402: South | K402: Home Appliances | L402: Microwave | M402: 10 | N402: 8500 | O402: 5 | P402: 80750 | Q402: 5 | R402: NetBanking | S402: Ritika | T402: mohit.verma@company.com | U402: 9833735234 | V402: Completed | W402: =IF(OR(Q402<=2, V402="Cancelled"), "Blacklisted", IF(AND(P402>=100000, Q402>=4, O402<=10, V402="Completed"), "Platinum", IF(AND(P402>=50000, P402<=99999, Q402>=3, V402="Completed"), "Gold", IF(AND(P402<50000, V402="Completed"), "Silver", "Pending")))) -> Gold
A403: ORD10402 | B403: C008 | C403: P302 | D403: 11/02/2025 | E403: 21/02/2025 | F403: Kavya Nair | G403: Female | H403: 09/08/1989 | I403: Ahmedabad | J403: West | K403: Stationery | L403: Pen | M403: 18 | N403: 20 | O403: 20 | P403: 288 | Q403: 1 | R403: UPI | S403: Ritika | T403: kavya.nair@company.com | U403: 9523689108 | V403: Pending | W403: =IF(OR(Q403<=2, V403="Cancelled"), "Blacklisted", IF(AND(P403>=100000, Q403>=4, O403<=10, V403="Completed"), "Platinum", IF(AND(P403>=50000, P403<=99999, Q403>=3, V403="Completed"), "Gold", IF(AND(P403<50000, V403="Completed"), "Silver", "Pending")))) -> Blacklisted
A404: ORD10403 | B404: C009 | C404: P203 | D404: 13/03/2026 | E404: 19/03/2026 | F404: Mohit Verma | G404: Male | H404: 22/10/1993 | I404: Mumbai | J404: West | K404: Home Appliances | L404: Microwave | M404: 9 | N404: 8500 | O404: 0 | P404: 76500 | Q404: 2 | R404: Card | S404: Ritika | T404: mohit.verma@company.com | U404: 9812909831 | V404: Pending | W404: =IF(OR(Q404<=2, V404="Cancelled"), "Blacklisted", IF(AND(P404>=100000, Q404>=4, O404<=10, V404="Completed"), "Platinum", IF(AND(P404>=50000, P404<=99999, Q404>=3, V404="Completed"), "Gold", IF(AND(P404<50000, V404="Completed"), "Silver", "Pending")))) -> Blacklisted
A405: ORD10404 | B405: C008 | C405: P203 | D405: 01/10/2025 | E405: 12/10/2025 | F405: Kavya Nair | G405: Female | H405: 05/05/2000 | I405: Mumbai | J405: West | K405: Home Appliances | L405: Microwave | M405: 8 | N405: 8500 | O405: 10 | P405: 61200 | Q405: 4 | R405: Cash | S405: Neha | T405: kavya.nair@company.com | U405: 9106290987 | V405: Cancelled | W405: =IF(OR(Q405<=2, V405="Cancelled"), "Blacklisted", IF(AND(P405>=100000, Q405>=4, O405<=10, V405="Completed"), "Platinum", IF(AND(P405>=50000, P405<=99999, Q405>=3, V405="Completed"), "Gold", IF(AND(P405<50000, V405="Completed"), "Silver", "Pending")))) -> Blacklisted
...

Sheet Q2
A1: Customer_Name | B1: Customer Code | C1: Email
A2: =TRIM(PROPER(Sales_Data!F2)) -> Kavya Nair | B2: =_xlfn.CONCAT(LEFT(A2,3),RIGHT(Sales_Data!B2,3),LEFT(Sales_Data!I2,2)) -> Kav008Hy | C2: =IF(COUNTIF(Sales_Data!T2, "*@*"), LOWER(TRIM(Sales_Data!T2)), "Invalid Email") -> kavya.nair@company.com
A3: =TRIM(PROPER(Sales_Data!F3)) -> Kavya Nair | B3: =_xlfn.CONCAT(LEFT(A3,3),RIGHT(Sales_Data!B3,3),LEFT(Sales_Data!I3,2)) -> Kav008De | C3: =IF(COUNTIF(Sales_Data!T3, "*@*"), LOWER(TRIM(Sales_Data!T3)), "Invalid Email") -> kavya.nair@company.com
A4: =TRIM(PROPER(Sales_Data!F4)) -> Pooja Shah | B4: =_xlfn.CONCAT(LEFT(A4,3),RIGHT(Sales_Data!B4,3),LEFT(Sales_Data!I4,2)) -> Poo010Be | C4: =IF(COUNTIF(Sales_Data!T4, "*@*"), LOWER(TRIM(Sales_Data!T4)), "Invalid Email") -> pooja.shah@company.com
A5: =TRIM(PROPER(Sales_Data!F5)) -> Kavya Nair | B5: =_xlfn.CONCAT(LEFT(A5,3),RIGHT(Sales_Data!B5,3),LEFT(Sales_Data!I5,2)) -> Kav008Be | C5: =IF(COUNTIF(Sales_Data!T5, "*@*"), LOWER(TRIM(Sales_Data!T5)), "Invalid Email") -> kavya.nair@company.com
A6: =TRIM(PROPER(Sales_Data!F6)) -> Mohit Verma | B6: =_xlfn.CONCAT(LEFT(A6,3),RIGHT(Sales_Data!B6,3),LEFT(Sales_Data!I6,2)) -> Moh009De | C6: =IF(COUNTIF(Sales_Data!T6, "*@*"), LOWER(TRIM(Sales_Data!T6)), "Invalid Email") -> mohit.verma@company.com
A7: =TRIM(PROPER(Sales_Data!F7)) -> Arjun Rao | B7: =_xlfn.CONCAT(LEFT(A7,3),RIGHT(Sales_Data!B7,3),LEFT(Sales_Data!I7,2)) -> Arj007Hy | C7: =IF(COUNTIF(Sales_Data!T7, "*@*"), LOWER(TRIM(Sales_Data!T7)), "Invalid Email") -> arjun.rao@company.com
A8: =TRIM(PROPER(Sales_Data!F8)) -> Kavya Nair | B8: =_xlfn.CONCAT(LEFT(A8,3),RIGHT(Sales_Data!B8,3),LEFT(Sales_Data!I8,2)) -> Kav008Hy | C8: =IF(COUNTIF(Sales_Data!T8, "*@*"), LOWER(TRIM(Sales_Data!T8)), "Invalid Email") -> kavya.nair@company.com
A9: =TRIM(PROPER(Sales_Data!F9)) -> Priya Patel | B9: =_xlfn.CONCAT(LEFT(A9,3),RIGHT(Sales_Data!B9,3),LEFT(Sales_Data!I9,2)) -> Pri002Mu | C9: =IF(COUNTIF(Sales_Data!T9, "*@*"), LOWER(TRIM(Sales_Data!T9)), "Invalid Email") -> priya.patel@company.com
A10: =TRIM(PROPER(Sales_Data!F10)) -> Kavya Nair | B10: =_xlfn.CONCAT(LEFT(A10,3),RIGHT(Sales_Data!B10,3),LEFT(Sales_Data!I10,2)) -> Kav008Pu | C10: =IF(COUNTIF(Sales_Data!T10, "*@*"), LOWER(TRIM(Sales_Data!T10)), "Invalid Email") -> kavya.nair@company.com
A11: =TRIM(PROPER(Sales_Data!F11)) -> Priya Patel | B11: =_xlfn.CONCAT(LEFT(A11,3),RIGHT(Sales_Data!B11,3),LEFT(Sales_Data!I11,2)) -> Pri002Mu | C11: =IF(COUNTIF(Sales_Data!T11, "*@*"), LOWER(TRIM(Sales_Data!T11)), "Invalid Email") -> priya.patel@company.com
A12: =TRIM(PROPER(Sales_Data!F12)) -> Rohit Singh | B12: =_xlfn.CONCAT(LEFT(A12,3),RIGHT(Sales_Data!B12,3),LEFT(Sales_Data!I12,2)) -> Roh003De | C12: =IF(COUNTIF(Sales_Data!T12, "*@*"), LOWER(TRIM(Sales_Data!T12)), "Invalid Email") -> rohit.singh@company.com
A13: =TRIM(PROPER(Sales_Data!F13)) -> Kavya Nair | B13: =_xlfn.CONCAT(LEFT(A13,3),RIGHT(Sales_Data!B13,3),LEFT(Sales_Data!I13,2)) -> Kav008Ah | C13: =IF(COUNTIF(Sales_Data!T13, "*@*"), LOWER(TRIM(Sales_Data!T13)), "Invalid Email") -> kavya.nair@company.com
... A502: =TRIM(PROPER(Sales_Data!F502)) | B502: =_xlfn.CONCAT(LEFT(A502,3),RIGHT(Sales_Data!B502,3),LEFT(Sales_Data!I502,2)) | C502: =IF(COUNTIF(Sales_Data!T502, "*@*"), LOWER(TRIM(Sales_Data!T502)), "Invalid Email") -> Invalid Email

Sheet Q3
A1: Order_ID | B1: Customer_ID | C1: Product_ID | D1: Order_Date | E1: Delivery_Date | F1: Customer_Name | G1: Gender | H1: DOB | I1: City | J1: Region | K1: Category | L1: Product_Name | M1: Quantity | N1: Unit_Price | O1: Discount_% | P1: Sales | Q1: Rating | R1: Payment_Mode | S1: Salesperson | T1: Email | U1: Phone | V1: Order_Status | W1: Customer Age | X1: Delivery time (Days) | Y1: Delivery Status
A2: ORD10001 | B2: C008 | C2: P202 | D2: 45918 | E2: 45922 | F2: Kavya Nair | G2: Female | H2: 27767 | I2: Hyderabad | J2: South | K2: Home Appliances | L2: Iron | M2: 4 | N2: 2200 | O2: 10 | P2: 7920 | Q2: 4 | R2: Cash | S2: Ritika | T2: KAvya.nair@company.com | U2: 9431429797 | V2: Completed | W2: =DATEDIF(H2,TODAY(),"Y") -> 50 | X2: =DATEDIF(D2,E2,"D") -> 4 | Y2: {=_xlfn.IFS(ISERROR(X2), "Pending", X2<=5, "On Time", X2>5, "Delayed")} -> On Time
A3: ORD10002 | B3: C008 | C3: P104 | D3: 45774 | E3: 45781 | F3: Kavya Nair | G3: Female | H3: 36815 | I3: Delhi | J3: North | K3: Electronics | L3: Monitor | M3: 17 | N3: 12000 | O3: 10 | P3: 183600 | Q3: 1 | R3: NetBanking | S3: Rahul | T3: kavya.nair@company.com | U3: 9129865339 | V3: Completed | W3: =DATEDIF(H3,TODAY(),"Y") -> 25 | X3: =DATEDIF(D3,E3,"D") -> 7 | Y3: {=_xlfn.IFS(ISERROR(X3), "Pending", X3<=5, "On Time", X3>5, "Delayed")} -> Delayed
A4: ORD10003 | B4: C010 | C4: P101 | D4: 45903 | E4: 45914 | F4: pooja shah | G4: Female | H4: 34593 | I4: Bengaluru | J4: South | K4: Electronics | L4: Laptop | M4: 5 | N4: 55000 | O4: 5 | P4: 261250 | Q4: 3 | R4: NetBanking | S4: Aisha | T4: pooja.shah@company.com | U4: 9380975626 | V4: Pending | W4: =DATEDIF(H4,TODAY(),"Y") -> 31 | X4: =DATEDIF(D4,E4,"D") -> 11 | Y4: {=_xlfn.IFS(ISERROR(X4), "Pending", X4<=5, "On Time", X4>5, "Delayed")} -> Delayed
A5: ORD10002 | B5: C008 | C5: P202 | D5: 46102 | E5: 46114 | F5: Kavya Nair | G5: Female | H5: 38171 | I5: Bengaluru | J5: South | K5: Home Appliances | L5: Iron | M5: 5 | N5: 2200 | O5: 5 | P5: 10450 | Q5: 5 | R5: NetBanking | S5: Aisha | T5: kavya.nair@company.com | U5: 9600261125 | V5: Cancelled | W5: =DATEDIF(H5,TODAY(),"Y") -> 22 | X5: =DATEDIF(D5,E5,"D") -> 12 | Y5: {=_xlfn.IFS(ISERROR(X5), "Pending", X5<=5, "On Time", X5>5, "Delayed")} -> Delayed
A6: ORD10005 | B6: C009 | C6: P103 | D6: 45927 | E6: 45937 | F6: Mohit Verma | G6: Male | H6: 27863 | I6: Delhi | J6: North | K6: Electronics | L6: Keyboard | M6: 8 | N6: 1200 | O6: 5 | P6: 9120 | Q6: 2 | R6: Card | S6: Aisha | T6: mohit.verma@company.com | U6: 9724635978 | V6: Pending | W6: =DATEDIF(H6,TODAY(),"Y") -> 50 | X6: =DATEDIF(D6,E6,"D") -> 10 | Y6: {=_xlfn.IFS(ISERROR(X6), "Pending", X6<=5, "On Time", X6>5, "Delayed")} -> Delayed
A7: ORD10006 | B7: C007 | C7: P202 | D7: 46026 | E7: 46034 | F7: arjun Rao | G7: Male | H7: 32326 | I7: Hyderabad | J7: South | K7: Home Appliances | L7: Iron | M7: 4 | N7: 2200 | O7: 0 | P7: 8800 | Q7: 1 | R7: UPI | S7: Ritika | T7: arjun.rao@company.com | U7: 9780584905 | V7: Completed | W7: =DATEDIF(H7,TODAY(),"Y") -> 38 | X7: =DATEDIF(D7,E7,"D") -> 8 | Y7: {=_xlfn.IFS(ISERROR(X7), "Pending", X7<=5, "On Time", X7>5, "Delayed")} -> Delayed
A8: ORD10007 | B8: C008 | C8: P201 | D8: 31/02/2025 | E8: 46078 | F8: Kavya Nair | G8: Female | H8: 37700 | I8: Hyderabad | J8: South | K8: Home Appliances | L8: Mixer | M8: 2 | N8: 3500 | O8: 5 | P8: 6650 | Q8: 1 | R8: UPI | S8: Ritika | T8: kavya.nair@company.com | U8: 9958252176 | V8: Completed | W8: =DATEDIF(H8,TODAY(),"Y") -> 23 | X8: =DATEDIF(D8,E8,"D") -> #VALUE! | Y8: {=_xlfn.IFS(ISERROR(X8), "Pending", X8<=5, "On Time", X8>5, "Delayed")} -> Pending
A9: ORD10008 | B9: C002 | C9: P104 | D9: 45760 | E9: 45766 | F9: Priya Patel | G9: Female | H9: 34883 | I9: Mumbai | J9: West | K9: Electronics | L9: Monitor | M9: 14 | N9: 12000 | O9: 15 | P9: 142800 | Q9: 4 | R9: NetBanking | S9: Ritika | T9: priYa.patel@company.com | U9: 9705521654 | V9: Completed | W9: =DATEDIF(H9,TODAY(),"Y") -> 31 | X9: =DATEDIF(D9,E9,"D") -> 6 | Y9: {=_xlfn.IFS(ISERROR(X9), "Pending", X9<=5, "On Time", X9>5, "Delayed")} -> Delayed
A10: ORD10009 | B10: C008 | C10: P104 | D10: 46053 | E10: 46055 | F10: kavya Nair | G10: Female | H10: 35585 | I10: Pune | J10: West | K10: Electronics | L10: Monitor | M10: 4 | N10: 12000 | O10: 15 | P10: 40800 | Q10: 4 | R10: UPI | S10: Neha | T10: kavya.nair@company.com | U10: 9588041011 | V10: Completed | W10: =DATEDIF(H10,TODAY(),"Y") -> 29 | X10: =DATEDIF(D10,E10,"D") -> 2 | Y10: {=_xlfn.IFS(ISERROR(X10), "Pending", X10<=5, "On Time", X10>5, "Delayed")} -> On Time
A11: ORD10010 | B11: C002 | C11: P301 | D11: 45741 | E11: 45743 | F11: Priya Patel | G11: Female | H11: 33055 | I11: Mumbai | J11: West | K11: Stationery | L11: Notebook | M11: 6 | N11: 60 | O11: 0 | P11: 360 | Q11: 4 | R11: Card | S11: Neha | T11: PRiya.patel@company.com | U11: 9340540608 | V11: Completed | W11: =DATEDIF(H11,TODAY(),"Y") -> 36 | X11: =DATEDIF(D11,E11,"D") -> 2 | Y11: {=_xlfn.IFS(ISERROR(X11), "Pending", X11<=5, "On Time", X11>5, "Delayed")} -> On Time
A12: ORD10011 | B12: C003 | C12: P202 | D12: 45919 | E12: 45923 | F12: Rohit Singh | G12: Male | H12: 30229 | I12: Delhi | J12: North | K12: Home Appliances | L12: Iron | M12: -3 | N12: 2200 | O12: 0 | P12: 35200 | Q12: 2 | R12: Card | S12: Rahul | T12: rohit.singh@company.com | U12: 9521710321 | V12: Pending | W12: =DATEDIF(H12,TODAY(),"Y") -> 43 | X12: =DATEDIF(D12,E12,"D") -> 4 | Y12: {=_xlfn.IFS(ISERROR(X12), "Pending", X12<=5, "On Time", X12>5, "Delayed")} -> On Time
A13: ORD10012 | B13: C008 | C13: P201 | D13: 45724 | E13: 45731 | F13: Kavya Nair | G13: Female | H13: 29974 | I13: Ahmedabad | J13: West | K13: Home Appliances | L13: Mixer | M13: 10 | N13: 3500 | O13: 5 | P13: 33250 | Q13: 5 | R13: Card | S13: Aisha | T13: kavya.nair@company.com | U13: 9123535241 | V13: Cancelled | W13: =DATEDIF(H13,TODAY(),"Y") -> 44 | X13: =DATEDIF(D13,E13,"D") -> 7 | Y13: {=_xlfn.IFS(ISERROR(X13), "Pending", X13<=5, "On Time", X13>5, "Delayed")} -> Delayed
A14: ORD10013 | B14: C002 | C14: P202 | D14: 45667 | E14: 45672 | F14: Priya Patel | G14: Female | H14: 33762 | I14: Pune | J14: West | K14: Home Appliances | L14: Iron | M14: 15 | N14: 2200 | O14: 10 | P14: 29700 | Q14: 1 | R14: UPI | S14: Neha | T14: priya.patel@company.com | U14: 9367316892 | V14: Pending | W14: =DATEDIF(H14,TODAY(),"Y") -> 34 | X14: =DATEDIF(D14,E14,"D") -> 5 | Y14: {=_xlfn.IFS(ISERROR(X14), "Pending", X14<=5, "On Time", X14>5, "Delayed")} -> On Time
A15: ORD10014 | B15: C003 | C15: P202 | D15: 45725 | E15: 45729 | F15: rohit Singh | G15: Male | H15: 37334 | I15: Mumbai | J15: West | K15: Home Appliances | L15: Iron | M15: 17 | N15: 2200 | O15: 5 | P15: 35530 | Q15: 1 | R15: Cash | S15: Karan | T15: rOhit.singh@company.com | U15: 9778489803 | V15: Completed | W15: =DATEDIF(H15,TODAY(),"Y") -> 24 | X15: =DATEDIF(D15,E15,"D") -> 4 | Y15: {=_xlfn.IFS(ISERROR(X15), "Pending", X15<=5, "On Time", X15>5, "Delayed")} -> On Time
A16: ORD10015 | B16: C008 | C16: P201 | D16: 45864 | E16: 45876 | F16: Kavya nair | G16: Female | H16: 36908 | I16: Mumbai | J16: West | K16: Home Appliances | L16: Mixer | M16: 15 | N16: 3500 | O16: 15 | P16: 44625 | Q16: 2 | R16: Cash | S16: Neha | T16: kavya.nair@company.com | U16: 9582960180 | V16: Cancelled | W16: =DATEDIF(H16,TODAY(),"Y") -> 25 | X16: =DATEDIF(D16,E16,"D") -> 12 | Y16: {=_xlfn.IFS(ISERROR(X16), "Pending", X16<=5, "On Time", X16>5, "Delayed")} -> Delayed
A17: ORD10016 | B17: C010 | C17: P103 | D17: 46120 | E17: 46123 | F17: Pooja Shah | G17: Female | H17: 37564 | I17: Hyderabad | J17: South | K17: Electronics | L17: Keyboard | M17: 3 | N17: 1200 | O17: 5 | P17: 3420 | Q17: 5 | R17: UPI | S17: Ritika | T17: pooja.shahcompany.com | U17: 9611394005 | V17: Completed | W17: =DATEDIF(H17,TODAY(),"Y") -> 23 | X17: =DATEDIF(D17,E17,"D") -> 3 | Y17: {=_xlfn.IFS(ISERROR(X17), "Pending", X17<=5, "On Time", X17>5, "Delayed")} -> On Time
A18: ORD10017 | B18: C004 | C18: P203 | D18: 46075 | E18: 46084 | F18: Amit Sharma | G18: Female | H18: 37272 | I18: Pune | J18: West | K18: Home Appliances | L18: Microwave | M18: 13 | N18: 8500 | O18: 20 | P18: 88400 | Q18: 4 | R18: Card | S18: Rahul | T18: anita.gupta@company.com | U18: 9692599404 | V18: Pending | W18: =DATEDIF(H18,TODAY(),"Y") -> 24 | X18: =DATEDIF(D18,E18,"D") -> 9 | Y18: {=_xlfn.IFS(ISERROR(X18), "Pending", X18<=5, "On Time", X18>5, "Delayed")} -> Delayed
A19: ORD10018 | B19: C007 | C19: P203 | D19: 46081 | E19: 46086 | F19: Arjun Rao | G19: Male | H19: 32761 | I19: Ahmedabad | J19: West | K19: Home Appliances | L19: Microwave | M19: 4 | N19: 8500 | O19: 20 | P19: 27200 | Q19: 5 | R19: Card | S19: Aisha | T19: arjun.rao@company.com | U19: 9426119622 | V19: Pending | W19: =DATEDIF(H19,TODAY(),"Y") -> 36 | X19: =DATEDIF(D19,E19,"D") -> 5 | Y19: {=_xlfn.IFS(ISERROR(X19), "Pending", X19<=5, "On Time", X19>5, "Delayed")} -> On Time
A20: ORD10019 | B20: C007 | C20: P102 | D20: 45992 | E20: 45995 | F20: arjun rao | G20: Male | H20: 33539 | I20: Mumbai | J20: West | K20: Electronics | L20: Mouse | M20: 9 | N20: 700 | O20: 5 | P20: 5985 | Q20: 3 | R20: UPI | S20: Ritika | T20: arjun.Rao@company.com | U20: 9184436009 | V20: Pending | W20: =DATEDIF(H20,TODAY(),"Y") -> 34 | X20: =DATEDIF(D20,E20,"D") -> 3 | Y20: {=_xlfn.IFS(ISERROR(X20), "Pending", X20<=5, "On Time", X20>5, "Delayed")} -> On Time
... A39: ORD10038 | B39: C006 | C39: P201 | D39: 46089 | E39: 46101 | F39: Sneha Joshi | G39: Female | H39: 29393 | I39: Delhi | J39: North | K39: Home Appliances | L39: Mixer | M39: 20 | N39: 3500 | O39: 10 | P39: 63000 | Q39: 3 | R39: Card | S39: Rahul | T39: sneha.joshi@company.com | U39: 9283578533 | V39: Cancelled | W39: =DATEDIF(H39,TODAY(),"Y") -> 46 | X39: =DATEDIF(D39,E39,"D") -> 12 | Y39: {=_xlfn.IFS(ISERROR(X39), "Pending", X39<=5, "On Time", X39>5, "Delayed")} -> Delayed
A40: ORD10039 | B40: C008 | C40: P302 | D40: 45701 | E40: 45707 | F40: Kavya Nair | G40: Female | H40: 29023 | I40: Pune | J40: West | K40: Stationery | L40: Pen | M40: 5 | N40: 1200 | O40: 0 | P40: 100 | Q40: 1 | R40: Cash | S40: Rahul | T40: kavya.nair@company.com | U40: 9963005771 | V40: Cancelled | W40: =DATEDIF(H40,TODAY(),"Y") -> 47 | X40: =DATEDIF(D40,E40,"D") -> 6 | Y40: {=_xlfn.IFS(ISERROR(X40), "Pending", X40<=5, "On Time", X40>5, "Delayed")} -> Delayed
A41: ORD10040 | B41: C010 | C41: P203 | D41: 45935 | E41: 45945 | F41: Pooja Shah | G41: Female | H41: 33773 | I41: Mumbai | J41: West | K41: Home Appliances | L41: Microwave | M41: 20 | N41: 8500 | O41: 0 | P41: 170000 | Q41: 1 | R41: UPI | S41: Neha | T41: pooja.shah@company.com | U41: 9484632635 | V41: Cancelled | W41: =DATEDIF(H41,TODAY(),"Y") -> 34 | X41: =DATEDIF(D41,E41,"D") -> 10 | Y41: {=_xlfn.IFS(ISERROR(X41), "Pending", X41<=5, "On Time", X41>5, "Delayed")} -> Delayed
A42: ORD10041 | B42: C007 | C42: P301 | D42: 46063 | E42: 46065 | F42: Arjun Rao | G42: Male | H42: 34491 | I42: Bengaluru | J42: South | K42: Stationery | L42: Notebook | M42: 8 | N42: 60 | O42: 15 | P42: 408 | Q42: 5 | R42: UPI | S42: Rahul | T42: arjun.rao@company.com | U42: 9276319484 | V42: Pending | W42: =DATEDIF(H42,TODAY(),"Y") -> 32 | X42: =DATEDIF(D42,E42,"D") -> 2 | Y42: {=_xlfn.IFS(ISERROR(X42), "Pending", X42<=5, "On Time", X42>5, "Delayed")} -> On Time
A43: ORD10042 | B43: C010 | C43: P201 | D43: 45812 | E43: 45824 | F43: Pooja Shah | G43: Female | H43: 32408 | I43: Pune | J43: West | K43: Home Appliances | L43: Mixer | M43: 8 | N43: 3500 | O43: 5 | P43: 26600 | Q43: 1 | R43: Card | S43: Neha | T43: pooja.shah@company.com | U43: 9619034852 | V43: Pending | W43: =DATEDIF(H43,TODAY(),"Y") -> 37 | X43: =DATEDIF(D43,E43,"D") -> 12 | Y43: {=_xlfn.IFS(ISERROR(X43), "Pending", X43<=5, "On Time", X43>5, "Delayed")} -> Delayed
A44: ORD10043 | B44: C009 | C44: P203 | D44: 46061 | E44: 46067 | F44: Mohit Verma | G44: Male | H44: 37086 | I44: Jaipur | J44: North | K44: Home Appliances | L44: Microwave | M44: 1 | N44: 8500 | O44: 0 | P44: 8500 | Q44: 2 | R44: Card | S44: Neha | T44: mohit.verma@company.com | U44: 9636416962 | V44: Pending | W44: =DATEDIF(H44,TODAY(),"Y") -> 25 | X44: =DATEDIF(D44,E44,"D") -> 6 | Y44: {=_xlfn.IFS(ISERROR(X44), "Pending", X44<=5, "On Time", X44>5, "Delayed")} -> Delayed
A45: ORD10044 | B45: C001 | C45: P303 | D45: 45746 | E45: 45747 | F45: amit Sharma | G45: Male | H45: 33489 | I45: Pune | J45: West | K45: Stationery | L45: Marker | M45: 8 | N45: 45 | O45: 15 | P45: 306 | Q45: 2 | R45: Card | S45: Aisha | T45: amit.sharma@company.com | U45: 9357133880 | V45: Completed | W45: =DATEDIF(H45,TODAY(),"Y") -> 34 | X45: =DATEDIF(D45,E45,"D") -> 1 | Y45: {=_xlfn.IFS(ISERROR(X45), "Pending", X45<=5, "On Time", X45>5, "Delayed")} -> On Time
A46: ORD10045 | B46: C006 | C46: P202 | D46: 45772 | E46: 45775 | F46: Sneha Joshi | G46: Female | H46: 32437 | I46: Pune | J46: West | K46: Home Appliances | L46: Iron | M46: 16 | N46: 2200 | O46: 5 | P46: 33440 | Q46: 5 | R46: Card | S46: Aisha | T46: sneha.joshi@company.com | U46: 9575210324 | V46: Cancelled | W46: =DATEDIF(H46,TODAY(),"Y") -> 37 | X46: =DATEDIF(D46,E46,"D") -> 3 | Y46: {=_xlfn.IFS(ISERROR(X46), "Pending", X46<=5, "On Time", X46>5, "Delayed")} -> On Time
A47: ORD10046 | B47: C009 | C47: P201 | D47: 45943 | E47: 45953 | F47: Mohit Verma | G47: Male | H47: 37579 | I47: Bengaluru | J47: South | K47: Home Appliances | L47: Mixer | M47: 19 | N47: 3500 | O47: 20 | P47: 53200 | Q47: 3 | R47: Cash | S47: Karan | T47: mohit.verma@company.com | U47: 9276080204 | V47: Cancelled | W47: =DATEDIF(H47,TODAY(),"Y") -> 23 | X47: =DATEDIF(D47,E47,"D") -> 10 | Y47: {=_xlfn.IFS(ISERROR(X47), "Pending", X47<=5, "On Time", X47>5, "Delayed")} -> Delayed
A48: ORD10047 | B48: C006 | C48: P102 | D48: 45941 | E48: 45944 | F48: Sneha Joshi | G48: Female | H48: 36684 | I48: Pune | J48: West | K48: Electronics | L48: Mouse | M48: 15 | N48: 700 | O48: 15 | P48: 8925 | Q48: 4 | R48: UPI | S48: Neha | T48: sneha.joshicompany.com | U48: 9856624471 | V48: Completed | W48: =DATEDIF(H48,TODAY(),"Y") -> 26 | X48: =DATEDIF(D48,E48,"D") -> 3 | Y48: {=_xlfn.IFS(ISERROR(X48), "Pending", X48<=5, "On Time", X48>5, "Delayed")} -> On Time
A49: ORD10048 | B49: C006 | C49: P102 | D49: 45988 | E49: 45994 | F49: Sneha Joshi | G49: Female | H49: 36125 | I49: Jaipur | J49: North | K49: Electronics | L49: Mouse | M49: 19 | N49: 700 | O49: 20 | P49: 10640 | Q49: 1 | R49: Cash | S49: Neha | T49: sneha.joshi@company.com | U49: 9238141322 | V49: Completed | W49: =DATEDIF(H49,TODAY(),"Y") -> 27 | X49: =DATEDIF(D49,E49,"D") -> 6 | Y49: {=_xlfn.IFS(ISERROR(X49), "Pending", X49<=5, "On Time", X49>5, "Delayed")} -> Delayed
A50: ORD10049 | B50: C009 | C50: P104 | D50: 46131 | F50: Mohit Verma | G50: Male | H50: 35130 | I50: Delhi | J50: North | K50: Electronics | L50: Monitor | M50: 19 | N50: 12000 | O50: 0 | P50: 228000 | Q50: 1 | R50: NetBanking | S50: Aisha | T50: mohit.verma@company.com | U50: 9890380030 | V50: Completed | W50: =DATEDIF(H50,TODAY(),"Y") -> 30 | X50: =DATEDIF(D50,E50,"D") -> #NUM! | Y50: {=_xlfn.IFS(ISERROR(X50), "Pending", X50<=5, "On Time", X50>5, "Delayed")} -> Pending
A51: ORD10050 | B51: C004 | C51: P103 | D51: 46131 | E51: 46133 | F51: Anita Gupta | G51: Female | H51: 31851 | I51: Pune | J51: West | K51: Electronics | L51: Keyboard | M51: 6 | N51: 1200 | O51: 5 | P51: 6840 | Q51: 2 | R51: Cash | S51: Ritika | T51: anita.gupta@company.com | U51: 9495893170 | V51: Pending | W51: =DATEDIF(H51,TODAY(),"Y") -> 39 | X51: =DATEDIF(D51,E51,"D") -> 2 | Y51: {=_xlfn.IFS(ISERROR(X51), "Pending", X51<=5, "On Time", X51>5, "Delayed")} -> On Time
A52: ORD10051 | B52: C010 | C52: P202 | D52: 45744 | E52: 45754 | F52: POoja Shah | G52: Female | H52: 28906 | I52: Bengaluru | J52: South | K52: Home Appliances | L52: Iron | M52: 7 | N52: 2200 | O52: 15 | P52: 13090 | Q52: 1 | R52: UPI | S52: Aisha | T52: pooja.shah@company.com | U52: 9485166307 | V52: Completed | W52: =DATEDIF(H52,TODAY(),"Y") -> 47 | X52: =DATEDIF(D52,E52,"D") -> 10 | Y52: {=_xlfn.IFS(ISERROR(X52), "Pending", X52<=5, "On Time", X52>5, "Delayed")} -> Delayed
A53: ORD10052 | B53: C002 | C53: P301 | D53: 45894 | E53: 45897 | F53: Priya Patel | G53: Female | H53: 36777 | I53: Jaipur | J53: North | K53: Stationery | L53: Notebook | M53: 8 | N53: 60 | O53: 10 | P53: 432 | Q53: 5 | R53: Card | S53: Aisha | T53: priya.patel@company.com | U53: 9924709648 | V53: Cancelled | W53: =DATEDIF(H53,TODAY(),"Y") -> 25 | X53: =DATEDIF(D53,E53,"D") -> 3 | Y53: {=_xlfn.IFS(ISERROR(X53), "Pending", X53<=5, "On Time", X53>5, "Delayed")} -> On Time
A54: ORD10053 | B54: C005 | C54: P101 | D54: 45888 | E54: 45892 | F54: Vikas Mehta | G54: Male | H54: 27776 | I54: Kolkata | J54: East | K54: Electronics | L54: Laptop | M54: 12 | N54: 55000 | O54: 5 | P54: 627000 | Q54: 2 | R54: UPI | S54: Rahul | T54: vikas.mehta@company.com | U54: 9350554626 | V54: Pending | W54: =DATEDIF(H54,TODAY(),"Y") -> 50 | X54: =DATEDIF(D54,E54,"D") -> 4 | Y54: {=_xlfn.IFS(ISERROR(X54), "Pending", X54<=5, "On Time", X54>5, "Delayed")} -> On Time
A55: ORD10054 | B55: C008 | C55: P102 | D55: 45865 | E55: 45874 | F55: Kavya Nair | G55: Female | H55: 27488 | I55: Jaipur | J55: North | K55: Electronics | L55: Mouse | M55: 3 | N55: 700 | O55: 0 | P55: 2100 | Q55: 3 | R55: Card | S55: Karan | T55: kavya.nair@company.com | U55: 9743295580 | V55: Cancelled | W55: =DATEDIF(H55,TODAY(),"Y") -> 51 | X55: =DATEDIF(D55,E55,"D") -> 9 | Y55: {=_xlfn.IFS(ISERROR(X55), "Pending", X55<=5, "On Time", X55>5, "Delayed")} -> Delayed
A56: ORD10055 | B56: C003 | C56: P301 | D56: 45709 | E56: 45714 | F56: RoHit Singh | G56: Male | H56: 28076 | I56: Ahmedabad | J56: West | K56: Stationery | L56: Notebook | M56: 19 | N56: 60 | O56: 15 | P56: 969 | Q56: 4 | R56: Card | S56: Rahul | T56: rohit.singh@company.com | U56: 9822926495 | V56: Cancelled | W56: =DATEDIF(H56,TODAY(),"Y") -> 49 | X56: =DATEDIF(D56,E56,"D") -> 5 | Y56: {=_xlfn.IFS(ISERROR(X56), "Pending", X56<=5, "On Time", X56>5, "Delayed")} -> On Time
A57: ORD10056 | B57: C001 | C57: P301 | D57: 45879 | E57: 45880 | F57: Amit Sharma | G57: Male | H57: 28926 | I57: Jaipur | J57: North | K57: Stationery | L57: Notebook | M57: 9 | N57: 60 | O57: 20 | P57: 432 | Q57: 1 | R57: NetBanking | S57: Neha | T57: amit.sharma@company.com | U57: 9518298190 | V57: Pending | W57: =DATEDIF(H57,TODAY(),"Y") -> 47 | X57: =DATEDIF(D57,E57,"D") -> 1 | Y57: {=_xlfn.IFS(ISERROR(X57), "Pending", X57<=5, "On Time", X57>5, "Delayed")} -> On Time
A58: ORD10057 | B58: C001 | C58: P102 | D58: 46105 | E58: 46111 | F58: Amit Sharma | G58: Male | H58: 28851 | I58: Bengaluru | J58: South | K58: Electronics | L58: Mouse | M58: 6 | N58: 700 | O58: 0 | P58: 4200 | Q58: 4 | R58: UPI | S58: Rahul | T58: amit.sharmcompany.com | U58: 9366223547 | V58: Cancelled | W58: =DATEDIF(H58,TODAY(),"Y") -> 47 | X58: =DATEDIF(D58,E58,"D") -> 6 | Y58: {=_xlfn.IFS(ISERROR(X58), "Pending", X58<=5, "On Time", X58>5, "Delayed")} -> Delayed
A59: ORD10058 | B59: C003 | C59: P303 | D59: 46094 | E59: 46100 | F59: Rohit Singh | G59: Male | H59: 27499 | I59: Delhi | J59: North | K59: Stationery | L59: Marker | M59: 18 | N59: 45 | O59: 5 | P59: 769.5 | Q59: 1 | R59: Card | S59: Aisha | T59: rohit.singh@company.com | U59: 9701988524 | V59: Pending | W59: =DATEDIF(H59,TODAY(),"Y") -> 51 | X59: =DATEDIF(D59,E59,"D") -> 6 | Y59: {=_xlfn.IFS(ISERROR(X59), "Pending", X59<=5, "On Time", X59>5, "Delayed")} -> Delayed
A60: ORD10059 | B60: C007 | C60: P302 | D60: 45823 | E60: 45834 | F60: Arjun Rao | G60: Male | H60: 32496 | I60: Jaipur | J60: North | K60: Stationery | L60: Pen | M60: 8 | N60: 20 | O60: 5 | P60: 152 | Q60: 1 | R60: Card | S60: Ritika | T60: arjun.rao@company.com | U60: 9836327649 | V60: completed | W60: =DATEDIF(H60,TODAY(),"Y") -> 37 | X60: =DATEDIF(D60,E60,"D") -> 11 | Y60: {=_xlfn.IFS(ISERROR(X60), "Pending", X60<=5, "On Time", X60>5, "Delayed")} -> Delayed
A61: ORD10060 | B61: C005 | C61: P102 | D61: 45721 | E61: 45722 | F61: Vikas Mehta | G61: Male | H61: 29039 | I61: Jaipur | J61: North | K61: Electronics | L61: Mouse | M61: 8 | N61: 700 | O61: 10 | P61: 5040 | Q61: 1 | R61: NetBanking | S61: Aisha | T61: Vikas.mehta@company.com | U61: 9261800516 | V61: Cancelled | W61: =DATEDIF(H61,TODAY(),"Y") -> 47 | X61: =DATEDIF(D61,E61,"D") -> 1 | Y61: {=_xlfn.IFS(ISERROR(X61), "Pending", X61<=5, "On Time", X61>5, "Delayed")} -> On Time
A62: ORD10061 | B62: C008 | C62: P302 | D62: 46121 | E62: 46131 | F62: Kavya Nair | G62: Female | H62: 37972 | I62: Delhi | J62: North | K62: Stationery | L62: Pen | M62: 7 | N62: 20 | O62: 15 | P62: 119 | Q62: 5 | R62: Card | S62: Rahul | T62: kavya.nair@company.com | U62: 9950802015 | V62: Completed | W62: =DATEDIF(H62,TODAY(),"Y") -> 22 | X62: =DATEDIF(D62,E62,"D") -> 10 | Y62: {=_xlfn.IFS(ISERROR(X62), "Pending", X62<=5, "On Time", X62>5, "Delayed")} -> Delayed
... A74: ORD10073 | B74: C008 | C74: P103 | D74: 46004 | E74: 46014 | F74: Kavya Nair | G74: Female | H74: 29851 | I74: Jaipur | J74: North | K74: Electronics | L74: Keyboard | M74: 1 | N74: 1200 | O74: 5 | P74: 1140 | Q74: 3 | R74: UPI | S74: Aisha | T74: kavya.nair@company.com | U74: 9808988530 | V74: Cancelled | W74: =DATEDIF(H74,TODAY(),"Y") -> 44 | X74: =DATEDIF(D74,E74,"D") -> 10 | Y74: {=_xlfn.IFS(ISERROR(X74), "Pending", X74<=5, "On Time", X74>5, "Delayed")} -> Delayed
A75: ORD10074 | B75: C010 | C75: P202 | D75: 46057 | E75: 46069 | F75: Pooja Shah | G75: Female | H75: 29392 | J75: South | K75: Home Appliances | L75: Iron | M75: 1 | N75: 2200 | O75: 15 | P75: 1870 | Q75: 4 | R75: Card | S75: Aisha | T75: pooja.shah@company.com | U75: 9286410494 | V75: Completed | W75: =DATEDIF(H75,TODAY(),"Y") -> 46 | X75: =DATEDIF(D75,E75,"D") -> 12 | Y75: {=_xlfn.IFS(ISERROR(X75), "Pending", X75<=5, "On Time", X75>5, "Delayed")} -> Delayed
A76: ORD10075 | B76: C003 | C76: P103 | D76: 46048 | E76: 46050 | F76: Rohit Singh | G76: Male | H76: 29993 | I76: Pune | J76: West | K76: Electronics | L76: Keyboard | M76: 3 | N76: 1200 | O76: 10 | P76: 3240 | Q76: 5 | R76: Cash | S76: Rahul | T76: rohit.singh@company.com | U76: 9311555196 | V76: Completed | W76: =DATEDIF(H76,TODAY(),"Y") -> 44 | X76: =DATEDIF(D76,E76,"D") -> 2 | Y76: {=_xlfn.IFS(ISERROR(X76), "Pending", X76<=5, "On Time", X76>5, "Delayed")} -> On Time
A77: ORD10076 | B77: C008 | C77: P201 | D77: 45835 | E77: 45845 | F77: Kavya Nair | G77: Female | H77: 29495 | I77: Bengaluru | J77: South | K77: Home Appliances | L77: Mixer | M77: 10 | N77: 3500 | O77: 20 | P77: 28000 | Q77: 5 | R77: Card | S77: Ritika | T77: kavya.nair@company.com | U77: 9101810266 | V77: Completed | W77: =DATEDIF(H77,TODAY(),"Y") -> 45 | X77: =DATEDIF(D77,E77,"D") -> 10 | Y77: {=_xlfn.IFS(ISERROR(X77), "Pending", X77<=5, "On Time", X77>5, "Delayed")} -> Delayed
A78: ORD10077 | B78: C007 | C78: P102 | D78: 46098 | E78: 46100 | F78: Arjun Rao | G78: Male | H78: 29703 | I78: Delhi | J78: North | K78: Electronics | L78: Mouse | M78: 18 | N78: 700 | O78: 5 | P78: 11970 | Q78: 3 | R78: Card | S78: Neha | T78: arjun.rao@company.com | U78: 9464556593 | V78: Cancelled | W78: =DATEDIF(H78,TODAY(),"Y") -> 45 | X78: =DATEDIF(D78,E78,"D") -> 2 | Y78: {=_xlfn.IFS(ISERROR(X78), "Pending", X78<=5, "On Time", X78>5, "Delayed")} -> On Time
A79: ORD10078 | B79: C005 | C79: P102 | D79: 45817 | E79: 45826 | F79: Vikas Mehta | G79: Male | H79: 31384 | I79: Bengaluru | J79: South | K79: Electronics | L79: Mouse | M79: 12 | N79: 700 | O79: 15 | P79: 7140 | Q79: 2 | R79: UPI | S79: Rahul | T79: vikas.mehta@company.com | U79: 9338278358 | V79: Completed | W79: =DATEDIF(H79,TODAY(),"Y") -> 40 | X79: =DATEDIF(D79,E79,"D") -> 9 | Y79: {=_xlfn.IFS(ISERROR(X79), "Pending", X79<=5, "On Time", X79>5, "Delayed")} -> Delayed
A80: ORD10079 | B80: C009 | C80: P103 | D80: 45976 | E80: 45977 | F80: Mohit Verma | G80: Male | H80: 36234 | I80: Mumbai | J80: West | K80: Electronics | L80: Keyboard | M80: 8 | N80: 1200 | O80: 0 | P80: 9600 | Q80: 4 | R80: Card | S80: Rahul | T80: mohit.verma@company.com | U80: 9621410770 | V80: Pending | W80: =DATEDIF(H80,TODAY(),"Y") -> 27 | X80: =DATEDIF(D80,E80,"D") -> 1 | Y80: {=_xlfn.IFS(ISERROR(X80), "Pending", X80<=5, "On Time", X80>5, "Delayed")} -> On Time
A81: ORD10080 | B81: C003 | C81: P301 | D81: 45967 | E81: 45971 | F81: Rohit Singh | G81: Male | H81: 30504 | I81: Pune | J81: West | K81: Stationery | L81: Notebook | M81: 2 | N81: 60 | O81: 0 | P81: 120 | Q81: 2 | R81: UPI | S81: Rahul | T81: rohit.singh@company.com | U81: 9981333189 | V81: Completed | W81: =DATEDIF(H81,TODAY(),"Y") -> 43 | X81: =DATEDIF(D81,E81,"D") -> 4 | Y81: {=_xlfn.IFS(ISERROR(X81), "Pending", X81<=5, "On Time", X81>5, "Delayed")} -> On Time
A82: ORD10081 | B82: C001 | C82: P303 | D82: 45658 | E82: 45664 | F82: Amit Sharma | G82: Male | H82: 32662 | I82: Pune | J82: West | K82: Stationery | L82: Marker | M82: 10 | N82: 45 | O82: 15 | P82: 382.5 | Q82: 3 | R82: NetBanking | S82: Ritika | T82: amit.sharma@company.com | U82: 9723450355 | V82: Cancelled | W82: =DATEDIF(H82,TODAY(),"Y") -> 37 | X82: =DATEDIF(D82,E82,"D") -> 6 | Y82: {=_xlfn.IFS(ISERROR(X82), "Pending", X82<=5, "On Time", X82>5, "Delayed")} -> Delayed
A83: ORD10082 | B83: C005 | C83: P201 | D83: 46137 | E83: 46145 | F83: Vikas Mehta | G83: Male | H83: 30122 | I83: Kolkata | J83: East | K83: Home Appliances | L83: Mixer | M83: 12 | N83: 3500 | O83: 5 | P83: 39900 | Q83: 3 | R83: NetBanking | S83: Aisha | T83: vikas.mehta@company.com | U83: 9886243907 | V83: Pending | W83: =DATEDIF(H83,TODAY(),"Y") -> 44 | X83: =DATEDIF(D83,E83,"D") -> 8 | Y83: {=_xlfn.IFS(ISERROR(X83), "Pending", X83<=5, "On Time", X83>5, "Delayed")} -> Delayed
A84: ORD10083 | B84: C003 | C84: P301 | D84: 45919 | E84: 45927 | F84: Rohit Singh | G84: Male | H84: 37065 | I84: Mumbai | J84: West | K84: Stationery | L84: Notebook | M84: 2 | N84: 60 | O84: 15 | P84: 102 | Q84: 1 | R84: UPI | S84: Neha | T84: rohit.singh@company.com | U84: 9473931904 | V84: Completed | W84: =DATEDIF(H84,TODAY(),"Y") -> 25 | X84: =DATEDIF(D84,E84,"D") -> 8 | Y84: {=_xlfn.IFS(ISERROR(X84), "Pending", X84<=5, "On Time", X84>5, "Delayed")} -> Delayed
A85: ORD10084 | B85: C003 | C85: P103 | D85: 45734 | E85: 45737 | F85: Rohit Singh | G85: Male | H85: 30516 | I85: Hyderabad | J85: South | K85: Electronics | L85: Keyboard | M85: 18 | N85: 1200 | O85: 15 | P85: 18360 | Q85: 3 | R85: Card | S85: Neha | T85: rohit.singh@company.com | U85: 9287159610 | V85: Pending | W85: =DATEDIF(H85,TODAY(),"Y") -> 43 | X85: =DATEDIF(D85,E85,"D") -> 3 | Y85: {=_xlfn.IFS(ISERROR(X85), "Pending", X85<=5, "On Time", X85>5, "Delayed")} -> On Time
A86: ORD10085 | B86: C008 | C86: P104 | D86: 45960 | E86: 45961 | F86: Kavya Nair | G86: Female | H86: 34052 | I86: Mumbai | J86: West | K86: Electronics | L86: Monitor | M86: 18 | N86: 12000 | O86: 15 | P86: 183600 | Q86: 2 | R86: Cash | S86: Rahul | T86: kavya.nair@company.com | U86: 9876513858 | V86: Completed | W86: =DATEDIF(H86,TODAY(),"Y") -> 33 | X86: =DATEDIF(D86,E86,"D") -> 1 | Y86: {=_xlfn.IFS(ISERROR(X86), "Pending", X86<=5, "On Time", X86>5, "Delayed")} -> On Time
A87: ORD10086 | B87: C007 | C87: P302 | D87: 45961 | E87: 45972 | F87: Arjun Rao | G87: Male | H87: 34977 | I87: Ahmedabad | J87: West | K87: Stationery | L87: Pen | M87: 7 | N87: 20 | O87: 0 | P87: 140 | Q87: 2 | R87: Card | S87: Ritika | T87: arjun.rao@company.com | U87: 9237400853 | V87: Cancelled | W87: =DATEDIF(H87,TODAY(),"Y") -> 30 | X87: =DATEDIF(D87,E87,"D") -> 11 | Y87: {=_xlfn.IFS(ISERROR(X87), "Pending", X87<=5, "On Time", X87>5, "Delayed")} -> Delayed
... A119: ORD10118 | B119: C001 | C119: P303 | D119: 45808 | E119: 45819 | F119: Amit Sharma | G119: Male | H119: 34889 | I119: Pune | J119: West | K119: Stationery | L119: Marker | M119: 16 | N119: 45 | O119: 0 | P119: 720 | Q119: 1 | R119: NetBanking | S119: Aisha | T119: amit.sharma@company.com | U119: 9807154421 | V119: Completed | W119: =DATEDIF(H119,TODAY(),"Y") -> 31 | X119: =DATEDIF(D119,E119,"D") -> 11 | Y119: {=_xlfn.IFS(ISERROR(X119), "Pending", X119<=5, "On Time", X119>5, "Delayed")} -> Delayed
A120: ORD10119 | B120: C009 | C120: P103 | D120: 45807 | E120: 45810 | F120: Mohit Verma | G120: Male | H120: 32358 | I120: Ahmedabad | J120: West | K120: Electronics | L120: Keyboard | M120: Ten | N120: 1200 | O120: 15 | P120: 7140 | Q120: 4 | R120: UPI | S120: Karan | T120: mohit.verma@company.com | U120: 9919834000 | V120: Pending | W120: =DATEDIF(H120,TODAY(),"Y") -> 38 | X120: =DATEDIF(D120,E120,"D") -> 3 | Y120: {=_xlfn.IFS(ISERROR(X120), "Pending", X120<=5, "On Time", X120>5, "Delayed")} -> On Time
A121: ORD10120 | B121: C002 | C121: P104 | D121: 45888 | E121: 45899 | F121: Priya Patel | G121: Female | H121: 32696 | I121: Jaipur | J121: North | K121: Electronics | L121: Monitor | M121: 14 | N121: 12000 | O121: 15 | P121: 142800 | Q121: 2 | R121: NetBanking | S121: Aisha | T121: priya.patel@company.com | U121: 9739798818 | V121: Pending | W121: =DATEDIF(H121,TODAY(),"Y") -> 37 | X121: =DATEDIF(D121,E121,"D") -> 11 | Y121: {=_xlfn.IFS(ISERROR(X121), "Pending", X121<=5, "On Time", X121>5, "Delayed")} -> Delayed
A122: ORD10121 | B122: C003 | C122: P203 | D122: 46005 | E122: 46007 | F122: Rohit Singh | G122: Male | H122: 34284 | I122: Pune | J122: West | K122: Home Appliances | L122: Microwave | M122: 8 | N122: 8500 | O122: 20 | P122: 54400 | Q122: 3 | R122: Card | S122: Rahul | T122: rohit.singh@company.com | U122: 9208625306 | V122: Completed | W122: =DATEDIF(H122,TODAY(),"Y") -> 32 | X122: =DATEDIF(D122,E122,"D") -> 2 | Y122: {=_xlfn.IFS(ISERROR(X122), "Pending", X122<=5, "On Time", X122>5, "Delayed")} -> On Time
A123: ORD10122 | B123: C007 | C123: P303 | D123: 46053 | E123: 46063 | F123: Arjun Rao | G123: Male | H123: 36527 | I123: Bengaluru | J123: South | K123: Stationery | L123: Marker | M123: 3 | N123: 45 | O123: 0 | P123: 135 | Q123: 4 | R123: UPI | S123: Aisha | T123: arjun.rao@company.com | U123: 9970178536 | V123: Cancelled | W123: =DATEDIF(H123,TODAY(),"Y") -> 26 | X123: =DATEDIF(D123,E123,"D") -> 10 | Y123: {=_xlfn.IFS(ISERROR(X123), "Pending", X123<=5, "On Time", X123>5, "Delayed")} -> Delayed
A124: ORD10123 | B124: C001 | C124: P102 | D124: 46025 | E124: 46026 | F124: Amit Sharma | G124: Male | H124: 31585 | I124: Jaipur | J124: North | K124: Electronics | L124: Mouse | M124: 13 | N124: 700 | O124: 5 | P124: 8645 | Q124: 3 | R124: Card | S124: Neha | T124: amit.sharma@company.com | U124: 9633745195 | V124: Pending | W124: =DATEDIF(H124,TODAY(),"Y") -> 40 | X124: =DATEDIF(D124,E124,"D") -> 1 | Y124: {=_xlfn.IFS(ISERROR(X124), "Pending", X124<=5, "On Time", X124>5, "Delayed")} -> On Time
A125: ORD10124 | B125: C004 | C125: P103 | D125: 45950 | E125: 45956 | F125: Anita Gupta | G125: Female | H125: 31459 | I125: Mumbai | J125: West | K125: Electronics | L125: Keyboard | M125: 14 | N125: 1200 | O125: 20 | P125: 13440 | Q125: 5 | R125: NetBanking | S125: Aisha | T125: anita.gupta@company.com | U125: 9922102053 | V125: Completed | W125: =DATEDIF(H125,TODAY(),"Y") -> 40 | X125: =DATEDIF(D125,E125,"D") -> 6 | Y125: {=_xlfn.IFS(ISERROR(X125), "Pending", X125<=5, "On Time", X125>5, "Delayed")} -> Delayed
A126: ORD10125 | B126: C002 | C126: P303 | D126: 45788 | E126: 45798 | F126: Priya Patel | G126: Female | H126: 33499 | I126: Delhi | J126: North | K126: Stationery | L126: Marker | M126: 2 | N126: 45 | O126: 5 | P126: 85.5 | Q126: 3 | R126: UPI | S126: Ritika | T126: priya.patel@company.com | U126: 9135963930 | V126: Cancelled | W126: =DATEDIF(H126,TODAY(),"Y") -> 34 | X126: =DATEDIF(D126,E126,"D") -> 10 | Y126: {=_xlfn.IFS(ISERROR(X126), "Pending", X126<=5, "On Time", X126>5, "Delayed")} -> Delayed
A127: ORD10126 | B127: C004 | C127: P103 | D127: 46024 | E127: 46028 | F127: Anita Gupta | G127: Female | H127: 29677 | I127: Bengaluru | J127: South | K127: Electronics | L127: Keyboard | M127: 2 | N127: 1200 | O127: 20 | P127: 1920 | Q127: 3 | R127: Card | S127: Neha | T127: anita.gupta@company.com | U127: 9429405275 | V127: Completed | W127: =DATEDIF(H127,TODAY(),"Y") -> 45 | X127: =DATEDIF(D127,E127,"D") -> 4 | Y127: {=_xlfn.IFS(ISERROR(X127), "Pending", X127<=5, "On Time", X127>5, "Delayed")} -> On Time
A128: ORD10127 | B128: C003 | C128: P101 | D128: 46132 | E128: 46138 | F128: Rohit Singh | G128: Male | H128: 38331 | I128: Bengaluru | J128: South | K128: Electronics | L128: Laptop | M128: 10 | N128: 55000 | O128: 5 | P128: 522500 | Q128: 5 | R128: UPI | S128: Aisha | T128: rohit.singh@company.com | U128: 9521757571 | V128: Pending | W128: =DATEDIF(H128,TODAY(),"Y") -> 21 | X128: =DATEDIF(D128,E128,"D") -> 6 | Y128: {=_xlfn.IFS(ISERROR(X128), "Pending", X128<=5, "On Time", X128>5, "Delayed")} -> Delayed
A129: ORD10128 | B129: C006 | C129: P201 | D129: 45873 | E129: 45874 | F129: Sneha Joshi | G129: Female | H129: 30766 | I129: Jaipur | J129: North | K129: Home Appliances | L129: Mixer | M129: 15 | N129: 3500 | O129: 10 | P129: 47250 | Q129: 3 | R129: NetBanking | S129: Neha | T129: sneha.joshi@company.com | U129: 9467375455 | V129: Completed | W129: =DATEDIF(H129,TODAY(),"Y") -> 42 | X129: =DATEDIF(D129,E129,"D") -> 1 | Y129: {=_xlfn.IFS(ISERROR(X129), "Pending", X129<=5, "On Time", X129>5, "Delayed")} -> On Time
A130: ORD10129 | B130: C002 | C130: P202 | D130: 45882 | E130: 45887 | F130: Priya Patel | G130: Female | H130: 30203 | I130: Bengaluru | J130: South | K130: Home Appliances | L130: Iron | M130: 10 | N130: 2200 | O130: 15 | P130: 18700 | Q130: 4 | R130: Card | S130: Rahul | T130: priya.patel@company.com | U130: 9838809695 | V130: Pending | W130: =DATEDIF(H130,TODAY(),"Y") -> 43 | X130: =DATEDIF(D130,E130,"D") -> 5 | Y130: {=_xlfn.IFS(ISERROR(X130), "Pending", X130<=5, "On Time", X130>5, "Delayed")} -> On Time
A131: ORD10130 | B131: C006 | C131: P201 | D131: 45824 | E131: 45832 | F131: Sneha Joshi | G131: Female | H131: 34015 | I131: Pune | J131: West | K131: Home Appliances | L131: Mixer | M131: 11 | N131: 3500 | O131: 5 | P131: 36575 | Q131: 5 | R131: Cash | S131: Ritika | T131: sneha.joshi@company.com | U131: 9296609782 | V131: Cancelled | W131: =DATEDIF(H131,TODAY(),"Y") -> 33 | X131: =DATEDIF(D131,E131,"D") -> 8 | Y131: {=_xlfn.IFS(ISERROR(X131), "Pending", X131<=5, "On Time", X131>5, "Delayed")} -> Delayed
A132: ORD10131 | B132: C004 | C132: P103 | D132: 46139 | E132: 46142 | F132: Anita Gupta | G132: Female | H132: 37837 | I132: Bengaluru | J132: South | K132: Electronics | L132: Keyboard | M132: 14 | N132: 1200 | O132: 0 | P132: 16800 | Q132: 5 | R132: Cash | S132: Rahul | T132: anita.gupta@company.com | U132: 9848259992 | V132: Cancelled | W132: =DATEDIF(H132,TODAY(),"Y") -> 23 | X132: =DATEDIF(D132,E132,"D") -> 3 | Y132: {=_xlfn.IFS(ISERROR(X132), "Pending", X132<=5, "On Time", X132>5, "Delayed")} -> On Time
... A299: ORD10298 | B299: C003 | C299: P101 | D299: 45670 | E299: 45673 | F299: Rohit Singh | G299: Male | H299: 38047 | I299: Hyderabad | J299: South | K299: Electronics | L299: Laptop | M299: 11 | N299: 55000 | O299: 5 | P299: 574750 | Q299: 1 | R299: UPI | S299: Ritika | T299: rohit.singh@company.com | U299: 9482699727 | V299: Cancelled | W299: =DATEDIF(H299,TODAY(),"Y") -> 22 | X299: =DATEDIF(D299,E299,"D") -> 3 | Y299: {=_xlfn.IFS(ISERROR(X299), "Pending", X299<=5, "On Time", X299>5, "Delayed")} -> On Time
A300: ORD10299 | B300: C007 | C300: P201 | D300: 45935 | E300: 45947 | F300: Arjun Rao | G300: Male | H300: 33639 | I300: Jaipur | J300: North | K300: Home Appliances | L300: Mixer | M300: 12 | N300: 3500 | O300: 0 | P300: 42000 | Q300: 2 | R300: NetBanking | T300: arjun.rao@company.com | U300: 9332473934 | V300: Pending | W300: =DATEDIF(H300,TODAY(),"Y") -> 34 | X300: =DATEDIF(D300,E300,"D") -> 12 | Y300: {=_xlfn.IFS(ISERROR(X300), "Pending", X300<=5, "On Time", X300>5, "Delayed")} -> Delayed
A301: ORD10300 | B301: C009 | C301: P303 | D301: 46078 | E301: 46089 | F301: Mohit Verma | G301: Male | H301: 37647 | I301: Hyderabad | J301: South | K301: Stationery | L301: Marker | M301: 15 | N301: 45 | O301: 10 | P301: 607.5 | Q301: 2 | R301: Cash | S301: Karan | T301: mohit.verma@company.com | U301: 9647657382 | V301: Pending | W301: =DATEDIF(H301,TODAY(),"Y") -> 23 | X301: =DATEDIF(D301,E301,"D") -> 11 | Y301: {=_xlfn.IFS(ISERROR(X301), "Pending", X301<=5, "On Time", X301>5, "Delayed")} -> Delayed
A302: ORD10301 | B302: C001 | C302: P303 | D302: 45793 | E302: 45803 | F302: Amit Sharma | G302: Male | H302: 31917 | I302: Bengaluru | J302: South | K302: Stationery | L302: Marker | M302: 13 | N302: 45 | O302: 0 | P302: 585 | Q302: 5 | R302: NetBanking | S302: Rahul | T302: amit.sharma@company.com | U302: 9736797776 | V302: Pending | W302: =DATEDIF(H302,TODAY(),"Y") -> 39 | X302: =DATEDIF(D302,E302,"D") -> 10 | Y302: {=_xlfn.IFS(ISERROR(X302), "Pending", X302<=5, "On Time", X302>5, "Delayed")} -> Delayed
A303: ORD10302 | B303: C003 | C303: P101 | D303: 46024 | E303: 46027 | F303: Rohit Singh | G303: Male | H303: 27584 | I303: Bengaluru | J303: South | K303: Electronics | L303: Laptop | M303: 8 | N303: 55000 | O303: 0 | P303: 440000 | Q303: 2 | R303: UPI | S303: Karan | T303: rohit.singh@company.com | U303: 9745773533 | V303: Cancelled | W303: =DATEDIF(H303,TODAY(),"Y") -> 51 | X303: =DATEDIF(D303,E303,"D") -> 3 | Y303: {=_xlfn.IFS(ISERROR(X303), "Pending", X303<=5, "On Time", X303>5, "Delayed")} -> On Time
A304: ORD10303 | B304: C006 | C304: P101 | D304: 45861 | E304: 45865 | F304: Sneha Joshi | G304: Female | H304: 29502 | I304: Delhi | J304: North | K304: Electronics | L304: Laptop | M304: 4 | N304: 55000 | O304: 20 | P304: 176000 | Q304: 5 | R304: Cash | S304: Rahul | T304: sneha.joshi@company.com | U304: 9246715757 | V304: Pending | W304: =DATEDIF(H304,TODAY(),"Y") -> 45 | X304: =DATEDIF(D304,E304,"D") -> 4 | Y304: {=_xlfn.IFS(ISERROR(X304), "Pending", X304<=5, "On Time", X304>5, "Delayed")} -> On Time
A305: ORD10304 | B305: C008 | C305: P201 | D305: 46135 | E305: 46138 | F305: Kavya Nair | G305: Female | H305: 32693 | I305: Ahmedabad | J305: West | K305: Home Appliances | L305: Mixer | M305: 19 | N305: 3500 | O305: 5 | P305: 63175 | Q305: 1 | R305: Card | S305: Neha | T305: kavya.nair@company.com | U305: 9904065774 | V305: Completed | W305: =DATEDIF(H305,TODAY(),"Y") -> 37 | X305: =DATEDIF(D305,E305,"D") -> 3 | Y305: {=_xlfn.IFS(ISERROR(X305), "Pending", X305<=5, "On Time", X305>5, "Delayed")} -> On Time
A306: ORD10305 | B306: C005 | C306: P103 | D306: 45718 | E306: 45722 | F306: Vikas Mehta | G306: Male | H306: 36027 | I306: Jaipur | J306: North | K306: Electronics | L306: Keyboard | M306: 17 | N306: 1200 | O306: 15 | P306: 17340 | Q306: 2 | R306: NetBanking | S306: Rahul | T306: vikas.mehta@company.com | U306: 9652985385 | V306: Completed | W306: =DATEDIF(H306,TODAY(),"Y") -> 28 | X306: =DATEDIF(D306,E306,"D") -> 4 | Y306: {=_xlfn.IFS(ISERROR(X306), "Pending", X306<=5, "On Time", X306>5, "Delayed")} -> On Time
A307: ORD10306 | B307: C008 | C307: P202 | D307: 46062 | E307: 46070 | F307: Kavya Nair | G307: Female | H307: 36954 | I307: Hyderabad | J307: South | K307: Home Appliances | L307: Iron | M307: 8 | N307: 2200 | O307: 5 | P307: 16720 | Q307: 3 | R307: Card | S307: Neha | T307: kavya.nair@company.com | U307: 9427001508 | V307: Pending | W307: =DATEDIF(H307,TODAY(),"Y") -> 25 | X307: =DATEDIF(D307,E307,"D") -> 8 | Y307: {=_xlfn.IFS(ISERROR(X307), "Pending", X307<=5, "On Time", X307>5, "Delayed")} -> Delayed
A308: ORD10307 | B308: C006 | C308: P102 | D308: 45704 | E308: 45714 | F308: Sneha Joshi | G308: Female | H308: 33727 | I308: Mumbai | J308: West | K308: Electronics | L308: Mouse | M308: 17 | N308: 700 | O308: 20 | P308: 9520 | Q308: 4 | R308: NetBanking | S308: Neha | T308: sneha.joshi@company.com | U308: 9666803655 | V308: Completed | W308: =DATEDIF(H308,TODAY(),"Y") -> 34 | X308: =DATEDIF(D308,E308,"D") -> 10 | Y308: {=_xlfn.IFS(ISERROR(X308), "Pending", X308<=5, "On Time", X308>5, "Delayed")} -> Delayed
A309: ORD10308 | B309: C006 | C309: P203 | D309: 45897 | E309: 45908 | F309: Sneha Joshi | G309: Female | H309: 28122 | I309: Pune | J309: West | K309: Home Appliances | L309: Microwave | M309: 6 | N309: 8500 | O309: 15 | P309: 43350 | Q309: 1 | R309: Cash | S309: Aisha | T309: sneha.joshi@company.com | U309: 9134878547 | V309: Completed | W309: =DATEDIF(H309,TODAY(),"Y") -> 49 | X309: =DATEDIF(D309,E309,"D") -> 11 | Y309: {=_xlfn.IFS(ISERROR(X309), "Pending", X309<=5, "On Time", X309>5, "Delayed")} -> Delayed
A310: ORD10309 | B310: C010 | C310: P201 | D310: 45936 | E310: 45941 | F310: Pooja Shah | G310: Female | H310: 31511 | I310: Hyderabad | J310: South | K310: Home Appliances | L310: Mixer | M310: 3 | N310: 3500 | O310: 10 | P310: 9450 | Q310: 1 | R310: NetBanking | S310: Rahul | T310: pooja.shah@company.com | U310: 9253593557 | V310: Completed | W310: =DATEDIF(H310,TODAY(),"Y") -> 40 | X310: =DATEDIF(D310,E310,"D") -> 5 | Y310: {=_xlfn.IFS(ISERROR(X310), "Pending", X310<=5, "On Time", X310>5, "Delayed")} -> On Time
A311: ORD10310 | B311: C009 | C311: P104 | D311: 45674 | E311: 45686 | F311: Mohit Verma | G311: Male | H311: 32734 | I311: Ahmedabad | J311: West | K311: Electronics | L311: Monitor | M311: 2 | N311: 12000 | O311: 20 | P311: 19200 | Q311: 1 | R311: Card | S311: Aisha | T311: mohit.verma@company.com | U311: 9183094051 | V311: Completed | W311: =DATEDIF(H311,TODAY(),"Y") -> 37 | X311: =DATEDIF(D311,E311,"D") -> 12 | Y311: {=_xlfn.IFS(ISERROR(X311), "Pending", X311<=5, "On Time", X311>5, "Delayed")} -> Delayed
A312: ORD10311 | B312: C005 | C312: P302 | D312: 45943 | E312: 45946 | F312: Vikas Mehta | G312: Male | H312: 33272 | I312: Delhi | J312: North | K312: Stationery | L312: Pen | M312: 12 | N312: 20 | O312: 20 | P312: 192 | Q312: 2 | R312: Card | S312: Rahul | T312: vikas.mehta@company.com | U312: 9293147620 | V312: Completed | W312: =DATEDIF(H312,TODAY(),"Y") -> 35 | X312: =DATEDIF(D312,E312,"D") -> 3 | Y312: {=_xlfn.IFS(ISERROR(X312), "Pending", X312<=5, "On Time", X312>5, "Delayed")} -> On Time
... A357: ORD10356 | B357: C008 | C357: P303 | D357: 45941 | E357: 45951 | F357: Kavya Nair | G357: Female | H357: 33746 | I357: Jaipur | J357: North | K357: Stationery | L357: Marker | M357: 5 | N357: 45 | O357: 5 | P357: 213.75 | Q357: 1 | R357: Card | S357: Neha | T357: kavya.nair@company.com | U357: 9810433484 | V357: Completed | W357: =DATEDIF(H357,TODAY(),"Y") -> 34 | X357: =DATEDIF(D357,E357,"D") -> 10 | Y357: {=_xlfn.IFS(ISERROR(X357), "Pending", X357<=5, "On Time", X357>5, "Delayed")} -> Delayed
A358: ORD10357 | B358: C006 | C358: P102 | D358: \ | E358: 45699 | F358: Sneha Joshi | G358: Female | H358: 32792 | I358: Mumbai | J358: West | K358: Electronics | L358: Mouse | M358: 3 | N358: 700 | O358: 15 | P358: 1785 | Q358: 4 | R358: Cash | S358: Karan | T358: sneha.joshi@company.com | U358: 9990243436 | V358: Completed | W358: =DATEDIF(H358,TODAY(),"Y") -> 36 | X358: =DATEDIF(D358,E358,"D") -> #VALUE! | Y358: {=_xlfn.IFS(ISERROR(X358), "Pending", X358<=5, "On Time", X358>5, "Delayed")} -> Pending
A359: ORD10358 | B359: C009 | C359: P203 | D359: 46005 | E359: 46017 | F359: Mohit Verma | G359: Male | H359: 29289 | I359: Jaipur | J359: North | K359: Home Appliances | L359: Microwave | M359: 12 | N359: 8500 | O359: 5 | P359: 96900 | Q359: 3 | R359: Card | S359: Aisha | T359: mohit.verma@company.com | U359: 9396678031 | V359: Pending | W359: =DATEDIF(H359,TODAY(),"Y") -> 46 | X359: =DATEDIF(D359,E359,"D") -> 12 | Y359: {=_xlfn.IFS(ISERROR(X359), "Pending", X359<=5, "On Time", X359>5, "Delayed")} -> Delayed
A360: ORD10359 | B360: C006 | C360: P203 | D360: 46123 | E360: 46131 | F360: Sneha Joshi | G360: Female | H360: 29009 | I360: Pune | J360: West | K360: Home Appliances | L360: Microwave | M360: 4 | N360: 8500 | O360: 15 | P360: 28900 | Q360: 4 | R360: NetBanking | S360: Aisha | T360: sneha.joshi@company.com | U360: 9818591245 | V360: Pending | W360: =DATEDIF(H360,TODAY(),"Y") -> 47 | X360: =DATEDIF(D360,E360,"D") -> 8 | Y360: {=_xlfn.IFS(ISERROR(X360), "Pending", X360<=5, "On Time", X360>5, "Delayed")} -> Delayed
A361: ORD10360 | B361: C003 | C361: P302 | D361: 45766 | E361: 45769 | F361: Rohit Singh | G361: Male | H361: 35164 | I361: Jaipur | J361: North | K361: Stationery | L361: Pen | M361: 16 | N361: 20 | O361: 10 | P361: 288 | Q361: 4 | R361: Cash | S361: Neha | T361: rohit.singh@company.com | U361: 9505550047 | V361: Cancelled | W361: =DATEDIF(H361,TODAY(),"Y") -> 30 | X361: =DATEDIF(D361,E361,"D") -> 3 | Y361: {=_xlfn.IFS(ISERROR(X361), "Pending", X361<=5, "On Time", X361>5, "Delayed")} -> On Time
A362: ORD10361 | B362: C003 | C362: P301 | D362: 46152 | E362: 46160 | F362: Rohit Singh | G362: Male | H362: 36233 | I362: Mumbai | J362: West | K362: Stationery | L362: Notebook | M362: 3 | N362: 60 | O362: 20 | P362: 144 | Q362: 4 | R362: UPI | S362: Karan | T362: rohit.singh@company.com | U362: 9469828772 | V362: Pending | W362: =DATEDIF(H362,TODAY(),"Y") -> 27 | X362: =DATEDIF(D362,E362,"D") -> 8 | Y362: {=_xlfn.IFS(ISERROR(X362), "Pending", X362<=5, "On Time", X362>5, "Delayed")} -> Delayed
A363: ORD10362 | B363: C009 | C363: P202 | D363: 45858 | E363: 45864 | F363: Mohit Verma | G363: Male | H363: 30751 | I363: Mumbai | J363: West | K363: Home Appliances | L363: Iron | M363: 19 | N363: 2200 | O363: 10 | P363: 37620 | Q363: 2 | R363: Cash | S363: Karan | T363: mohit.verma@company.com | U363: 9885092680 | V363: Pending | W363: =DATEDIF(H363,TODAY(),"Y") -> 42 | X363: =DATEDIF(D363,E363,"D") -> 6 | Y363: {=_xlfn.IFS(ISERROR(X363), "Pending", X363<=5, "On Time", X363>5, "Delayed")} -> Delayed
A364: ORD10363 | B364: C009 | C364: P103 | D364: 46045 | E364: 46049 | F364: Mohit Verma | G364: Male | H364: 30932 | I364: Hyderabad | J364: South | K364: Electronics | L364: Keyboard | M364: 7 | N364: 1200 | O364: 20 | P364: 6720 | Q364: 3 | R364: Card | S364: Neha | T364: mohit.verma@company.com | U364: 9362319457 | V364: Cancelled | W364: =DATEDIF(H364,TODAY(),"Y") -> 41 | X364: =DATEDIF(D364,E364,"D") -> 4 | Y364: {=_xlfn.IFS(ISERROR(X364), "Pending", X364<=5, "On Time", X364>5, "Delayed")} -> On Time
A365: ORD10364 | B365: C010 | C365: P302 | D365: 46097 | E365: 46102 | F365: Pooja Shah | G365: Female | H365: 32784 | I365: Bengaluru | J365: South | K365: Stationery | L365: Pen | M365: 20 | N365: 20 | O365: 20 | P365: 320 | Q365: 5 | R365: Card | S365: Neha | T365: pooja.shah@company.com | U365: 9223945130 | V365: Pending | W365: =DATEDIF(H365,TODAY(),"Y") -> 36 | X365: =DATEDIF(D365,E365,"D") -> 5 | Y365: {=_xlfn.IFS(ISERROR(X365), "Pending", X365<=5, "On Time", X365>5, "Delayed")} -> On Time
A366: ORD10365 | B366: C002 | C366: P103 | D366: 45777 | E366: 45784 | F366: Priya Patel | G366: Female | H366: 31156 | I366: Hyderabad | J366: South | K366: Electronics | L366: Keyboard | M366: 19 | N366: 1200 | O366: 5 | P366: 21660 | Q366: 3 | R366: Card | S366: Ritika | T366: priya.patel@company.com | U366: 9910804926 | V366: Pending | W366: =DATEDIF(H366,TODAY(),"Y") -> 41 | X366: =DATEDIF(D366,E366,"D") -> 7 | Y366: {=_xlfn.IFS(ISERROR(X366), "Pending", X366<=5, "On Time", X366>5, "Delayed")} -> Delayed
A367: ORD10366 | B367: C010 | C367: P302 | D367: 45691 | E367: 45701 | F367: Pooja Shah | G367: Female | H367: 37846 | I367: Hyderabad | J367: South | K367: Stationery | L367: Pen | M367: 5 | N367: 20 | O367: 0 | P367: 100 | Q367: 2 | R367: UPI | S367: Rahul | T367: pooja.shah@company.com | U367: 9274269744 | V367: Pending | W367: =DATEDIF(H367,TODAY(),"Y") -> 23 | X367: =DATEDIF(D367,E367,"D") -> 10 | Y367: {=_xlfn.IFS(ISERROR(X367), "Pending", X367<=5, "On Time", X367>5, "Delayed")} -> Delayed
A368: ORD10367 | B368: C002 | C368: P303 | D368: 46088 | E368: 46097 | F368: Priya Patel | G368: Female | H368: 30629 | I368: Jaipur | J368: North | K368: Stationery | L368: Marker | M368: 16 | N368: 45 | O368: 15 | P368: 612 | Q368: 5 | R368: Cash | S368: Aisha | T368: priya.patel@company.com | U368: 9223196101 | V368: Cancelled | W368: =DATEDIF(H368,TODAY(),"Y") -> 42 | X368: =DATEDIF(D368,E368,"D") -> 9 | Y368: {=_xlfn.IFS(ISERROR(X368), "Pending", X368<=5, "On Time", X368>5, "Delayed")} -> Delayed
A369: ORD10368 | B369: C008 | C369: P202 | D369: 45780 | E369: 45792 | F369: Kavya Nair | G369: Female | H369: 28070 | I369: Jaipur | J369: North | K369: Home Appliances | L369: Iron | M369: 1 | N369: 2200 | O369: 10 | P369: 1980 | Q369: 5 | R369: Card | S369: Rahul | T369: kavya.nair@company.com | U369: 9888477457 | V369: Completed | W369: =DATEDIF(H369,TODAY(),"Y") -> 49 | X369: =DATEDIF(D369,E369,"D") -> 12 | Y369: {=_xlfn.IFS(ISERROR(X369), "Pending", X369<=5, "On Time", X369>5, "Delayed")} -> Delayed
A370: ORD10369 | B370: C010 | C370: P301 | D370: 46113 | E370: 46117 | F370: Pooja Shah | G370: Female | H370: 31868 | I370: Hyderabad | J370: South | K370: Stationery | L370: Notebook | M370: 19 | N370: 60 | O370: 15 | P370: 969 | Q370: 4 | R370: NetBanking | S370: Neha | T370: pooja.shah@company.com | U370: 9435947486 | V370: Cancelled | W370: =DATEDIF(H370,TODAY(),"Y") -> 39 | X370: =DATEDIF(D370,E370,"D") -> 4 | Y370: {=_xlfn.IFS(ISERROR(X370), "Pending", X370<=5, "On Time", X370>5, "Delayed")} -> On Time
...

Sheet Product Lookup Report (Q4)
B2: Product ID | C2: Product Name | D2: Supplier | E2: Cost Price | F2: Warrenty (Months)
B3: P103 | C3: =IFERROR(_xlfn.XLOOKUP('Product Lookup Report (Q4)'!$B$3,Product_master!$A$2:$A$11,Product_master!B2:B11),"Product Not Found") -> Keyboard | D3: =IFERROR(_xlfn.XLOOKUP('Product Lookup Report (Q4)'!$B$3,Product_master!$A$2:$A$11,Product_master!D2:D11),"Product Not Found") -> TechHub | E3: =IFERROR(_xlfn.XLOOKUP('Product Lookup Report (Q4)'!$B$3,Product_master!$A$2:$A$11,Product_master!E2:E11),"Product Not Found") -> 900 | F3: =IFERROR(_xlfn.XLOOKUP('Product Lookup Report (Q4)'!$B$3,Product_master!$A$2:$A$11,Product_master!F2:F11),"Product Not Found") -> 6

Sheet Sales Summary Report (Q5)
B7: Total Sales Amount Generated From Electronics Cateogary For Completed orders | C7: =SUMIFS(Sales_Data!P3:P502,Sales_Data!K3:K502,"Electronics",Sales_Data!V3:V502,"Completed") -> 7222090
B8: Total Sales Amount Generated by Neha in North Region | C8: =SUMIFS(Sales_Data!P2:P501,Sales_Data!S2:S501,"Neha",Sales_Data!J2:J501,"North") -> 1550369.2
B9: Number of orders where Discount Percentage is greater than or equal to 15% and the Payment Mode is UPI | C9: =COUNTIFS(Sales_Data!O2:O501,">=15",Sales_Data!R2:R501,"UPI") -> 45
B10: Number of customers who have given a Rating of 5 and whose Order Status is Completed | C10: =COUNTIFS(Sales_Data!Q2:Q501,5,Sales_Data!V2:V501,"Completed") -> 27
B11: Average Sales Amount for orders placed in the West region where the Quantity is greater than 5 | C11: =AVERAGEIFS(Sales_Data!P2:P501,Sales_Data!J2:J501,"WEST",Sales_Data!M2:M501,">5") -> 82824.451

Sheet Sales Statistics Report(Q6)
A2: Average Sales Amount | B2: =AVERAGE(Sales_Data!P2:P501) -> 69531.875
A3: Median Sales Amount | B3: =MEDIAN(Sales_Data!P2:P501) -> 10475
A4: Highest Sales Amount | B4: =MAX(Sales_Data!P2:P501) -> 1045000
A5: Lowest Sales Amount | B5: =MIN(Sales_Data!P2:P501) -> 19
A6: Standard Deviation | B6: =_xlfn.STDEV.S(Sales_Data!P2:P501) -> 167151.45
A7: 90th Percentile | B7: =_xlfn.PERCENTILE.INC(Sales_Data!P2:P501,90%) -> 163880 | C7: The 90th percentile shows the sales amount below which around 90% of the sales transactions fall. It helps us understand what sales value separates the top 10% of the highest sales from the rest.

Sheet Product Performance (Q7)
B2: Summary Table
B4: Total Revenue | D4: =SUMPRODUCT(Sales_Data!M2:M501,Sales_Data!N2:N501) -> 36604875 | E4: Calculated total Revenue | G4: =SUMPRODUCT(Sales_Data!M2:M501,Sales_Data!N2:N501) -> 36604875
B5: Weighted Average Unit Price | D5: =SUMPRODUCT(Sales_Data!N2:N501,Sales_Data!M2:M501)/SUM(Sales_Data!M2:M501) -> 6989.6649 | E5: Total Revenue in Sales column | G5: =SUM(Sales_Data!P2:P501) -> 34765938
C6: Difference b/w Calculated sales & Total revenue in sales column | E6: =G4-G5 -> 1838937.5
C8: Total Discounted Amount | E8: =SUMPRODUCT(Sales_Data!M2:M501,Sales_Data!N2:N501,Sales_Data!O2:O501)/100 -> 2918151.5

Sheet Financial Analysis Report (Q8)
B2: Summary Table
B3: Future Value of the Invetment | C3: =ROUND(FV(10%/12,5*12,-50000),2) -> 3871853.6
B4: Monthly Investment Required | C4: =PMT(0%,5*12,-5000000) -> 83333.333
B5: EMI per Month | C5: =ROUND(PMT(9%/12,5*12,-1000000),0) -> 20758

Sheet Cleaned_Data (Q9)
A1: Order_ID | B1: Customer_ID | C1: Product_ID | D1: Order_Date | E1: Delivery_Date | F1: Customer_Name | G1: Gender | H1: DOB | I1: City | J1: Region | K1: Category | L1: Product_Name | M1: Quantity | N1: Unit_Price | O1: Discount_% | P1: Sales | Q1: Rating | R1: Payment_Mode | S1: Salesperson | T1: Email | U1: Phone | V1: Order_Status
A2: ORD10001 | B2: C008 | C2: P202 | D2: 18/09/2025 | E2: 22/09/2025 | F2: =TRIM(PROPER(Sales_Data!F2)) -> Kavya Nair | G2: Female | H2: 01/08/1976 | I2: Hyderabad | J2: =PROPER(Sales_Data!J2) -> South | K2: =PROPER(Sales_Data!K2) -> Home Appliances | L2: Iron | M2: 4 | N2: 2200 | O2: 10 | P2: 7920 | Q2: 4 | R2: Cash | S2: Ritika | T2: KAvya.nair@company.com | U2: 9431429797 | V2: Completed | X2: =PROPER(Sales_Data!X2)
A3: ORD10002 | B3: C008 | C3: P104 | D3: 27/04/2025 | E3: 04/05/2025 | F3: =TRIM(PROPER(Sales_Data!F3)) -> Kavya Nair | G3: Female | H3: 16/10/2000 | I3: Delhi | J3: =PROPER(Sales_Data!J3) -> North | K3: =PROPER(Sales_Data!K3) -> Electronics | L3: Monitor | M3: 17 | N3: 12000 | O3: 10 | P3: 183600 | Q3: 1 | R3: NetBanking | S3: Rahul | T3: kavya.nair@company.com | U3: 9129865339 | V3: Completed | X3: =PROPER(Sales_Data!X3)
A4: ORD10003 | B4: C010 | C4: P101 | D4: 45725 | E4: 14/09/2025 | F4: =TRIM(PROPER(Sales_Data!F4)) -> Pooja Shah | G4: Female | H4: 16/09/1994 | I4: Bengaluru | J4: =PROPER(Sales_Data!J4) -> South | K4: =PROPER(Sales_Data!K4) -> Electronics | L4: Laptop | M4: 5 | N4: 55000 | O4: 5 | P4: 261250 | Q4: 3 | R4: NetBanking | S4: Aisha | T4: pooja.shah@company.com | U4: 9380975626 | V4: Pending | X4: =PROPER(Sales_Data!X4)
A5: ORD10002 | B5: C008 | C5: P202 | D5: 21/03/2026 | E5: 02/04/2026 | F5: =TRIM(PROPER(Sales_Data!F5)) -> Kavya Nair | G5: Female | H5: 07/03/2004 | I5: Bengaluru | J5: =PROPER(Sales_Data!J5) -> South | K5: =PROPER(Sales_Data!K5) -> Home Appliances | L5: Iron | M5: 5 | N5: 2200 | O5: 5 | P5: 10450 | Q5: 5 | R5: NetBanking | S5: Aisha | T5: kavya.nair@company.com | U5: 9600261125 | V5: Cancelled | X5: =PROPER(Sales_Data!X5)
A6: ORD10005 | B6: C009 | C6: P103 | D6: 27/09/2025 | E6: 07/10/2025 | F6: =TRIM(PROPER(Sales_Data!F6)) -> Mohit Verma | G6: Male | H6: 13/04/1976 | I6: Delhi | J6: =PROPER(Sales_Data!J6) -> North | K6: =PROPER(Sales_Data!K6) -> Electronics | L6: Keyboard | M6: 8 | N6: 1200 | O6: 5 | P6: 9120 | Q6: 2 | R6: Card | S6: Aisha | T6: mohit.verma@company.com | U6: 9724635978 | V6: Pending | X6: =PROPER(Sales_Data!X6)
A7: ORD10006 | B7: C007 | C7: P202 | D7: 46113 | E7: 12/01/2026 | F7: =TRIM(PROPER(Sales_Data!F7)) -> Arjun Rao | G7: Male | H7: 07/02/1988 | I7: Hyderabad | J7: =PROPER(Sales_Data!J7) -> South | K7: =PROPER(Sales_Data!K7) -> Home Appliances | L7: Iron | M7: 4 | N7: 2200 | O7: 0 | P7: 8800 | Q7: 1 | R7: UPI | S7: Ritika | T7: arjun.rao@company.com | U7: 9780584905 | V7: Completed | X7: =PROPER(Sales_Data!X7)
A8: ORD10007 | B8: C008 | C8: P201 | D8: 31/02/2025 | E8: 25/02/2026 | F8: =TRIM(PROPER(Sales_Data!F8)) -> Kavya Nair | G8: Female | H8: 20/03/2003 | I8: Hyderabad | J8: =PROPER(Sales_Data!J8) -> South | K8: =PROPER(Sales_Data!K8) -> Home Appliances | L8: Mixer | M8: 2 | N8: 3500 | O8: 5 | P8: 6650 | Q8: 1 | R8: UPI | S8: Ritika | T8: kavya.nair@company.com | U8: 9958252176 | V8: Completed | X8: =PROPER(Sales_Data!X8)
A9: ORD10008 | B9: C002 | C9: P104 | D9: 13/04/2025 | E9: 19/04/2025 | F9: =TRIM(PROPER(Sales_Data!F9)) -> Priya Patel | G9: Female | H9: 07/03/1995 | I9: Mumbai | J9: =PROPER(Sales_Data!J9) -> West | K9: =PROPER(Sales_Data!K9) -> Electronics | L9: Monitor | M9: 14 | N9: 12000 | O9: 15 | P9: 142800 | Q9: 4 | R9: NetBanking | S9: Ritika | T9: priYa.patel@company.com | U9: 9705521654 | V9: Completed | X9: =PROPER(Sales_Data!X9)
A10: ORD10009 | B10: C008 | C10: P104 | D10: 31/01/2026 | E10: 02/02/2026 | F10: =TRIM(PROPER(Sales_Data!F10)) -> Kavya Nair | G10: Female | H10: 06/04/1997 | I10: Pune | J10: =PROPER(Sales_Data!J10) -> West | K10: =PROPER(Sales_Data!K10) -> Electronics | L10: Monitor | M10: 4 | N10: 12000 | O10: 15 | P10: 40800 | Q10: 4 | R10: UPI | S10: Neha | T10: kavya.nair@company.com | U10: 9588041011 | V10: Completed | X10: =PROPER(Sales_Data!X10)
A11: ORD10010 | B11: C002 | C11: P301 | D11: 25/03/2025 | E11: 27/03/2025 | F11: =TRIM(PROPER(Sales_Data!F11)) -> Priya Patel | G11: Female | H11: 07/01/1990 | I11: Mumbai | J11: =PROPER(Sales_Data!J11) -> West | K11: =PROPER(Sales_Data!K11) -> Stationery | L11: Notebook | M11: 6 | N11: 60 | O11: 0 | P11: 360 | Q11: 4 | R11: Card | S11: Neha | T11: PRiya.patel@company.com | U11: 9340540608 | V11: Completed | X11: =PROPER(Sales_Data!X11)
A12: ORD10011 | B12: C003 | C12: P202 | D12: 19/09/2025 | E12: 23/09/2025 | F12: =TRIM(PROPER(Sales_Data!F12)) -> Rohit Singh | G12: Male | H12: 10/05/1982 | I12: Delhi | J12: =PROPER(Sales_Data!J12) -> North | K12: =PROPER(Sales_Data!K12) -> Home Appliances | L12: Iron | M12: -3 | N12: 2200 | O12: 0 | P12: 35200 | Q12: 2 | R12: Card | S12: Rahul | T12: rohit.singh@company.com | U12: 9521710321 | V12: Pending | X12: =PROPER(Sales_Data!X12)
A13: ORD10012 | B13: C008 | C13: P201 | D13: 45872 | E13: 15/03/2025 | F13: =TRIM(PROPER(Sales_Data!F13)) -> Kavya Nair | G13: Female | H13: 23/01/1982 | I13: Ahmedabad | J13: =PROPER(Sales_Data!J13) -> West | K13: =PROPER(Sales_Data!K13) -> Home Appliances | L13: Mixer | M13: 10 | N13: 3500 | O13: 5 | P13: 33250 | Q13: 5 | R13: Card | S13: Aisha | T13: kavya.nair@company.com | U13: 9123535241 | V13: Cancelled | X13: =PROPER(Sales_Data!X13)
A14: ORD10013 | B14: C002 | C14: P202 | D14: 45931 | E14: 15/01/2025 | F14: =TRIM(PROPER(Sales_Data!F14)) -> Priya Patel | G14: Female | H14: 06/07/1992 | I14: Pune | J14: =PROPER(Sales_Data!J14) -> West | K14: =PROPER(Sales_Data!K14) -> Home Appliances | L14: Iron | M14: 15 | N14: 2200 | O14: 10 | P14: 29700 | Q14: 1 | R14: UPI | S14: Neha | T14: priya.patel@company.com | U14: 9367316892 | V14: Pending | X14: =PROPER(Sales_Data!X14)
A15: ORD10014 | B15: C003 | C15: P202 | D15: 45903 | E15: 13/03/2025 | F15: =TRIM(PROPER(Sales_Data!F15)) -> Rohit Singh | G15: Male | H15: 19/03/2002 | I15: Mumbai | J15: =PROPER(Sales_Data!J15) -> West | K15: =PROPER(Sales_Data!K15) -> Home Appliances | L15: Iron | M15: 17 | N15: 2200 | O15: 5 | P15: 35530 | Q15: 1 | R15: Cash | S15: Karan | T15: rOhit.singh@company.com | U15: 9778489803 | V15: Completed | X15: =PROPER(Sales_Data!X15)
A16: ORD10015 | B16: C008 | C16: P201 | D16: 26/07/2025 | E16: 07/08/2025 | F16: =TRIM(PROPER(Sales_Data!F16)) -> Kavya Nair | G16: Female | H16: 17/01/2001 | I16: Mumbai | J16: =PROPER(Sales_Data!J16) -> West | K16: =PROPER(Sales_Data!K16) -> Home Appliances | L16: Mixer | M16: 15 | N16: 3500 | O16: 15 | P16: 44625 | Q16: 2 | R16: Cash | S16: Neha | T16: kavya.nair@company.com | U16: 9582960180 | V16: Cancelled | X16: =PROPER(Sales_Data!X16)
A17: ORD10016 | B17: C010 | C17: P103 | D17: 46238 | E17: 11/04/2026 | F17: =TRIM(PROPER(Sales_Data!F17)) -> Pooja Shah | G17: Female | H17: 11/04/2002 | I17: Hyderabad | J17: =PROPER(Sales_Data!J17) -> South | K17: =PROPER(Sales_Data!K17) -> Electronics | L17: Keyboard | M17: 3 | N17: 1200 | O17: 5 | P17: 3420 | Q17: 5 | R17: UPI | S17: Ritika | T17: pooja.shahcompany.com | U17: 9611394005 | V17: Completed | X17: =PROPER(Sales_Data!X17)
A18: ORD10017 | B18: C004 | C18: P203 | D18: 22/02/2026 | E18: 03/03/2026 | F18: =TRIM(PROPER(Sales_Data!F18)) -> Amit Sharma | G18: Female | H18: 16/01/2002 | I18: Pune | J18: =PROPER(Sales_Data!J18) -> West | K18: =PROPER(Sales_Data!K18) -> Home Appliances | L18: Microwave | M18: 13 | N18: 8500 | O18: 20 | P18: 88400 | Q18: 4 | R18: Card | S18: Rahul | T18: anita.gupta@company.com | U18: 9692599404 | V18: Pending | X18: =PROPER(Sales_Data!X18)
A19: ORD10018 | B19: C007 | C19: P203 | D19: 28/02/2026 | E19: 05/03/2026 | F19: =TRIM(PROPER(Sales_Data!F19)) -> Arjun Rao | G19: Male | H19: 09/10/1989 | I19: Ahmedabad | J19: =PROPER(Sales_Data!J19) -> West | K19: =PROPER(Sales_Data!K19) -> Home Appliances | L19: Microwave | M19: 4 | N19: 8500 | O19: 20 | P19: 27200 | Q19: 5 | R19: Card | S19: Aisha | T19: arjun.rao@company.com | U19: 9426119622 | V19: Pending | X19: =PROPER(Sales_Data!X19)
A20: ORD10019 | B20: C007 | C20: P102 | D20: 45669 | E20: 04/12/2025 | F20: =TRIM(PROPER(Sales_Data!F20)) -> Arjun Rao | G20: Male | H20: 28/10/1991 | I20: Mumbai | J20: =PROPER(Sales_Data!J20) -> West | K20: =PROPER(Sales_Data!K20) -> Electronics | L20: Mouse | M20: 9 | N20: 700 | O20: 5 | P20: 5985 | Q20: 3 | R20: UPI | S20: Ritika | T20: arjun.Rao@company.com | U20: 9184436009 | V20: Pending | X20: =PROPER(Sales_Data!X20)
A21: ORD10020 | B21: C008 | C21: P101 | D21: 25/06/2025 | E21: 03/07/2025 | F21: =TRIM(PROPER(Sales_Data!F21)) -> Kavya Nair | G21: Female | H21: 01/03/1990 | I21: Ahmedabad | J21: =PROPER(Sales_Data!J21) -> West | K21: =PROPER(Sales_Data!K21) -> Electronics | L21: Laptop | M21: 8 | N21: 55000 | O21: 20 | P21: 352000 | Q21: 1 | R21: Cash | S21: Karan | T21: kavya.nair@company.com | U21: 9263774934 | V21: Completed | X21: =PROPER(Sales_Data!X21)
A22: ORD10021 | B22: C003 | C22: P102 | D22: 26/04/2025 | E22: 05/05/2025 | F22: =TRIM(PROPER(Sales_Data!F22)) -> Rohit Singh | G22: Male | H22: 18/07/2002 | I22: Delhi | J22: =PROPER(Sales_Data!J22) -> North | K22: =PROPER(Sales_Data!K22) -> Electronics | L22: Mouse | M22: 10 | N22: 700 | O22: 20 | P22: 5600 | Q22: 4 | R22: Card | S22: Aisha | T22: rohit.singh@company.com | U22: 9473159572 | V22: Cancelled | X22: =PROPER(Sales_Data!X22)
A23: ORD10022 | B23: C008 | C23: P201 | D23: 45717 | E23: 08/01/2025 | F23: =TRIM(PROPER(Sales_Data!F23)) -> Kavya Nair | G23: Female | H23: 15/12/2004 | I23: Bengaluru | J23: =PROPER(Sales_Data!J23) -> South | K23: =PROPER(Sales_Data!K23) -> Home Appliances | L23: Mixer | M23: 1 | N23: 3500 | O23: 5 | P23: 3325 | Q23: 3 | R23: UPI | S23: Neha | T23: kavya.nair@company.com | U23: 9660493688 | V23: Cancelled | X23: =PROPER(Sales_Data!X23)
A24: ORD10023 | B24: C002 | C24: P102 | D24: 19/04/2025 | E24: 30/04/2025 | F24: =TRIM(PROPER(Sales_Data!F24)) -> Priya Patel | G24: Female | H24: 04/07/1984 | I24: Jaipur | J24: =PROPER(Sales_Data!J24) -> North | K24: =PROPER(Sales_Data!K24) -> Electronics | L24: Mouse | M24: 19 | N24: 700 | O24: 15 | P24: 11305 | Q24: 3 | R24: NetBanking | S24: Karan | T24: priya.patel@company.com | U24: 9513325819 | V24: Pending | X24: =PROPER(Sales_Data!X24)
A25: ORD10024 | B25: C009 | C25: P101 | D25: 22/12/2025 | E25: 01/01/2026 | F25: =TRIM(PROPER(Sales_Data!F25)) -> Mohit Verma | G25: Male | H25: 25/02/1978 | I25: Bengaluru | J25: =PROPER(Sales_Data!J25) -> South | K25: =PROPER(Sales_Data!K25) -> Electronics | L25: Laptop | M25: 12 | N25: 55000 | O25: 0 | P25: 660000 | Q25: 1 | R25: Card | S25: Rahul | T25: mohit.verma@company.com | U25: 9641063242 | V25: Pending | X25: =PROPER(Sales_Data!X25)
A26: ORD10025 | B26: C005 | C26: P302 | D26: 46269 | E26: 20/04/2026 | F26: =TRIM(PROPER(Sales_Data!F26)) -> Vikas Mehta | G26: Male | H26: 03/08/1991 | I26: Mumbai | J26: =PROPER(Sales_Data!J26) -> West | K26: =PROPER(Sales_Data!K26) -> Stationery | L26: Pen | M26: 1 | N26: 20 | O26: 5 | P26: 19 | Q26: 5 | R26: Card | S26: Ritika | T26: vikas.mehta@company.com | U26: 9277372518 | V26: Cancelled | X26: =PROPER(Sales_Data!X26)
A27: ORD10026 | B27: C007 | C27: P302 | D27: 24/06/2025 | E27: 02/07/2025 | F27: =TRIM(PROPER(Sales_Data!F27)) -> Arjun Rao | G27: Male | H27: 11/12/1977 | I27: Mumbai | J27: =PROPER(Sales_Data!J27) -> West | K27: =PROPER(Sales_Data!K27) -> Stationery | L27: Pen | M27: 2 | N27: 20 | O27: 15 | P27: 34 | Q27: 1 | R27: UPI | S27: Ritika | T27: arjun.rao@company.com | U27: 9193154372 | V27: Pending | X27: =PROPER(Sales_Data!X27)
A28: ORD10027 | B28: C009 | C28: P201 | D28: 22/05/2025 | E28: 25/05/2025 | F28: =TRIM(PROPER(Sales_Data!F28)) -> Mohit Verma | G28: Male | H28: 08/02/1992 | I28: Ahmedabad | J28: =PROPER(Sales_Data!J28) -> West | K28: =PROPER(Sales_Data!K28) -> Home Appliances | L28: Mixer | M28: 12 | N28: 3500 | O28: 15 | P28: 35700 | Q28: 4 | R28: Cash | S28: Rahul | T28: mohit.verma@company.com | U28: 9400073244 | V28: Cancelled | X28: =PROPER(Sales_Data!X28)
A29: ORD10028 | B29: C008 | C29: P103 | D29: 13/03/2026 | E29: 20/03/2026 | F29: =TRIM(PROPER(Sales_Data!F29)) -> Kavya Nair | G29: Female | H29: 05/06/2004 | I29: Ahmedabad | J29: =PROPER(Sales_Data!J29) -> West | K29: =PROPER(Sales_Data!K29) -> Electronics | L29: Keyboard | M29: 11 | N29: 1200 | O29: 0 | P29: 13200 | Q29: 2 | R29: UPI | S29: Karan | T29: kavya.nair@company.com | U29: 9771556720 | V29: Completed | X29: =PROPER(Sales_Data!X29)
A30: ORD10029 | B30: C003 | C30: P203 | D30: 45878 | E30: 20/09/2025 | F30: =TRIM(PROPER(Sales_Data!F30)) -> Rohit Singh | G30: Male | H30: 11/08/2001 | I30: Pune | J30: =PROPER(Sales_Data!J30) -> West | K30: =PROPER(Sales_Data!K30) -> Home Appliances | L30: Microwave | M30: 6 | N30: 8500 | O30: 65 | P30: 51000 | Q30: 1 | R30: Card | S30: Aisha | T30: rohit.singh@company.com | U30: 9127480734 | V30: Completed | X30: =PROPER(Sales_Data!X30)
A31: ORD10030 | B31: C006 | C31: P301 | D31: 46327 | E31: 16/01/2026 | F31: =TRIM(PROPER(Sales_Data!F31)) -> Sneha Joshi | G31: Female | H31: 04/04/1981 | I31: Pune | J31: =PROPER(Sales_Data!J31) -> West | K31: =PROPER(Sales_Data!K31) -> Stationery | L31: Notebook | M31: 2 | N31: 60 | O31: 5 | P31: 114 | Q31: 3 | R31: Cash | S31: Karan | T31: sneha.joshi@company.com | U31: 9512997042 | V31: Cancelled | X31: =PROPER(Sales_Data!X31)
A32: ORD10031 | B32: C008 | C32: P303 | D32: 16/06/2025 | E32: 26/06/2025 | F32: =TRIM(PROPER(Sales_Data!F32)) -> Kavya Nair | G32: Female | H32: 02/07/1996 | I32: Bengaluru | J32: =PROPER(Sales_Data!J32) -> South | K32: =PROPER(Sales_Data!K32) -> Stationery | L32: Marker | M32: 19 | N32: 45 | O32: 20 | P32: 684 | Q32: 4 | R32: NetBanking | S32: Aisha | T32: kavya.nair@company.com | U32: 9372748661 | V32: Cancelled | X32: =PROPER(Sales_Data!X32)
A33: ORD10032 | B33: C002 | C33: P104 | D33: 45664 | E33: 13/07/2025 | F33: =TRIM(PROPER(Sales_Data!F33)) -> Priya Patel | G33: Female | H33: 15/11/1976 | I33: Ahmedabad | J33: =PROPER(Sales_Data!J33) -> West | K33: =PROPER(Sales_Data!K33) -> Electronics | L33: Monitor | M33: 11 | N33: 12000 | O33: 0 | P33: 132000 | Q33: 3 | R33: UPI | S33: Ritika | T33: priya.patel@company.com | U33: 9570437805 | V33: Pending | X33: =PROPER(Sales_Data!X33)
A34: ORD10033 | B34: C006 | C34: P202 | D34: 45841 | E34: 15/03/2025 | F34: =TRIM(PROPER(Sales_Data!F34)) -> Sneha Joshi | G34: Female | H34: 28/10/1988 | I34: Bengaluru | J34: =PROPER(Sales_Data!J34) -> South | K34: =PROPER(Sales_Data!K34) -> Home Appliances | L34: Iron | M34: 20 | N34: 2200 | O34: 5 | P34: 41800 | Q34: 1 | R34: Cash | S34: Rahul | T34: sneha.joshi@company.com | U34: 9310669113 | V34: Pending | X34: =PROPER(Sales_Data!X34)
A35: ORD10034 | B35: C007 | C35: P302 | D35: 24/06/2025 | E35: 04/07/2025 | F35: =TRIM(PROPER(Sales_Data!F35)) -> Arjun Rao | G35: Male | H35: 23/06/2004 | I35: Ahmedabad | J35: =PROPER(Sales_Data!J35) -> West | K35: =PROPER(Sales_Data!K35) -> Stationery | L35: Pen | M35: 3 | N35: 20 | O35: 0 | P35: 60 | Q35: 2 | R35: Card | S35: Ritika | T35: wrongmail | U35: 9437132894 | V35: Cancelled | X35: =PROPER(Sales_Data!X35)
A36: ORD10035 | B36: C003 | C36: P303 | D36: 45910 | E36: 19/10/2025 | F36: =TRIM(PROPER(Sales_Data!F36)) -> Rohit Singh | G36: Male | H36: 22/04/1996 | I36: Pune | J36: =PROPER(Sales_Data!J36) -> West | K36: =PROPER(Sales_Data!K36) -> Stationery | L36: Marker | M36: 18 | N36: 45 | O36: 20 | P36: 648 | Q36: 4 | R36: NetBanking | S36: Ritika | T36: rohit.singh@company.com | U36: 9762437243 | V36: Cancelled | X36: =PROPER(Sales_Data!X36)
A37: ORD10036 | B37: C003 | C37: P103 | D37: 19/11/2025 | E37: 26/11/2025 | F37: =TRIM(PROPER(Sales_Data!F37)) -> Rohit Singh | G37: Male | H37: 07/07/1979 | I37: Bengaluru | J37: =PROPER(Sales_Data!J37) -> South | K37: =PROPER(Sales_Data!K37) -> Electronics | L37: Keyboard | M37: 4 | N37: 1200 | O37: 20 | P37: 3840 | Q37: 3 | R37: NetBanking | S37: Aisha | T37: rohit.singh@company.com | U37: 9149046970 | V37: Completed | X37: =PROPER(Sales_Data!X37)
A38: ORD10037 | B38: C009 | C38: P101 | D38: 45788 | E38: 14/11/2025 | F38: =TRIM(PROPER(Sales_Data!F38)) -> Mohit Verma | G38: Male | H38: 27/09/1980 | I38: Kolkata | J38: =PROPER(Sales_Data!J38) -> East | K38: =PROPER(Sales_Data!K38) -> Electronics | L38: Laptop | M38: 10 | N38: 55000 | O38: 0 | P38: 550000 | Q38: 1 | R38: UPI | S38: Rahul | T38: mohit.verma@company.com | U38: 9869182901 | V38: Cancelled | X38: =PROPER(Sales_Data!X38)
A39: ORD10038 | B39: C006 | C39: P201 | D39: 46237 | E39: 20/03/2026 | F39: =TRIM(PROPER(Sales_Data!F39)) -> Sneha Joshi | G39: Female | H39: 21/06/1980 | I39: Delhi | J39: =PROPER(Sales_Data!J39) -> North | K39: =PROPER(Sales_Data!K39) -> Home Appliances | L39: Mixer | M39: 20 | N39: 3500 | O39: 10 | P39: 63000 | Q39: 3 | R39: Card | S39: Rahul | T39: sneha.joshi@company.com | U39: 9283578533 | V39: Cancelled | X39: =PROPER(Sales_Data!X39)
A40: ORD10039 | B40: C008 | C40: P302 | D40: 13/02/2025 | E40: 19/02/2025 | F40: =TRIM(PROPER(Sales_Data!F40)) -> Kavya Nair | G40: Female | H40: 17/06/1979 | I40: Pune | J40: =PROPER(Sales_Data!J40) -> West | K40: =PROPER(Sales_Data!K40) -> Stationery | L40: Pen | M40: 5 | N40: 1200 | O40: 0 | P40: 100 | Q40: 1 | R40: Cash | S40: Rahul | T40: kavya.nair@company.com | U40: 9963005771 | V40: Cancelled | X40: =PROPER(Sales_Data!X40)
A41: ORD10040 | B41: C010 | C41: P203 | D41: 45787 | E41: 15/10/2025 | F41: =TRIM(PROPER(Sales_Data!F41)) -> Pooja Shah | G41: Female | H41: 18/06/1992 | I41: Mumbai | J41: =PROPER(Sales_Data!J41) -> West | K41: =PROPER(Sales_Data!K41) -> Home Appliances | L41: Microwave | M41: 20 | N41: 8500 | O41: 0 | P41: 170000 | Q41: 1 | R41: UPI | S41: Neha | T41: pooja.shah@company.com | U41: 9484632635 | V41: Cancelled | X41: =PROPER(Sales_Data!X41)
A42: ORD10041 | B42: C007 | C42: P301 | D42: 46297 | E42: 12/02/2026 | F42: =TRIM(PROPER(Sales_Data!F42)) -> Arjun Rao | G42: Male | H42: 06/06/1994 | I42: Bengaluru | J42: =PROPER(Sales_Data!J42) -> South | K42: =PROPER(Sales_Data!K42) -> Stationery | L42: Notebook | M42: 8 | N42: 60 | O42: 15 | P42: 408 | Q42: 5 | R42: UPI | S42: Rahul | T42: arjun.rao@company.com | U42: 9276319484 | V42: Pending | X42: =PROPER(Sales_Data!X42)
A43: ORD10042 | B43: C010 | C43: P201 | D43: 45753 | E43: 16/06/2025 | F43: =TRIM(PROPER(Sales_Data!F43)) -> Pooja Shah | G43: Female | H43: 22/09/1988 | I43: Pune | J43: =PROPER(Sales_Data!J43) -> West | K43: =PROPER(Sales_Data!K43) -> Home Appliances | L43: Mixer | M43: 8 | N43: 3500 | O43: 5 | P43: 26600 | Q43: 1 | R43: Card | S43: Neha | T43: pooja.shah@company.com | U43: 9619034852 | V43: Pending | X43: =PROPER(Sales_Data!X43)
A44: ORD10043 | B44: C009 | C44: P203 | D44: 46236 | E44: 14/02/2026 | F44: =TRIM(PROPER(Sales_Data!F44)) -> Mohit Verma | G44: Male | H44: 14/07/2001 | I44: Jaipur | J44: =PROPER(Sales_Data!J44) -> North | K44: =PROPER(Sales_Data!K44) -> Home Appliances | L44: Microwave | M44: 1 | N44: 8500 | O44: 0 | P44: 8500 | Q44: 2 | R44: Card | S44: Neha | T44: mohit.verma@company.com | U44: 9636416962 | V44: Pending | X44: =PROPER(Sales_Data!X44)
A45: ORD10044 | B45: C001 | C45: P303 | D45: 30/03/2025 | E45: 31/03/2025 | F45: =TRIM(PROPER(Sales_Data!F45)) -> Amit Sharma | G45: Male | H45: 09/08/1991 | I45: Pune | J45: =PROPER(Sales_Data!J45) -> West | K45: =PROPER(Sales_Data!K45) -> Stationery | L45: Marker | M45: 8 | N45: 45 | O45: 15 | P45: 306 | Q45: 2 | R45: Card | S45: Aisha | T45: amit.sharma@company.com | U45: 9357133880 | V45: Completed | X45: =PROPER(Sales_Data!X45)
A46: ORD10045 | B46: C006 | C46: P202 | D46: 25/04/2025 | E46: 28/04/2025 | F46: =TRIM(PROPER(Sales_Data!F46)) -> Sneha Joshi | G46: Female | H46: 21/10/1988 | I46: Pune | J46: =PROPER(Sales_Data!J46) -> West | K46: =PROPER(Sales_Data!K46) -> Home Appliances | L46: Iron | M46: 16 | N46: 2200 | O46: 5 | P46: 33440 | Q46: 5 | R46: Card | S46: Aisha | T46: sneha.joshi@company.com | U46: 9575210324 | V46: Cancelled | X46: =PROPER(Sales_Data!X46)
A47: ORD10046 | B47: C009 | C47: P201 | D47: 13/10/2025 | E47: 23/10/2025 | F47: =TRIM(PROPER(Sales_Data!F47)) -> Mohit Verma | G47: Male | H47: 19/11/2002 | I47: Bengaluru | J47: =PROPER(Sales_Data!J47) -> South | K47: =PROPER(Sales_Data!K47) -> Home Appliances | L47: Mixer | M47: 19 | N47: 3500 | O47: 20 | P47: 53200 | Q47: 3 | R47: Cash | S47: Karan | T47: mohit.verma@company.com | U47: 9276080204 | V47: Cancelled | X47: =PROPER(Sales_Data!X47)
A48: ORD10047 | B48: C006 | C48: P102 | D48: 45971 | E48: 14/10/2025 | F48: =TRIM(PROPER(Sales_Data!F48)) -> Sneha Joshi | G48: Female | H48: 06/07/2000 | I48: Pune | J48: =PROPER(Sales_Data!J48) -> West | K48: =PROPER(Sales_Data!K48) -> Electronics | L48: Mouse | M48: 15 | N48: 700 | O48: 15 | P48: 8925 | Q48: 4 | R48: UPI | S48: Neha | T48: sneha.joshicompany.com | U48: 9856624471 | V48: Completed | X48: =PROPER(Sales_Data!X48)
A49: ORD10048 | B49: C006 | C49: P102 | D49: 27/11/2025 | E49: 03/12/2025 | F49: =TRIM(PROPER(Sales_Data!F49)) -> Sneha Joshi | G49: Female | H49: 26/11/1998 | I49: Jaipur | J49: =PROPER(Sales_Data!J49) -> North | K49: =PROPER(Sales_Data!K49) -> Electronics | L49: Mouse | M49: 19 | N49: 700 | O49: 20 | P49: 10640 | Q49: 1 | R49: Cash | S49: Neha | T49: sneha.joshi@company.com | U49: 9238141322 | V49: Completed | X49: =PROPER(Sales_Data!X49)
A50: ORD10049 | B50: C009 | C50: P104 | D50: 19/04/2026 | E50: Pending | F50: =TRIM(PROPER(Sales_Data!F50)) -> Mohit Verma | G50: Male | H50: 03/06/1996 | I50: Delhi | J50: =PROPER(Sales_Data!J50) -> North | K50: =PROPER(Sales_Data!K50) -> Electronics | L50: Monitor | M50: 19 | N50: 12000 | O50: 0 | P50: 228000 | Q50: 1 | R50: NetBanking | S50: Aisha | T50: mohit.verma@company.com | U50: 9890380030 | V50: Completed | X50: =PROPER(Sales_Data!X50)
A51: ORD10050 | B51: C004 | C51: P103 | D51: 19/04/2026 | E51: 21/04/2026 | F51: =TRIM(PROPER(Sales_Data!F51)) -> Anita Gupta | G51: Female | H51: 15/03/1987 | I51: Pune | J51: =PROPER(Sales_Data!J51) -> West | K51: =PROPER(Sales_Data!K51) -> Electronics | L51: Keyboard | M51: 6 | N51: 1200 | O51: 5 | P51: 6840 | Q51: 2 | R51: Cash | S51: Ritika | T51: anita.gupta@company.com | U51: 9495893170 | V51: Pending | X51: =PROPER(Sales_Data!X51)
A52: ORD10051 | B52: C010 | C52: P202 | D52: 28/03/2025 | E52: 07/04/2025 | F52: =TRIM(PROPER(Sales_Data!F52)) -> Pooja Shah | G52: Female | H52: 20/02/1979 | I52: Bengaluru | J52: =PROPER(Sales_Data!J52) -> South | K52: =PROPER(Sales_Data!K52) -> Home Appliances | L52: Iron | M52: 7 | N52: 2200 | O52: 15 | P52: 13090 | Q52: 1 | R52: UPI | S52: Aisha | T52: pooja.shah@company.com | U52: 9485166307 | V52: Completed | X52: =PROPER(Sales_Data!X52)
A53: ORD10052 | B53: C002 | C53: P301 | D53: 25/08/2025 | E53: 28/08/2025 | F53: =TRIM(PROPER(Sales_Data!F53)) -> Priya Patel | G53: Female | H53: 09/08/2000 | I53: Jaipur | J53: =PROPER(Sales_Data!J53) -> North | K53: =PROPER(Sales_Data!K53) -> Stationery | L53: Notebook | M53: 8 | N53: 60 | O53: 10 | P53: 432 | Q53: 5 | R53: Card | S53: Aisha | T53: priya.patel@company.com | U53: 9924709648 | V53: Cancelled | X53: =PROPER(Sales_Data!X53)
A54: ORD10053 | B54: C005 | C54: P101 | D54: 19/08/2025 | E54: 23/08/2025 | F54: =TRIM(PROPER(Sales_Data!F54)) -> Vikas Mehta | G54: Male | H54: 17/01/1976 | I54: Kolkata | J54: =PROPER(Sales_Data!J54) -> East | K54: =PROPER(Sales_Data!K54) -> Electronics | L54: Laptop | M54: 12 | N54: 55000 | O54: 5 | P54: 627000 | Q54: 2 | R54: UPI | S54: Rahul | T54: vikas.mehta@company.com | U54: 9350554626 | V54: Pending | X54: =PROPER(Sales_Data!X54)
A55: ORD10054 | B55: C008 | C55: P102 | D55: 27/07/2025 | E55: 05/08/2025 | F55: =TRIM(PROPER(Sales_Data!F55)) -> Kavya Nair | G55: Female | H55: 04/04/1975 | I55: Jaipur | J55: =PROPER(Sales_Data!J55) -> North | K55: =PROPER(Sales_Data!K55) -> Electronics | L55: Mouse | M55: 3 | N55: 700 | O55: 0 | P55: 2100 | Q55: 3 | R55: Card | S55: Karan | T55: kavya.nair@company.com | U55: 9743295580 | V55: Cancelled | X55: =PROPER(Sales_Data!X55)
A56: ORD10055 | B56: C003 | C56: P301 | D56: 21/02/2025 | E56: 26/02/2025 | F56: =TRIM(PROPER(Sales_Data!F56)) -> Rohit Singh | G56: Male | H56: 11/12/1976 | I56: Ahmedabad | J56: =PROPER(Sales_Data!J56) -> West | K56: =PROPER(Sales_Data!K56) -> Stationery | L56: Notebook | M56: 19 | N56: 60 | O56: 15 | P56: 969 | Q56: 4 | R56: Card | S56: Rahul | T56: rohit.singh@company.com | U56: 9822926495 | V56: Cancelled | X56: =PROPER(Sales_Data!X56)
A57: ORD10056 | B57: C001 | C57: P301 | D57: 45938 | E57: 11/08/2025 | F57: =TRIM(PROPER(Sales_Data!F57)) -> Amit Sharma | G57: Male | H57: 03/12/1979 | I57: Jaipur | J57: =PROPER(Sales_Data!J57) -> North | K57: =PROPER(Sales_Data!K57) -> Stationery | L57: Notebook | M57: 9 | N57: 60 | O57: 20 | P57: 432 | Q57: 1 | R57: NetBanking | S57: Neha | T57: amit.sharma@company.com | U57: 9518298190 | V57: Pending | X57: =PROPER(Sales_Data!X57)
A58: ORD10057 | B58: C001 | C58: P102 | D58: 24/03/2026 | E58: 30/03/2026 | F58: =TRIM(PROPER(Sales_Data!F58)) -> Amit Sharma | G58: Male | H58: 27/12/1978 | I58: Bengaluru | J58: =PROPER(Sales_Data!J58) -> South | K58: =PROPER(Sales_Data!K58) -> Electronics | L58: Mouse | M58: 6 | N58: 700 | O58: 0 | P58: 4200 | Q58: 4 | R58: UPI | S58: Rahul | T58: amit.sharmcompany.com | U58: 9366223547 | V58: Cancelled | X58: =PROPER(Sales_Data!X58)
A59: ORD10058 | B59: C003 | C59: P303 | D59: 13/03/2026 | E59: 19/03/2026 | F59: =TRIM(PROPER(Sales_Data!F59)) -> Rohit Singh | G59: Male | H59: 15/04/1975 | I59: Delhi | J59: =PROPER(Sales_Data!J59) -> North | K59: =PROPER(Sales_Data!K59) -> Stationery | L59: Marker | M59: 18 | N59: 45 | O59: 5 | P59: 769.5 | Q59: 1 | R59: Card | S59: Aisha | T59: rohit.singh@company.com | U59: 9701988524 | V59: Pending | X59: =PROPER(Sales_Data!X59)
A60: ORD10059 | B60: C007 | C60: P302 | D60: 15/06/2025 | E60: 26/06/2025 | F60: =TRIM(PROPER(Sales_Data!F60)) -> Arjun Rao | G60: Male | H60: 19/12/1988 | I60: Jaipur | J60: =PROPER(Sales_Data!J60) -> North | K60: =PROPER(Sales_Data!K60) -> Stationery | L60: Pen | M60: 8 | N60: 20 | O60: 5 | P60: 152 | Q60: 1 | R60: Card | S60: Ritika | T60: arjun.rao@company.com | U60: 9836327649 | V60: completed | X60: =PROPER(Sales_Data!X60)
A61: ORD10060 | B61: C005 | C61: P102 | D61: 45780 | E61: 06/03/2025 | F61: =TRIM(PROPER(Sales_Data!F61)) -> Vikas Mehta | G61: Male | H61: 07/03/1979 | I61: Jaipur | J61: =PROPER(Sales_Data!J61) -> North | K61: =PROPER(Sales_Data!K61) -> Electronics | L61: Mouse | M61: 8 | N61: 700 | O61: 10 | P61: 5040 | Q61: 1 | R61: NetBanking | S61: Aisha | T61: Vikas.mehta@company.com | U61: 9261800516 | V61: Cancelled | X61: =PROPER(Sales_Data!X61)
A62: ORD10061 | B62: C008 | C62: P302 | D62: 46269 | E62: 19/04/2026 | F62: =TRIM(PROPER(Sales_Data!F62)) -> Kavya Nair | G62: Female | H62: 17/12/2003 | I62: Delhi | J62: =PROPER(Sales_Data!J62) -> North | K62: =PROPER(Sales_Data!K62) -> Stationery | L62: Pen | M62: 7 | N62: 20 | O62: 15 | P62: 119 | Q62: 5 | R62: Card | S62: Rahul | T62: kavya.nair@company.com | U62: 9950802015 | V62: Completed | X62: =PROPER(Sales_Data!X62)
A63: ORD10062 | B63: C002 | C63: P302 | D63: 16/08/2025 | E63: 25/08/2025 | F63: =TRIM(PROPER(Sales_Data!F63)) -> Priya Patel | G63: Female | H63: 05/04/1984 | I63: Pune | J63: =PROPER(Sales_Data!J63) -> West | K63: =PROPER(Sales_Data!K63) -> Stationery | L63: Pen | M63: 16 | N63: 20 | O63: 0 | P63: 320 | Q63: 5 | R63: NetBanking | S63: Aisha | T63: priya.patel@company.com | U63: 9595183767 | V63: Pending | X63: =PROPER(Sales_Data!X63)
A64: ORD10063 | B64: C010 | C64: P303 | D64: 13/05/2026 | E64: 20/05/2026 | F64: =TRIM(PROPER(Sales_Data!F64)) -> Pooja Shah | G64: Female | H64: 13/04/1996 | I64: Mumbai | J64: =PROPER(Sales_Data!J64) -> West | K64: =PROPER(Sales_Data!K64) -> Stationery | L64: Marker | M64: 15 | N64: 45 | O64: 0 | P64: 675 | Q64: 4 | R64: Cash | S64: Aisha | T64: pooja.shah@company.com | U64: 9560201307 | V64: Cancelled | X64: =PROPER(Sales_Data!X64)
A65: ORD10064 | B65: C006 | C65: P102 | D65: 45660 | E65: 05/03/2025 | F65: =TRIM(PROPER(Sales_Data!F65)) -> Sneha Joshi | G65: Female | H65: 08/09/2003 | I65: Ahmedabad | J65: =PROPER(Sales_Data!J65) -> West | K65: =PROPER(Sales_Data!K65) -> Electronics | L65: Mouse | M65: 15 | N65: 700 | O65: 10 | P65: 9450 | Q65: 3 | R65: NetBanking | S65: Karan | T65: sneha.joshi@company.com | U65: 9826484650 | V65: Completed | X65: =PROPER(Sales_Data!X65)
A66: ORD10065 | B66: C010 | C66: P303 | D66: 45902 | E66: 12/02/2025 | F66: =TRIM(PROPER(Sales_Data!F66)) -> Pooja Shah | G66: Female | H66: 24/09/1992 | I66: Kolkata | J66: =PROPER(Sales_Data!J66) -> East | K66: =PROPER(Sales_Data!K66) -> Stationery | L66: Marker | M66: 3 | N66: 45 | O66: 15 | P66: 114.75 | Q66: 2 | R66: UPI | S66: Neha | T66: pooja.shah@company.com | U66: 9219978007 | V66: Pending | X66: =PROPER(Sales_Data!X66)
A67: ORD10066 | B67: C002 | C67: P202 | D67: 46266 | E67: 10/01/2026 | F67: =TRIM(PROPER(Sales_Data!F67)) -> Priya Patel | G67: Female | H67: 19/09/1986 | I67: Kolkata | J67: =PROPER(Sales_Data!J67) -> East | K67: =PROPER(Sales_Data!K67) -> Home Appliances | L67: Iron | M67: 7 | N67: 2200 | O67: 15 | P67: 13090 | Q67: 5 | R67: UPI | S67: Neha | T67: priya.patel@company.com | U67: 9662063276 | V67: Completed | X67: =PROPER(Sales_Data!X67)
A68: ORD10067 | B68: C008 | C68: P303 | D68: 45666 | E68: 05/09/2025 | F68: =TRIM(PROPER(Sales_Data!F68)) -> Kavya Nair | G68: Female | H68: 28/05/1985 | I68: Delhi | J68: =PROPER(Sales_Data!J68) -> North | K68: =PROPER(Sales_Data!K68) -> Stationery | L68: Marker | M68: 19 | N68: 45 | O68: 10 | P68: 769.5 | Q68: 5 | R68: Card | S68: Neha | T68: kavya.nair@company.com | U68: 9190393639 | V68: Cancelled | X68: =PROPER(Sales_Data!X68)
A69: ORD10068 | B69: C006 | C69: P201 | D69: 46267 | E69: 14/02/2026 | F69: =TRIM(PROPER(Sales_Data!F69)) -> Sneha Joshi | G69: Female | H69: 27/08/1979 | I69: Hyderabad | J69: =PROPER(Sales_Data!J69) -> South | K69: =PROPER(Sales_Data!K69) -> Home Appliances | L69: Mixer | M69: 7 | N69: 3500 | O69: 15 | P69: 20825 | Q69: 1 | R69: Cash | S69: Karan | T69: sneha.joshi@company.com | U69: 9106328582 | V69: Pending | X69: =PROPER(Sales_Data!X69)
A70: ORD10069 | B70: C010 | C70: P203 | D70: 14/12/2025 | E70: 19/12/2025 | F70: =TRIM(PROPER(Sales_Data!F70)) -> Pooja Shah | G70: Female | H70: 22/12/1976 | I70: Jaipur | J70: =PROPER(Sales_Data!J70) -> North | K70: =PROPER(Sales_Data!K70) -> Home Appliances | L70: Microwave | M70: 7 | N70: 8500 | O70: 20 | P70: 47600 | Q70: 4 | R70: NetBanking | S70: Neha | T70: pooja.shah@company.com | U70: 9264401015 | V70: Completed | X70: =PROPER(Sales_Data!X70)
A71: ORD10070 | B71: C008 | C71: P101 | D71: 45842 | E71: 10/04/2025 | F71: =TRIM(PROPER(Sales_Data!F71)) -> Kavya Nair | G71: Female | H71: 05/02/2000 | I71: Bengaluru | J71: =PROPER(Sales_Data!J71) -> South | K71: =PROPER(Sales_Data!K71) -> Electronics | L71: Laptop | M71: 16 | N71: 55000 | O71: 10 | P71: 792000 | Q71: 1 | R71: Card | S71: Aisha | T71: kavya.nair@company.com | U71: 9959237375 | V71: Completed | X71: =PROPER(Sales_Data!X71)
A72: ORD10071 | B72: C004 | C72: P104 | D72: 24/12/2025 | E72: 03/01/2026 | F72: =TRIM(PROPER(Sales_Data!F72)) -> Anita Gupta | G72: Female | H72: 24/02/1987 | I72: Mumbai | J72: =PROPER(Sales_Data!J72) -> West | K72: =PROPER(Sales_Data!K72) -> Electronics | L72: Monitor | M72: 2 | N72: 12000 | O72: 20 | P72: 19200 | Q72: 1 | R72: Cash | S72: Karan | T72: Anita.gupta@company.com | U72: 9561836580 | V72: Pending | X72: =PROPER(Sales_Data!X72)
A73: ORD10072 | B73: C003 | C73: P303 | D73: 30/08/2025 | E73: 05/09/2025 | F73: =TRIM(PROPER(Sales_Data!F73)) -> Rohit Singh | G73: Male | H73: 24/07/1984 | I73: Bengaluru | J73: =PROPER(Sales_Data!J73) -> South | K73: =PROPER(Sales_Data!K73) -> Stationery | L73: Marker | M73: 4 | N73: 45 | O73: 5 | P73: 171 | Q73: 1 | R73: Card | S73: Rahul | T73: rohit.singh@company.com | U73: 9512666401 | V73: Pending | X73: =PROPER(Sales_Data!X73)
A74: ORD10073 | B74: C008 | C74: P103 | D74: 13/12/2025 | E74: 23/12/2025 | F74: =TRIM(PROPER(Sales_Data!F74)) -> Kavya Nair | G74: Female | H74: 22/09/1981 | I74: Jaipur | J74: =PROPER(Sales_Data!J74) -> North | K74: =PROPER(Sales_Data!K74) -> Electronics | L74: Keyboard | M74: 1 | N74: 1200 | O74: 5 | P74: 1140 | Q74: 3 | R74: UPI | S74: Aisha | T74: kavya.nair@company.com | U74: 9808988530 | V74: Cancelled | X74: =PROPER(Sales_Data!X74)
A75: ORD10074 | B75: C010 | C75: P202 | D75: 46114 | E75: 16/02/2026 | F75: =TRIM(PROPER(Sales_Data!F75)) -> Pooja Shah | G75: Female | H75: 20/06/1980 | J75: =PROPER(Sales_Data!J75) -> South | K75: =PROPER(Sales_Data!K75) -> Home Appliances | L75: Iron | M75: 1 | N75: 2200 | O75: 15 | P75: 1870 | Q75: 4 | R75: Card | S75: Aisha | T75: pooja.shah@company.com | U75: 9286410494 | V75: Completed | X75: =PROPER(Sales_Data!X75)
A76: ORD10075 | B76: C003 | C76: P103 | D76: 26/01/2026 | E76: 28/01/2026 | F76: =TRIM(PROPER(Sales_Data!F76)) -> Rohit Singh | G76: Male | H76: 02/11/1982 | I76: Pune | J76: =PROPER(Sales_Data!J76) -> West | K76: =PROPER(Sales_Data!K76) -> Electronics | L76: Keyboard | M76: 3 | N76: 1200 | O76: 10 | P76: 3240 | Q76: 5 | R76: Cash | S76: Rahul | T76: rohit.singh@company.com | U76: 9311555196 | V76: Completed | X76: =PROPER(Sales_Data!X76)
A77: ORD10076 | B77: C008 | C77: P201 | D77: 27/06/2025 | E77: 07/07/2025 | F77: =TRIM(PROPER(Sales_Data!F77)) -> Kavya Nair | G77: Female | H77: 10/01/1980 | I77: Bengaluru | J77: =PROPER(Sales_Data!J77) -> South | K77: =PROPER(Sales_Data!K77) -> Home Appliances | L77: Mixer | M77: 10 | N77: 3500 | O77: 20 | P77: 28000 | Q77: 5 | R77: Card | S77: Ritika | T77: kavya.nair@company.com | U77: 9101810266 | V77: Completed | X77: =PROPER(Sales_Data!X77)
A78: ORD10077 | B78: C007 | C78: P102 | D78: 17/03/2026 | E78: 19/03/2026 | F78: =TRIM(PROPER(Sales_Data!F78)) -> Arjun Rao | G78: Male | H78: 27/04/1981 | I78: Delhi | J78: =PROPER(Sales_Data!J78) -> North | K78: =PROPER(Sales_Data!K78) -> Electronics | L78: Mouse | M78: 18 | N78: 700 | O78: 5 | P78: 11970 | Q78: 3 | R78: Card | S78: Neha | T78: arjun.rao@company.com | U78: 9464556593 | V78: Cancelled | X78: =PROPER(Sales_Data!X78)
A79: ORD10078 | B79: C005 | C79: P102 | D79: 45906 | E79: 18/06/2025 | F79: =TRIM(PROPER(Sales_Data!F79)) -> Vikas Mehta | G79: Male | H79: 12/03/1985 | I79: Bengaluru | J79: =PROPER(Sales_Data!J79) -> South | K79: =PROPER(Sales_Data!K79) -> Electronics | L79: Mouse | M79: 12 | N79: 700 | O79: 15 | P79: 7140 | Q79: 2 | R79: UPI | S79: Rahul | T79: vikas.mehta@company.com | U79: 9338278358 | V79: Completed | X79: =PROPER(Sales_Data!X79)
A80: ORD10079 | B80: C009 | C80: P103 | D80: 15/11/2025 | E80: 16/11/2025 | F80: =TRIM(PROPER(Sales_Data!F80)) -> Mohit Verma | G80: Male | H80: 15/03/1999 | I80: Mumbai | J80: =PROPER(Sales_Data!J80) -> West | K80: =PROPER(Sales_Data!K80) -> Electronics | L80: Keyboard | M80: 8 | N80: 1200 | O80: 0 | P80: 9600 | Q80: 4 | R80: Card | S80: Rahul | T80: mohit.verma@company.com | U80: 9621410770 | V80: Pending | X80: =PROPER(Sales_Data!X80)
A81: ORD10080 | B81: C003 | C81: P301 | D81: 45819 | E81: 10/11/2025 | F81: =TRIM(PROPER(Sales_Data!F81)) -> Rohit Singh | G81: Male | H81: 07/07/1983 | I81: Pune | J81: =PROPER(Sales_Data!J81) -> West | K81: =PROPER(Sales_Data!K81) -> Stationery | L81: Notebook | M81: 2 | N81: 60 | O81: 0 | P81: 120 | Q81: 2 | R81: UPI | S81: Rahul | T81: rohit.singh@company.com | U81: 9981333189 | V81: Completed | X81: =PROPER(Sales_Data!X81)
A82: ORD10081 | B82: C001 | C82: P303 | D82: 45658 | E82: 07/01/2025 | F82: =TRIM(PROPER(Sales_Data!F82)) -> Amit Sharma | G82: Male | H82: 06/03/1989 | I82: Pune | J82: =PROPER(Sales_Data!J82) -> West | K82: =PROPER(Sales_Data!K82) -> Stationery | L82: Marker | M82: 10 | N82: 45 | O82: 15 | P82: 382.5 | Q82: 3 | R82: NetBanking | S82: Ritika | T82: amit.sharma@company.com | U82: 9723450355 | V82: Cancelled | X82: =PROPER(Sales_Data!X82)
A83: ORD10082 | B83: C005 | C83: P201 | D83: 25/04/2026 | E83: 03/05/2026 | F83: =TRIM(PROPER(Sales_Data!F83)) -> Vikas Mehta | G83: Male | H83: 20/06/1982 | I83: Kolkata | J83: =PROPER(Sales_Data!J83) -> East | K83: =PROPER(Sales_Data!K83) -> Home Appliances | L83: Mixer | M83: 12 | N83: 3500 | O83: 5 | P83: 39900 | Q83: 3 | R83: NetBanking | S83: Aisha | T83: vikas.mehta@company.com | U83: 9886243907 | V83: Pending | X83: =PROPER(Sales_Data!X83)
A84: ORD10083 | B84: C003 | C84: P301 | D84: 19/09/2025 | E84: 27/09/2025 | F84: =TRIM(PROPER(Sales_Data!F84)) -> Rohit Singh | G84: Male | H84: 23/06/2001 | I84: Mumbai | J84: =PROPER(Sales_Data!J84) -> West | K84: =PROPER(Sales_Data!K84) -> Stationery | L84: Notebook | M84: 2 | N84: 60 | O84: 15 | P84: 102 | Q84: 1 | R84: UPI | S84: Neha | T84: rohit.singh@company.com | U84: 9473931904 | V84: Completed | X84: =PROPER(Sales_Data!X84)
A85: ORD10084 | B85: C003 | C85: P103 | D85: 18/03/2025 | E85: 21/03/2025 | F85: =TRIM(PROPER(Sales_Data!F85)) -> Rohit Singh | G85: Male | H85: 19/07/1983 | I85: Hyderabad | J85: =PROPER(Sales_Data!J85) -> South | K85: =PROPER(Sales_Data!K85) -> Electronics | L85: Keyboard | M85: 18 | N85: 1200 | O85: 15 | P85: 18360 | Q85: 3 | R85: Card | S85: Neha | T85: rohit.singh@company.com | U85: 9287159610 | V85: Pending | X85: =PROPER(Sales_Data!X85)
A86: ORD10085 | B86: C008 | C86: P104 | D86: 30/10/2025 | E86: 31/10/2025 | F86: =TRIM(PROPER(Sales_Data!F86)) -> Kavya Nair | G86: Female | H86: 24/03/1993 | I86: Mumbai | J86: =PROPER(Sales_Data!J86) -> West | K86: =PROPER(Sales_Data!K86) -> Electronics | L86: Monitor | M86: 18 | N86: 12000 | O86: 15 | P86: 183600 | Q86: 2 | R86: Cash | S86: Rahul | T86: kavya.nair@company.com | U86: 9876513858 | V86: Completed | X86: =PROPER(Sales_Data!X86)
A87: ORD10086 | B87: C007 | C87: P302 | D87: 31/10/2025 | E87: 11/11/2025 | F87: =TRIM(PROPER(Sales_Data!F87)) -> Arjun Rao | G87: Male | H87: 10/05/1995 | I87: Ahmedabad | J87: =PROPER(Sales_Data!J87) -> West | K87: =PROPER(Sales_Data!K87) -> Stationery | L87: Pen | M87: 7 | N87: 20 | O87: 0 | P87: 140 | Q87: 2 | R87: Card | S87: Ritika | T87: arjun.rao@company.com | U87: 9237400853 | V87: Cancelled | X87: =PROPER(Sales_Data!X87)
A88: ORD10087 | B88: C006 | C88: P201 | D88: 45934 | E88: 18/04/2025 | F88: =TRIM(PROPER(Sales_Data!F88)) -> Sneha Joshi | G88: Female | H88: 15/02/2001 | I88: Pune | J88: =PROPER(Sales_Data!J88) -> West | K88: =PROPER(Sales_Data!K88) -> Home Appliances | L88: Mixer | M88: 20 | N88: 3500 | O88: 20 | P88: 56000 | Q88: 4 | R88: Card | S88: Neha | T88: sneha.joshi@company.com | U88: 9599597595 | V88: Pending | X88: =PROPER(Sales_Data!X88)
A89: ORD10088 | B89: C002 | C89: P203 | D89: 16/03/2026 | E89: 26/03/2026 | F89: =TRIM(PROPER(Sales_Data!F89)) -> Priya Patel | G89: Female | H89: 14/08/1999 | I89: Ahmedabad | J89: =PROPER(Sales_Data!J89) -> West | K89: =PROPER(Sales_Data!K89) -> Home Appliances | L89: Microwave | M89: 8 | N89: 8500 | O89: 20 | P89: 54400 | Q89: 3 | R89: Card | S89: Neha | T89: priya.patel@company.com | U89: 9230007509 | V89: Pending | X89: =PROPER(Sales_Data!X89)
A90: ORD10089 | B90: C001 | C90: P104 | D90: 15/09/2025 | E90: 24/09/2025 | F90: =TRIM(PROPER(Sales_Data!F90)) -> Amit Sharma | G90: Male | H90: 20/03/2002 | I90: Ahmedabad | J90: =PROPER(Sales_Data!J90) -> North | K90: =PROPER(Sales_Data!K90) -> Electronics | L90: Monitor | M90: 6 | N90: 12000 | O90: 5 | P90: 68400 | Q90: 4 | R90: NetBanking | S90: Ritika | T90: amit.sharma@company.com | U90: 9823428025 | V90: Completed | X90: =PROPER(Sales_Data!X90)
A91: ORD10090 | B91: C008 | C91: P203 | D91: 46329 | E91: 19/03/2026 | F91: =TRIM(PROPER(Sales_Data!F91)) -> Kavya Nair | G91: Female | H91: 13/06/1992 | I91: Pune | J91: =PROPER(Sales_Data!J91) -> West | K91: =PROPER(Sales_Data!K91) -> Home Appliances | L91: Microwave | M91: 15 | N91: 8500 | O91: 0 | P91: 127500 | Q91: 4 | R91: NetBanking | S91: Ritika | T91: kavya.nair@company.com | U91: 9505048912 | V91: Cancelled | X91: =PROPER(Sales_Data!X91)
A92: ORD10091 | B92: C010 | C92: P103 | D92: 20/08/2025 | E92: 23/08/2025 | F92: =TRIM(PROPER(Sales_Data!F92)) -> Pooja Shah | G92: Female | H92: 18/06/1996 | I92: Jaipur | J92: =PROPER(Sales_Data!J92) -> North | K92: =PROPER(Sales_Data!K92) -> Electronics | L92: Keyboard | M92: 5 | N92: 1200 | O92: 15 | P92: 5100 | Q92: 1 | R92: NetBanking | S92: Ritika | T92: pooja.shah@company.com | U92: 9508068393 | V92: Cancelled | X92: =PROPER(Sales_Data!X92)
A93: ORD10092 | B93: C010 | C93: P302 | D93: 13/08/2025 | E93: 14/08/2025 | F93: =TRIM(PROPER(Sales_Data!F93)) -> Pooja Shah | G93: Female | H93: 08/11/1982 | I93: Hyderabad | J93: =PROPER(Sales_Data!J93) -> South | K93: =PROPER(Sales_Data!K93) -> Stationery | L93: Pen | M93: 4 | N93: 20 | O93: 0 | P93: 80 | Q93: 4 | R93: NetBanking | S93: Rahul | T93: pooja.shah@company.com | U93: 9785807771 | V93: Completed | X93: =PROPER(Sales_Data!X93)
A94: ORD10093 | B94: C008 | C94: P302 | D94: 16/03/2025 | E94: 20/03/2025 | F94: =TRIM(PROPER(Sales_Data!F94)) -> Kavya Nair | G94: Female | H94: 25/06/1984 | I94: Bengaluru | J94: =PROPER(Sales_Data!J94) -> South | K94: =PROPER(Sales_Data!K94) -> Stationery | L94: Pen | M94: 10 | N94: 20 | O94: 0 | P94: 200 | Q94: 3 | R94: Cash | S94: Karan | T94: kavya.nair@company.com | U94: 9215250979 | V94: Pending | X94: =PROPER(Sales_Data!X94)
A95: ORD10094 | B95: C004 | C95: P202 | D95: 45756 | E95: 10/09/2025 | F95: =TRIM(PROPER(Sales_Data!F95)) -> Anita Gupta | G95: Female | H95: 21/06/1994 | I95: Delhi | J95: =PROPER(Sales_Data!J95) -> North | K95: =PROPER(Sales_Data!K95) -> Home Appliances | L95: Iron | M95: 18 | N95: 2200 | O95: 10 | P95: 35640 | Q95: 3 | R95: Cash | S95: Ritika | T95: anita.gupta@company.com | U95: 9845884906 | V95: Cancelled | X95: =PROPER(Sales_Data!X95)
A96: ORD10095 | B96: C001 | C96: P201 | D96: 45995 | E96: 15/04/2025 | F96: =TRIM(PROPER(Sales_Data!F96)) -> Amit Sharma | G96: Male | H96: 17/10/1990 | I96: Delhi | J96: =PROPER(Sales_Data!J96) -> North | K96: =PROPER(Sales_Data!K96) -> Home Appliances | L96: Mixer | M96: 7 | N96: 3500 | O96: 15 | P96: 20825 | Q96: 3 | R96: NetBanking | S96: Rahul | T96: amit.sharma@company.com | U96: 9393097397 | V96: Completed | X96: =PROPER(Sales_Data!X96)
A97: ORD10096 | B97: C002 | C97: P203 | D97: 46117 | E97: 07/05/2026 | F97: =TRIM(PROPER(Sales_Data!F97)) -> Priya Patel | G97: Female | H97: 28/01/1987 | I97: Kolkata | J97: =PROPER(Sales_Data!J97) -> East | K97: =PROPER(Sales_Data!K97) -> Home Appliances | L97: Microwave | M97: 19 | N97: 8500 | O97: 15 | P97: 137275 | Q97: 4 | R97: Card | S97: Karan | T97: priya.patel@company.com | U97: 9958032109 | V97: Pending | X97: =PROPER(Sales_Data!X97)
A98: ORD10097 | B98: C006 | C98: P104 | D98: 18/01/2026 | E98: 27/01/2026 | F98: =TRIM(PROPER(Sales_Data!F98)) -> Sneha Joshi | G98: Female | H98: 21/09/1983 | I98: Ahmedabad | J98: =PROPER(Sales_Data!J98) -> West | K98: =PROPER(Sales_Data!K98) -> Electronics | L98: Monitor | M98: 13 | N98: 12000 | O98: 15 | P98: 132600 | Q98: 4 | R98: Cash | S98: Rahul | T98: sneha.joshi@company.com | U98: 9755082957 | V98: Completed | X98: =PROPER(Sales_Data!X98)
A99: ORD10098 | B99: C001 | C99: P302 | D99: 14/03/2026 | E99: 24/03/2026 | F99: =TRIM(PROPER(Sales_Data!F99)) -> Amit Sharma | G99: Male | H99: 04/04/1989 | I99: Pune | J99: =PROPER(Sales_Data!J99) -> West | K99: =PROPER(Sales_Data!K99) -> Stationery | L99: Pen | M99: 7 | N99: 20 | O99: 0 | P99: 140 | Q99: 1 | R99: Card | S99: Karan | T99: amit.sharma@company.com | U99: 9872235856 | V99: Cancelled | X99: =PROPER(Sales_Data!X99)
A100: ORD10099 | B100: C004 | C100: P102 | D100: 45905 | E100: 11/05/2025 | F100: =TRIM(PROPER(Sales_Data!F100)) -> Anita Gupta | G100: Female | H100: 25/09/1987 | I100: Delhi | J100: =PROPER(Sales_Data!J100) -> North | K100: =PROPER(Sales_Data!K100) -> Electronics | L100: Mouse | M100: 5 | N100: 700 | O100: 15 | P100: 999999 | Q100: 4 | R100: Card | S100: Ritika | T100: anita.gupta@company.com | U100: 9335138816 | V100: Pending | X100: =PROPER(Sales_Data!X100)
...

Sheet Sales Dashboard (Q10)
G7: Total Sales | I7: Total Orders | K7: Average sales
G8: 33932012 | I8: 497 | K8: 68273.667

Sheet Priliminary analysis (rough)
A1: Order_ID | B1: Customer_ID | C1: Product_ID | D1: Order_Date | E1: Delivery_Date | F1: Customer_Name | G1: Gender | H1: DOB | I1: City | J1: Region | K1: Category | L1: Product_Name | M1: Quantity | N1: Unit_Price | O1: Discount_% | P1: Sales | Q1: Rating | R1: Payment_Mode | S1: Salesperson | T1: Email | U1: Phone | V1: Order_Status
A2: ORD10001 | B2: C008 | C2: P202 | D2: 45918 | E2: 22/09/2025 | F2: =TRIM(PROPER(Sales_Data!F2)) -> Kavya Nair | G2: Female | H2: 01/08/1976 | I2: Hyderabad | J2: =PROPER(Sales_Data!J2) -> South | K2: =PROPER(Sales_Data!K2) -> Home Appliances | L2: Iron | M2: 4 | N2: 2200 | O2: 10 | P2: 7920 | Q2: 4 | R2: Cash | S2: Ritika | T2: KAvya.nair@company.com | U2: 9431429797 | V2: Completed
A3: ORD10002 | B3: C008 | C3: P104 | D3: 45774 | E3: 04/05/2025 | F3: =TRIM(PROPER(Sales_Data!F3)) -> Kavya Nair | G3: Female | H3: 16/10/2000 | I3: Delhi | J3: =PROPER(Sales_Data!J3) -> North | K3: =PROPER(Sales_Data!K3) -> Electronics | L3: Monitor | M3: 17 | N3: 12000 | O3: 10 | P3: 183600 | Q3: 1 | R3: NetBanking | S3: Rahul | T3: kavya.nair@company.com | U3: 9129865339 | V3: Completed
A4: ORD10003 | B4: C010 | C4: P101 | D4: 45903 | E4: 14/09/2025 | F4: =TRIM(PROPER(Sales_Data!F4)) -> Pooja Shah | G4: Female | H4: 16/09/1994 | I4: Bengaluru | J4: =PROPER(Sales_Data!J4) -> South | K4: =PROPER(Sales_Data!K4) -> Electronics | L4: Laptop | M4: 5 | N4: 55000 | O4: 5 | P4: 261250 | Q4: 3 | R4: NetBanking | S4: Aisha | T4: pooja.shah@company.com | U4: 9380975626 | V4: Pending | X4: Row Labels | Y4: Sum of Sales | AA4: Row Labels | AB4: Sum of Sales | AD4: Row Labels | AE4: Sum of Sales
A5: ORD10002 | B5: C008 | C5: P202 | D5: 46102 | E5: 02/04/2026 | F5: =TRIM(PROPER(Sales_Data!F5)) -> Kavya Nair | G5: Female | H5: 07/03/2004 | I5: Bengaluru | J5: =PROPER(Sales_Data!J5) -> South | K5: =PROPER(Sales_Data!K5) -> Home Appliances | L5: Iron | M5: 5 | N5: 2200 | O5: 5 | P5: 10450 | Q5: 5 | R5: NetBanking | S5: Aisha | T5: kavya.nair@company.com | U5: 9600261125 | V5: Cancelled | X5: East | Y5: 4041922 | AA5: Electronics | AB5: 26999534 | AD5: 45658 | AE5: 15012.5
A6: ORD10005 | B6: C009 | C6: P103 | D6: 45927 | E6: 07/10/2025 | F6: =TRIM(PROPER(Sales_Data!F6)) -> Mohit Verma | G6: Male | H6: 13/04/1976 | I6: Delhi | J6: =PROPER(Sales_Data!J6) -> North | K6: =PROPER(Sales_Data!K6) -> Electronics | L6: Keyboard | M6: 8 | N6: 1200 | O6: 5 | P6: 9120 | Q6: 2 | R6: Card | S6: Aisha | T6: mohit.verma@company.com | U6: 9724635978 | V6: Pending | X6: North | Y6: 9197852.5 | AA6: Home Appliances | AB6: 6816975 | AD6: 45660 | AE6: 47085
A7: ORD10006 | B7: C007 | C7: P202 | D7: 46026 | E7: 12/01/2026 | F7: =TRIM(PROPER(Sales_Data!F7)) -> Arjun Rao | G7: Male | H7: 07/02/1988 | I7: Hyderabad | J7: =PROPER(Sales_Data!J7) -> South | K7: =PROPER(Sales_Data!K7) -> Home Appliances | L7: Iron | M7: 4 | N7: 2200 | O7: 0 | P7: 8800 | Q7: 1 | R7: UPI | S7: Ritika | T7: arjun.rao@company.com | U7: 9780584905 | V7: Completed | X7: South | Y7: 7490491.5 | AA7: Stationery | AB7: 115503.5 | AD7: 45666 | AE7: 161500
A8: ORD10007 | B8: C008 | C8: P201 | D8: 45719 | E8: 25/02/2026 | F8: =TRIM(PROPER(Sales_Data!F8)) -> Kavya Nair | G8: Female | H8: 20/03/2003 | I8: Hyderabad | J8: =PROPER(Sales_Data!J8) -> South | K8: =PROPER(Sales_Data!K8) -> Home Appliances | L8: Mixer | M8: 2 | N8: 3500 | O8: 5 | P8: 6650 | Q8: 1 | R8: UPI | S8: Ritika | T8: kavya.nair@company.com | U8: 9958252176 | V8: Completed | X8: West | Y8: 13201746 | AA8: Grand Total | AB8: 33932012 | AD8: 45667 | AE8: 29700
A9: ORD10008 | B9: C002 | C9: P104 | D9: 45760 | E9: 19/04/2025 | F9: =TRIM(PROPER(Sales_Data!F9)) -> Priya Patel | G9: Female | H9: 07/03/1995 | I9: Mumbai | J9: =PROPER(Sales_Data!J9) -> West | K9: =PROPER(Sales_Data!K9) -> Electronics | L9: Monitor | M9: 14 | N9: 12000 | O9: 15 | P9: 142800 | Q9: 4 | R9: NetBanking | S9: Ritika | T9: priYa.patel@company.com | U9: 9705521654 | V9: Completed | X9: Grand Total | Y9: 33932012 | AD9: 45669 | AE9: 128
A10: ORD10009 | B10: C008 | C10: P104 | D10: 46053 | E10: 02/02/2026 | F10: =TRIM(PROPER(Sales_Data!F10)) -> Kavya Nair | G10: Female | H10: 06/04/1997 | I10: Pune | J10: =PROPER(Sales_Data!J10) -> West | K10: =PROPER(Sales_Data!K10) -> Electronics | L10: Monitor | M10: 4 | N10: 12000 | O10: 15 | P10: 40800 | Q10: 4 | R10: UPI | S10: Neha | T10: kavya.nair@company.com | U10: 9588041011 | V10: Completed | AD10: 45670 | AE10: 574930
A11: ORD10010 | B11: C002 | C11: P301 | D11: 45741 | E11: 27/03/2025 | F11: =TRIM(PROPER(Sales_Data!F11)) -> Priya Patel | G11: Female | H11: 07/01/1990 | I11: Mumbai | J11: =PROPER(Sales_Data!J11) -> West | K11: =PROPER(Sales_Data!K11) -> Stationery | L11: Notebook | M11: 6 | N11: 60 | O11: 0 | P11: 360 | Q11: 4 | R11: Card | S11: Neha | T11: PRiya.patel@company.com | U11: 9340540608 | V11: Completed | AD11: 45672 | AE11: 20505
